Workbook
Name adjusted_beta: '15_WACC'!$F$11
Name Capex_pct: '00_Assumptions'!$C$42
Name effective_tax_rate: '15_WACC'!$F$17
Name equity_risk_premium: '15_WACC'!$F$12
Name risk_free_rate: '15_WACC'!$F$10
Name Tax_Rate: '00_Assumptions'!$B$11
Name Terminal_Growth: '00_Assumptions'!$B$19
Name wacc_output: '15_WACC'!$F$19

Sheet 00_Assumptions
A1: NVIDIA Corporation — Model Assumptions
A2: Valuation Date: October 17, 2025 | Currency: USD millions | Model: L3 DCF (FCFF / Gordon Growth) | Forecast: FY2026–FY2030
A4: 1. WACC & COST OF CAPITAL
A5: Input | B5: Value | C5: FY2026F | D5: FY2027F | E5: FY2028F | F5: FY2029F | G5: FY2030F | H5: Rationale | I5: Source / Sheet
A6: Risk-free rate | B6: ='15_WACC'!F10 -> 0.0407 | H6: US 10-Year Treasury yield as of October 17, 2025. Represents the minimum risk-free return investors require. | I6: 15_WACC!F10 | US Treasury / FRED
A7: Equity risk premium (ERP) | B7: ='15_WACC'!F12 -> 0.05 | H7: Damodaran implied ERP for US market. Represents the additional return equity investors demand over the risk-free rate. | I7: 15_WACC!F12 | Damodaran (Jan 2025)
A8: Adjusted beta (Blume) | B8: ='15_WACC'!F11 -> 1.7728261 | H8: Blume-adjusted beta from regression of NVDA vs S&P 500 (60M weekly). Formula: β_adj = 0.67×β_raw + 0.33×1.0. Pulls from 14_Beta sheet. | I8: 15_WACC!F11 | Yahoo Finance / 14_Beta
A9: Cost of equity (CAPM) | B9: ='15_WACC'!F9 -> 0.12934131 | H9: CAPM: Ke = Rf + β × ERP. Represents the return required by equity investors based on systematic risk. | I9: 15_WACC!F9 (computed)
A10: Pre-tax cost of debt | B10: ='15_WACC'!F16 -> 0.028285274 | H10: Weighted average interest rate on NVIDIA's outstanding debt. Derived from interest expense / average debt balance. | I10: 15_WACC!F16 | 13_DebtSchedule
A11: Effective tax rate (FY2025) | B11: ='15_WACC'!F17 -> 0.13264942 | H11: FY2025 actual effective tax rate (Income Tax / Pre-Tax Income). Used as proxy for normalized rate in WACC. Forecast rates in Section 4. | I11: 15_WACC!F17 | 04a_Projection_IS!F71
A12: Weight of equity | B12: ='15_WACC'!F8 -> 0.99810266 | H12: Market cap / (Market cap + Total debt). NVIDIA is near debt-free — equity weight is 99.8%. | I12: 15_WACC!F8 (computed)
A13: Weight of debt | B13: ='15_WACC'!F15 -> 0.0018973367 | H13: Total debt / (Market cap + Total debt). Minimal debt — 0.19% weight. | I13: 15_WACC!F15 (computed)
A14: WACC ✦ | B14: ='15_WACC'!F19 -> 0.12914245 | H14: Weighted Average Cost of Capital: w_e × Ke + w_d × Kd × (1–t). Primary discount rate for FCF discounting. | I14: 15_WACC!F19 (computed) | named range: wacc_output
A16: 2. DCF ASSUMPTIONS
A17: Input | B17: Value | C17: FY2026F | D17: FY2027F | E17: FY2028F | F17: FY2029F | G17: FY2030F | H17: Rationale | I17: Source / Sheet
A18: Projection horizon | B18: 5 | H18: Standard 5-year explicit forecast period. NVIDIA's Data Center hyper-growth makes longer periods too speculative. | I18: Convention
A19: Terminal growth rate (g) ✦ | B19: ='05b_DCF'!C13 -> 0.04 | H19: Long-run nominal GDP growth (3%–5% range). Set at 4% — midpoint, consistent with NVIDIA's presence in structural AI growth market. | I19: 05b_DCF!C13 | named range: terminal_growth
A20: Terminal value method | B20: Gordon Growth | H20: Gordon Growth Model: TV = FCF₅ × (1+g) / (WACC–g). Single terminal value method used. Exit multiple (EV/EBITDA) recommended as cross-check — see 05b_DCF. | I20: 05b_DCF rows 24–28
A21: Diluted shares outstanding | B21: ='05b_DCF'!C20 -> 24300 | H21: Diluted share count as of Q2 FY2025 (in millions). Used to convert equity value to per-share price. | I21: 05b_DCF!C20 | NVIDIA 10-K
A22: Valuation date | B22: October 17, 2025 | H22: Date of valuation. Market price on this date: $183.22. Implied price: $109.26 (–39.9%). | I22: Manual input
A23: Market price (Oct 17, 2025) | B23: 183.22 | H23: NVIDIA closing price on the valuation date. Used as reference point for premium/discount calculation. | I23: 16_MarketData | Yahoo Finance
A25: 3. REVENUE GROWTH ASSUMPTIONS — Base Case ($ millions)
A26: Input | B26: Value | C26: FY2026F | D26: FY2027F | E26: FY2028F | F26: FY2029F | G26: FY2030F | H26: Rationale | I26: Source / Sheet
A27: Data Center revenue — YoY growth | B27: Primary driver | C27: 0.69 | D27: 0.42 | E27: 0.27 | F27: 0.16 | G27: 0.22 | H27: AI accelerator demand (H100/H200/B200). Dominant segment at 88% of FY2025 revenue. Base case reflects decelerating but still exceptional growth. | I27: 04a_Projection_IS rows 5–9
A28: Gaming revenue — YoY growth | B28: Stable/slow | C28: 0.05 | D28: 0.03 | E28: 0.02 | F28: 0.02 | G28: 0.03 | H28: PC GPU upgrade cycle. Mature segment. Base case assumes modest growth recovering post-crypto hangover. | I28: 04a_Projection_IS rows 11–15
A29: Professional Visualization — YoY growth | B29: Steady | C29: 0.06 | D29: 0.07 | E29: 0.05 | F29: 0.04 | G29: 0.05 | H29: Workstation GPU (Quadro/RTX). Stable enterprise market. Base case: low-to-mid single digit growth. | I29: 04a_Projection_IS rows 17–21
A30: Automotive — YoY growth | B30: High growth | C30: 0.45 | D30: 0.5 | E30: 0.35 | F30: 0.26 | G30: 0.35 | H30: DRIVE Orin/Thor autonomous vehicle platform. Long adoption cycle but accelerating. Base case is conservative vs upside (65%+). | I30: 04a_Projection_IS rows 23–27
A31: OEM & Other — YoY growth | B31: Minimal | C31: 0.02 | D31: 0.03 | E31: 0.02 | F31: 0.02 | G31: 0.03 | H31: Legacy OEM business declining/flat. Smallest segment. Immaterial to total revenue. | I31: 04a_Projection_IS rows 29–33
A32: Total revenue — YoY growth ✦ | B32: See forecast | C32: 0.62 | D32: 0.39 | E32: 0.26 | F32: 0.16 | G32: 0.21 | H32: Blended growth driven primarily by Data Center. FY2026 +62% reflects continued AI buildout; decelerates through FY2030. | I32: 04a_Projection_IS row 36 (computed)
A34: 4. MARGIN & COST ASSUMPTIONS
A35: Input | B35: Value | C35: FY2026F | D35: FY2027F | E35: FY2028F | F35: FY2029F | G35: FY2030F | H35: Rationale | I35: Source / Sheet
A36: Effective tax rate — Base case | B36: 15.0% (FY26) | C36: 0.15 | D36: 0.145 | E36: 0.145 | F36: 0.14 | G36: 0.14 | H36: Forecast ETR stepping up from FY2025 actual 13.3% towards normalized 14–15% range. Reflects global minimum tax (Pillar Two) impact. | I36: 04a_Projection_IS rows 62–65
A37: Cash & equivalents as % of revenue | B37: 28% (FY26) | C37: 0.28 | D37: 0.25 | E37: 0.23 | F37: 0.22 | G37: 0.21 | H37: NVIDIA holds significant net cash. Declining % of revenue as absolute revenue scales rapidly. Used to compute interest income. | I37: 04a_Projection_IS row 55
A38: Assumed yield on cash | B38: 3.45% (FY26) | C38: 0.0345 | D38: 0.0325 | E38: 0.0325 | F38: 0.031 | G38: 0.031 | H38: Interest earned on cash/short-term investments. Reflects prevailing money market / short-duration bond rates. Declining with rate cycle. | I38: 04a_Projection_IS row 57
A39: Other income (net) — Base case ($M) | B39: Flat $1,000M from FY27 (conservative; excl. equity gains) | C39: 1700 | D39: 1000 | E39: 1000 | F39: 1000 | G39: 1000
A40: 5. CAPITAL EXPENDITURE & DEPRECIATION
A41: Input | B41: Value | C41: FY2026F | D41: FY2027F | E41: FY2028F | F41: FY2029F | G41: FY2030F | H41: Rationale | I41: Source / Sheet
A42: CapEx as % of revenue ✦ | B42: 3.0% (FY26) | C42: 0.03 | D42: 0.032 | E42: 0.033 | F42: 0.03 | G42: 0.028 | H42: NVIDIA is asset-light (fabless). CapEx covers data centers, tools, and leasehold improvements. % slightly increasing as hyperscaler infrastructure spend rises. | I42: 12_FixedAssets row 7
A43: Average useful life (years) | B43: ='11_DA'!B3 -> 5 | H43: Weighted average depreciation period for fixed assets and capitalized costs. Used to compute annual D&A schedule in 11_DA sheet. | I43: 11_DA!B3
A44: D&A — FY2026F ($M) | B44: 3046 | C44: 3046 | D44: 4817 | E44: 6921 | F44: 9078 | G44: 11117 | H44: Projected D&A driven by CapEx schedule and 5-year useful life assumption. Adds back to EBIT to derive EBITDA and FCFF. | I44: 11_DA row 19 (computed)
A46: 6. DEBT, CASH & BALANCE SHEET
A47: Input | B47: Value | C47: FY2026F | D47: FY2027F | E47: FY2028F | F47: FY2029F | G47: FY2030F | H47: Rationale | I47: Source / Sheet
A48: Total debt (current) ($M) | B48: ='15_WACC'!F14 -> 8463 | H48: Long-term debt + current portion of leases as of FY2025. NVIDIA has minimal leverage. Net debt is negative (net cash position). | I48: 15_WACC!F14 | 02_Historical_BS
A49: Cash & equivalents ($M) | B49: 43210 | H49: FY2025 cash and short-term investments. Deducted from EV to derive equity value in DCF. | I49: 05b_DCF!C37 | 02_Historical_BS
A50: Net debt / (net cash) ($M) | B50: ='05b_DCF'!C38 -> -32940 | H50: Total Debt minus Cash. NVIDIA has a net cash position of ~$32.9B — this is subtracted from EV, increasing equity value. | I50: 05b_DCF!C38 (computed)
A52: Note: Values marked ✦ are key model drivers — changes here flow through the full P&L, FCFF schedule, and implied share price. All formula cells link live to source sheets. Sensitivity analysis: see 05b_DCF and 06_Sensitivity.

Sheet 01_Historical_IS
A1: Income Statement
B2: 2020 | C2: 2021 | D2: 2022 | E2: 2023 | F2: 2024 | G2: 2025 | J2: Common-Size Income Statements
A3: Revenue | B3: 10918 | C3: 16675 | D3: 26914 | E3: 26974 | F3: 60922 | G3: 130497 | K3: 2020 | L3: 2021 | M3: 2022 | N3: 2023 | O3: 2024 | P3: 2025
A4: Cost of revenue( COGS) | B4: 4150 | C4: 6279 | D4: 9439 | E4: 11618 | F4: 16621 | G4: 32639 | J4: Revenue | K4: 1 | L4: 1 | M4: 1 | N4: =E3/E3 -> 1 | O4: =F3/F3 -> 1 | P4: =G3/G3 -> 1
A5: Gross profit | B5: =B3-B4 -> 6768 | C5: =C3-C4 -> 10396 | D5: =D3-D4 -> 17475 | E5: 15356 | F5: 44301 | G5: 97858 | J5: Cost of revenue | K5: =B4/B3 -> 0.38010625 | L5: =C4/C3 -> 0.37655172 | M5: =D4/D3 -> 0.35070967 | N5: =E4/E3 -> 0.43071106 | O5: =F4/F3 -> 0.27282427 | P5: =G4/G3 -> 0.25011303
B6: 0 | C6: =(C5/B5)-1 -> 0.53605201 | D6: =(D5/C5)-1 -> 0.68093497 | E6: =(E5/D5)-1 -> -0.12125894 | F6: =(F5/E5)-1 -> 1.884931 | G6: =(G5/F5)-1 -> 1.2089343
A7: Operating expenses | J7: Gross profit | K7: =B5/B3 -> 0.61989375 | L7: =C5/C3 -> 0.62344828 | M7: =D5/D3 -> 0.64929033 | N7: =E5/E3 -> 0.56928894 | O7: =F5/F3 -> 0.72717573 | P7: =G5/G3 -> 0.74988697
A8: Research and development | B8: ='10_GrowthRates'!I6 -> 2829 | C8: ='10_GrowthRates'!J6 -> 3924 | D8: ='10_GrowthRates'!K6 -> 5268 | E8: 7339 | F8: 8675 | G8: 12914 | J8: Operating expenses
A9: Sales, general and administrative | B9: 1093 | C9: 1940 | D9: 2166 | E9: 2440 | F9: 2654 | G9: 3491 | J9: Research and development | K9: =B8/B3 -> 0.25911339 | L9: =C8/C3 -> 0.23532234 | M9: =D8/D3 -> 0.19573456 | N9: =E8/E3 -> 0.27207681 | O9: =F8/F3 -> 0.14239519 | P9: =G8/G3 -> 0.098960129
A10: Acquisition termination cost | B10: 0 | C10: 0 | D10: 0 | E10: 1353 | F10: 0 | G10: 0 | J10: Sales, general and administrative | K10: =B9/B3 -> 0.10010991 | L10: =C9/C3 -> 0.11634183 | M10: =D9/D3 -> 0.080478561 | N10: =E9/E3 -> 0.090457478 | O10: =F9/F3 -> 0.043563901 | P10: =G9/G3 -> 0.026751573
A11: Total operating expenses | B11: 3922 | C11: 5864 | D11: 7434 | E11: 11132 | F11: 11329 | G11: 16405 | J11: Acquisition termination cost | K11: =IFERROR((B10/B3), " _ ") -> 0 | L11: =IFERROR((C10/C3), " _ ") -> 0 | M11: =IFERROR((D10/D3), " _ ") -> 0 | N11: =IFERROR(E10/E3,"_") -> 0.050159413 | O11: =IFERROR(F10/F3,"_") -> 0 | P11: =IFERROR(G10/G3,"_") -> 0
A12: EBIT (Operating income ) | B12: =B5-B11 -> 2846 | C12: =C5-C11 -> 4532 | D12: =D5-D11 -> 10041 | E12: 4224 | F12: 32972 | G12: 81453 | J12: Total operating expenses | K12: =B11/B3 -> 0.3592233 | L12: =C11/C3 -> 0.35166417 | M12: =D11/D3 -> 0.27621312 | N12: =E11/E3 -> 0.41269371 | O12: =F11/F3 -> 0.1859591 | P12: =G11/G3 -> 0.1257117
A13: D&A | B13: 381 | C13: 1098 | D13: 1174 | E13: ='03_Historical_CF'!B7 -> 1544 | F13: ='03_Historical_CF'!C7 -> 1508 | G13: ='03_Historical_CF'!D7 -> 1864 | J13: EBIT (Operating income) | K13: =B12/B3 -> 0.26067045 | L13: =C12/C3 -> 0.27178411 | M13: =D12/D3 -> 0.37307721 | N13: =E12/E3 -> 0.15659524 | O13: =F12/F3 -> 0.54121664 | P13: =G12/G3 -> 0.62417527
A14: EBITDA | B14: =B12+B13 -> 3227 | C14: =C12+C13 -> 5630 | D14: =D12+D13 -> 11215 | E14: =E12+E13 -> 5768 | F14: =F12+F13 -> 34480 | G14: =G12+G13 -> 83317 | J14: =A13 -> D&A | K14: =B13/B3 -> 0.034896501 | L14: =C13/C3 -> 0.065847076 | M14: =D13/D3 -> 0.043620421 | N14: =E13/E3 -> 0.057240305 | O14: =F13/F3 -> 0.024752963 | P14: =G13/G3 -> 0.014283853
A15: Interest income | B15: 178 | C15: 57 | D15: 29 | E15: 267 | F15: 866 | G15: 1786 | J15: =A14 -> EBITDA | K15: =B14/B3 -> 0.29556695 | L15: =C14/C3 -> 0.33763118 | M15: =D14/D3 -> 0.41669763 | N15: =E14/E3 -> 0.21383555 | O15: =F14/F3 -> 0.5659696 | P15: =G14/G3 -> 0.63845912
A16: Interest expense | B16: -52 | C16: -184 | D16: -236 | E16: -262 | F16: -257 | G16: -247 | J16: Interest income | K16: =B15/B3 -> 0.016303352 | L16: =C15/C3 -> 0.0034182909 | M16: =D15/D3 -> 0.0010775061 | N16: =E15/E3 -> 0.0098984207 | O16: =F15/F3 -> 0.014214898 | P16: =G15/G3 -> 0.013686138
A17: Other, net | B17: -2 | C17: 4 | D17: 107 | E17: -48 | F17: 237 | G17: 1034 | J17: Interest expense | K17: =B16/B3 -> -0.0047627771 | L17: =C16/C3 -> -0.011034483 | M17: =D16/D3 -> -0.0087686706 | N17: =E16/E3 -> -0.009713057 | O17: =F16/F3 -> -0.0042185089 | P17: =G16/G3 -> -0.0018927638
A18: Other income (expense), net | B18: =SUM(B15:B17) -> 124 | C18: =SUM(C15:C17) -> -123 | D18: =SUM(D15:D17) -> -100 | E18: -43 | F18: 846 | G18: 2573 | J18: Other, net | K18: =B17/B3 -> -0.00018318373 | L18: =C17/C3 -> 0.00023988006 | M18: =D17/D3 -> 0.0039756261 | N18: =E17/E3 -> -0.0017794914 | O18: =F17/F3 -> 0.0038902203 | P18: =G17/G3 -> 0.0079235538
A19: EBT (Income before income tax) | B19: 2970 | C19: 4409 | D19: 9941 | E19: 4181 | F19: 33818 | G19: 84026 | J19: Other income (expense), net | K19: =B18/B3 -> 0.011357391 | L19: =C18/C3 -> -0.0073763118 | M19: =D18/D3 -> -0.0037155384 | N19: =E18/E3 -> -0.0015941277 | O19: =F18/F3 -> 0.013886609 | P19: =G18/G3 -> 0.019716928
A20: Income tax expense (benefit) | B20: 174 | C20: 77 | D20: 189 | E20: -187 | F20: 4058 | G20: 11146 | J20: EBT (Income before income tax ) | K20: =B19/B3 -> 0.27202784 | L20: =C19/C3 -> 0.2644078 | M20: =D19/D3 -> 0.36936167 | N20: =E19/E3 -> 0.15500111 | O20: =F19/F3 -> 0.55510325 | P20: =G19/G3 -> 0.6438922
A21: Net income | B21: 2796 | C21: 4332 | D21: 9752 | E21: 4368 | F21: 29760 | G21: 72880 | J21: Income tax expense (benefit) | K21: =B20/B3 -> 0.015936985 | L21: =C20/C3 -> 0.0046176912 | M21: =D20/D3 -> 0.0070223675 | N21: =E20/E3 -> -0.0069326018 | O21: =F20/F3 -> 0.066609763 | P21: =G20/G3 -> 0.085411925
J22: Net income | K22: =B21/B3 -> 0.25609086 | L22: =C21/C3 -> 0.2597901 | M22: =D21/D3 -> 0.3623393 | N22: =E21/E3 -> 0.16193371 | O22: =F21/F3 -> 0.48849348 | P22: =G21/G3 -> 0.55848027
B25: 2025 | C25: 2024 | D25: 2023
A26: Data Center | B26: 115186 | C26: 47525 | D26: 15005
A27: Compute | B27: 102196 | C27: 38950 | D27: 11317
A28: Networking | B28: 12990 | C28: 8575 | D28: 3688
A29: Gaming | B29: 11350 | C29: 10447 | D29: 9067
A30: Professional Visualization | B30: 1878 | C30: 1553 | D30: 1544
A31: Automotive | B31: 1694 | C31: 1091 | D31: 903
A32: OEM and Other | B32: 389 | C32: 306 | D32: 455
A33: Total revenue | B33: 130497 | C33: 60922 | D33: 26974
B36: 2025 | C36: 2024 | D36: 2023
A37: United States | B37: 61257 | C37: 26966 | D37: 8292
A38: Singapore | B38: 23684 | C38: 6831 | D38: 2288
A39: Taiwan | B39: 20573 | C39: 13405 | D39: 6986
A40: China (including Hong Kong) | B40: 17108 | C40: 10306 | D40: 5785
A41: Other | B41: 7875 | C41: 3414 | D41: 3623
A42: Total revenue | B42: 130497 | C42: 60922 | D42: 26974
E50: Growth rate | G50: 2025 | H50: 2024 | I50: 2023
E51: United States | G51: =B37/$B$42 -> 0.46941309 | H51: =C37/$C$42 -> 0.44263156 | I51: =D37/$D$42 -> 0.30740713
E52: Singapore | G52: =B38/$B$42 -> 0.18149076 | H52: =C38/$C$42 -> 0.11212698 | I52: =D38/$D$42 -> 0.084822422
E53: Taiwan | G53: =B39/$B$42 -> 0.15765113 | H53: =C39/$C$42 -> 0.22003546 | I53: =D39/$D$42 -> 0.25899014
E54: China (including Hong Kong) | G54: =B40/$B$42 -> 0.1310988 | H54: =C40/$C$42 -> 0.16916713 | I54: =D40/$D$42 -> 0.21446578
E55: Other | G55: =B41/$B$42 -> 0.060346215 | H55: =C41/$C$42 -> 0.056038869 | I55: =D41/$D$42 -> 0.13431453
A61: Growth rate | B61: 2025 | C61: 2024 | D61: 2023 | E61: 2022 | F61: 2021 | G61: 2020
A62: Revenue | B62: =(G3/F3)-1 -> 1.1420341 | C62: =(F3/E3)-1 -> 1.2585453 | D62: =(E3/D3)-1 -> 0.002229323 | E62: =(D3/C3)-1 -> 0.61403298 | F62: =(C3/B3)-1 -> 0.52729438 | G62: 0
A63: Cost of revenue( COGS) | B63: =(G4/F4)-1 -> 0.96372059 | C63: =(F4/E4)-1 -> 0.43062489 | D63: =(E4/D4)-1 -> 0.23085073 | E63: =(D4/C4)-1 -> 0.50326485 | F63: =(C4/B4)-1 -> 0.51301205 | G63: 0
A64: Total operating expenses | B64: =(G11/F11)-1 -> 0.44805367 | C64: =(F11/E11)-1 -> 0.01769673 | D64: =(E11/D11)-1 -> 0.49744418 | E64: =(D11/C11)-1 -> 0.26773533 | F64: =(C11/B11)-1 -> 0.49515553 | G64: 0

Sheet 02_Historical_BS
A1: Balance Sheet | J1: Common-size Balance Sheet
A2: Fiscal Year | B2: 2021 | C2: 2022 | D2: 2023 | E2: 2024 | F2: 2025 | J2: Fiscal Year | K2: 2025 | L2: 2024 | M2: 2023 | N2: 2022 | O2: 2021
A3: Period Ending | B3: Jan '21 Jan 31, 2021 | C3: Jan '22 Jan 30, 2022 | D3: Jan '23 Jan 29, 2023 | E3: Jan '24 Jan 28, 2024 | F3: Jan '25 Jan 26, 2025 | J3: Period Ending | K3: Jan '25 Jan 26, 2025 | L3: Jan '24 Jan 28, 2024 | M3: Jan '23 Jan 29, 2023 | N3: Jan '22 Jan 30, 2022 | O3: Jan '21 Jan 31, 2021
A4: Cash & Equivalents | B4: 847 | C4: 1990 | D4: 3389 | E4: 7280 | F4: 8589 | J4: Cash & Equivalents | K4: =F4/F$17 -> 0.076961676 | L4: =E4/E$17 -> 0.11075949 | M4: =D4/D$17 -> 0.082293235 | N4: =C4/C$17 -> 0.04503587 | O4: =B4/B$17 -> 0.029418916
A5: Short-Term Investments | B5: 10714 | C5: 19218 | D5: 9907 | E5: 18704 | F5: 34621 | J5: Short-Term Investments | K5: =F5/F$17 -> 0.31022123 | L5: =E5/E$17 -> 0.2845667 | M5: =D5/D$17 -> 0.24056627 | N5: =C5/C$17 -> 0.4349243 | O5: =B5/B$17 -> 0.37213018
A6: Cash & Short-Term Investments | B6: 11561 | C6: 21208 | D6: 13296 | E6: 25984 | F6: 43210 | J6: Cash & Short-Term Investments | K6: =F6/F$17 -> 0.38718291 | L6: =E6/E$17 -> 0.39532619 | M6: =D6/D$17 -> 0.3228595 | N6: =C6/C$17 -> 0.47996017 | O6: =B6/B$17 -> 0.4015491
A7: Receivables | B7: 2429 | C7: 4650 | D7: 3827 | E7: 9999 | F7: 23065 | J7: Receivables | K7: =F7/F$17 -> 0.20667378 | L7: =E7/E$17 -> 0.15212695 | M7: =D7/D$17 -> 0.09292895 | N7: =C7/C$17 -> 0.10523457 | O7: =B7/B$17 -> 0.084366642
A8: Inventory | B8: 1826 | C8: 2605 | D8: 5159 | E8: 5282 | F8: 10080 | J8: Inventory | K8: =F8/F$17 -> 0.090321771 | L8: =E8/E$17 -> 0.08036149 | M8: =D8/D$17 -> 0.12527318 | N8: =C8/C$17 -> 0.058953991 | O8: =B8/B$17 -> 0.063422597
A9: Prepaid Expenses | B9: 239 | C9: 366 | D9: 791 | E9: 3080 | F9: 3771 | J9: Prepaid Expenses | K9: =F9/F$17 -> 0.03379002 | L9: =E9/E$17 -> 0.046859786 | M9: =D9/D$17 -> 0.019207421 | N9: =C9/C$17 -> 0.0082829792 | O9: =B9/B$17 -> 0.0083012052
A10: Total Current Assets | B10: 16055 | C10: 28829 | D10: 23073 | E10: 44345 | F10: 80126 | J10: Total Current Assets | K10: =F10/F$17 -> 0.71796848 | L10: =E10/E$17 -> 0.67467442 | M10: =D10/D$17 -> 0.56026905 | N10: =C10/C$17 -> 0.65243171 | O10: =B10/B$17 -> 0.55763954
A11: Property, Plant & Equipment | B11: 2149 | C11: 2778 | D11: 3807 | E11: 3914 | F11: 6283 | J11: Property, Plant & Equipment | K11: =F11/F$17 -> 0.056298779 | L11: =E11/E$17 -> 0.059548442 | M11: =D11/D$17 -> 0.0924433 | N11: =C11/C$17 -> 0.06286917 | O11: =B11/B$17 -> 0.074641381
A12: Operating lease assets | B12: 707 | C12: 829 | D12: 1038 | E12: 1346 | F12: 1793 | J12: Long-Term Investments | K12: =F12/F$17 -> 0.016066164 | L12: =E12/E$17 -> 0.020478335 | M12: =D12/D$17 -> 0.025205187 | N12: =C12/C$17 -> 0.018761174 | O12: =B12/B$17 -> 0.024556285
A13: Goodwill | B13: 4193 | C13: 4349 | D13: 4372 | E13: 4430 | F13: 5188 | J13: Goodwill | K13: =F13/F$17 -> 0.046487039 | L13: =E13/E$17 -> 0.067398978 | M13: =D13/D$17 -> 0.10616289 | N13: =C13/C$17 -> 0.098422613 | O13: =B13/B$17 -> 0.14563579
A14: Intangible Assets, net | B14: 2737 | C14: 2339 | D14: 1676 | E14: 1112 | F14: 807 | J14: Other Intangible Assets | K14: =F14/F$17 -> 0.007231118 | L14: =E14/E$17 -> 0.016918208 | M14: =D14/D$17 -> 0.040697392 | N14: =C14/C$17 -> 0.052934121 | O14: =B14/B$17 -> 0.09506443
A15: Long-Term Deferred Tax Assets | B15: 806 | C15: 1222 | D15: 3396 | E15: 6081 | F15: 10979 | J15: Long-Term Deferred Tax Assets | K15: =F15/F$17 -> 0.098377255 | L15: =E15/E$17 -> 0.092517648 | M15: =D15/D$17 -> 0.082463212 | N15: =C15/C$17 -> 0.027655193 | O15: =B15/B$17 -> 0.02799486
... A17: Total Assets | B17: 28791 | C17: 44187 | D17: 41182 | E17: 65728 | F17: 111601 | J17: Total Assets | K17: =F17/F$17 -> 1 | L17: =E17/E$17 -> 1 | M17: =D17/D$17 -> 1 | N17: =C17/C$17 -> 1 | O17: =B17/B$17 -> 1
A18: Accounts Payable | B18: 1149 | C18: 1783 | D18: 1193 | E18: 2699 | F18: 6310 | J18: Accounts Payable | K18: =IFERROR(F18/F$31,"-") -> 0.19551342 | L18: =IFERROR(E18/E$31,"-") -> 0.11863736 | M18: =IFERROR(D18/D$31,"-") -> 0.062522929 | N18: =IFERROR(C18/C$31,"-") -> 0.10145092 | O18: =IFERROR(B18/B$31,"-") -> 0.096570852
A19: Accrued Expenses | B19: 297 | C19: 409 | D19: 530 | E19: 675 | F19: 848 | J19: Accrued Expenses | K19: =IFERROR(F19/F$31,"-") -> 0.02627502 | L19: =IFERROR(E19/E$31,"-") -> 0.02967033 | M19: =IFERROR(D19/D$31,"-") -> 0.027776322 | N19: =IFERROR(C19/C$31,"-") -> 0.023271693 | O19: =IFERROR(B19/B$31,"-") -> 0.024962179
A20: Short-Term Debt | B20: 999 | C20: 0 | D20: 1250 | E20: 1250 | F20: 0 | J20: Current Portion of Long-Term Debt | K20: =IFERROR(F20/F$31,"-") -> 0 | L20: =IFERROR(E20/E$31,"-") -> 0.054945055 | M20: =IFERROR(D20/D$31,"-") -> 0.065510193 | N20: =IFERROR(C20/C$31,"-") -> 0 | O20: =IFERROR(B20/B$31,"-") -> 0.083963691
A21: Current Portion of Leases | B21: 0 | C21: 144 | D21: 176 | E21: 228 | F21: 288 | J21: Current Portion of Leases | K21: =IFERROR(F21/F$31,"-") -> 0.0089235917 | L21: =IFERROR(E21/E$31,"-") -> 0.010021978 | M21: =IFERROR(D21/D$31,"-") -> 0.0092238352 | N21: =IFERROR(C21/C$31,"-") -> 0.0081934566 | O21: =IFERROR(B21/B$31,"-") -> 0
A22: Current Income Taxes Payable | B22: 0 | C22: 132 | D22: 467 | E22: 296 | F22: 881 | J22: Current Income Taxes Payable | K22: =IFERROR(F22/F$31,"-") -> 0.027297515 | L22: =IFERROR(E22/E$31,"-") -> 0.013010989 | M22: =IFERROR(D22/D$31,"-") -> 0.024474608 | N22: =IFERROR(C22/C$31,"-") -> 0.0075106686 | O22: =IFERROR(B22/B$31,"-") -> 0
A23: Current Unearned Revenue | B23: 288 | C23: 300 | D23: 354 | E23: 764 | F23: 837 | J23: Current Unearned Revenue | K23: =IFERROR(F23/F$31,"-") -> 0.025934189 | L23: =IFERROR(E23/E$31,"-") -> 0.033582418 | M23: =IFERROR(D23/D$31,"-") -> 0.018552487 | N23: =IFERROR(C23/C$31,"-") -> 0.017069701 | O23: =IFERROR(B23/B$31,"-") -> 0.024205749
A24: Other Current Liabilities | B24: 1192 | C24: 1567 | D24: 2593 | E24: 4719 | F24: 8883 | J24: Other Current Liabilities | K24: =IFERROR(F24/F$31,"-") -> 0.27523703 | L24: =IFERROR(E24/E$31,"-") -> 0.20742857 | M24: =IFERROR(D24/D$31,"-") -> 0.13589435 | N24: =IFERROR(C24/C$31,"-") -> 0.08916074 | O24: =IFERROR(B24/B$31,"-") -> 0.10018491
A25: Total Current Liabilities | B25: 3925 | C25: 4335 | D25: 6563 | E25: 10631 | F25: 18047 | J25: Total Current Liabilities | K25: =IFERROR(F25/F$31,"-") -> 0.55918076 | L25: =IFERROR(E25/E$31,"-") -> 0.4672967 | M25: =IFERROR(D25/D$31,"-") -> 0.34395472 | N25: =IFERROR(C25/C$31,"-") -> 0.24665718 | O25: =IFERROR(B25/B$31,"-") -> 0.32988738
A26: Long-Term Debt | B26: 5964 | C26: 10946 | D26: 9703 | E26: 8459 | F26: 8463 | J26: Long-Term Debt | K26: =IFERROR(F26/F$31,"-") -> 0.26222346 | L26: =IFERROR(E26/E$31,"-") -> 0.37182418 | M26: =IFERROR(D26/D$31,"-") -> 0.50851633 | N26: =IFERROR(C26/C$31,"-") -> 0.6228165 | O26: =IFERROR(B26/B$31,"-") -> 0.50126072
A27: Long-Term Leases | B27: 634 | C27: 741 | D27: 902 | E27: 1119 | F27: 1519 | J27: Long-Term Leases | K27: =IFERROR(F27/F$31,"-") -> 0.04706575 | L27: =IFERROR(E27/E$31,"-") -> 0.049186813 | M27: =IFERROR(D27/D$31,"-") -> 0.047272156 | N27: =IFERROR(C27/C$31,"-") -> 0.042162162 | O27: =IFERROR(B27/B$31,"-") -> 0.053286267
A28: Long-Term Unearned Revenue | B28: 163 | C28: 202 | D28: 218 | E28: 573 | F28: 976 | J28: Long-Term Unearned Revenue | K28: =IFERROR(F28/F$31,"-") -> 0.030241061 | L28: =IFERROR(E28/E$31,"-") -> 0.025186813 | M28: =IFERROR(D28/D$31,"-") -> 0.011424978 | N28: =IFERROR(C28/C$31,"-") -> 0.011493599 | O28: =IFERROR(B28/B$31,"-") -> 0.013699781
A29: Long-Term Deferred Tax Liabilities | B29: 241 | C29: 245 | D29: 247 | E29: 462 | F29: 886 | J29: Long-Term Deferred Tax Liabilities | K29: =IFERROR(F29/F$31,"-") -> 0.027452438 | L29: =IFERROR(E29/E$31,"-") -> 0.020307692 | M29: =IFERROR(D29/D$31,"-") -> 0.012944814 | N29: =IFERROR(C29/C$31,"-") -> 0.013940256 | O29: =IFERROR(B29/B$31,"-") -> 0.020255505
... A31: Total Liabilities | B31: 11898 | C31: 17575 | D31: 19081 | E31: 22750 | F31: 32274 | J31: Total Liabilities | K31: =IFERROR(F31/F$31,"-") -> 1 | L31: =IFERROR(E31/E$31,"-") -> 1 | M31: =IFERROR(D31/D$31,"-") -> 1 | N31: =IFERROR(C31/C$31,"-") -> 1 | O31: =IFERROR(B31/B$31,"-") -> 1
A32: Common Stock | B32: 3 | C32: 3 | D32: 2 | E32: 25 | F32: 24 | J32: Common Stock | K32: =IFERROR(F32/F$37,"-") -> 0.00030254516 | L32: =IFERROR(E32/E$37,"-") -> 0.00058169296 | M32: =IFERROR(D32/D$37,"-") -> 9.0493643e-05 | N32: =IFERROR(C32/C$37,"-") -> 0.0001127311 | O32: =IFERROR(B32/B$37,"-") -> 0.00017758835
A33: Additional Paid-In Capital | B33: 8719 | C33: 10385 | D33: 11971 | E33: 13109 | F33: 11237 | J33: Additional Paid-In Capital | K33: =IFERROR(F33/F$37,"-") -> 0.14165417 | L33: =IFERROR(E33/E$37,"-") -> 0.30501652 | M33: =IFERROR(D33/D$37,"-") -> 0.5416497 | N33: =IFERROR(C33/C$37,"-") -> 0.39023749 | O33: =IFERROR(B33/B$37,"-") -> 0.51613094
A34: Retained Earnings | B34: 18908 | C34: 16235 | D34: 10171 | E34: 29817 | F34: 68038 | J34: Retained Earnings | K34: =IFERROR(F34/F$37,"-") -> 0.85769032 | L34: =IFERROR(E34/E$37,"-") -> 0.69377356 | M34: =IFERROR(D34/D$37,"-") -> 0.46020542 | N34: =IFERROR(C34/C$37,"-") -> 0.61006313 | O34: =IFERROR(B34/B$37,"-") -> 1.1192802
A35: Treasury Stock | B35: -10756 | C35: 0 | D35: 0 | E35: 0 | F35: 0 | J35: Treasury Stock | K35: =IFERROR(F35/F$37,"-") -> 0 | L35: =IFERROR(E35/E$37,"-") -> 0 | M35: =IFERROR(D35/D$37,"-") -> 0 | N35: =IFERROR(C35/C$37,"-") -> 0 | O35: =IFERROR(B35/B$37,"-") -> -0.63671343
A36: Comprehensive Income & Other | B36: 19 | C36: -11 | D36: -43 | E36: 27 | F36: 28 | J36: Comprehensive Income & Other | K36: =IFERROR(F36/F$37,"-") -> 0.00035296935 | L36: =IFERROR(E36/E$37,"-") -> 0.0006282284 | M36: =IFERROR(D36/D$37,"-") -> -0.0019456133 | N36: =IFERROR(C36/C$37,"-") -> -0.00041334736 | O36: =IFERROR(B36/B$37,"-") -> 0.0011247262
A37: Shareholders' Equity | B37: 16893 | C37: 26612 | D37: 22101 | E37: 42978 | F37: 79327 | J37: Shareholders' Equity | K37: =IFERROR(F37/F$37,"-") -> 1 | L37: =IFERROR(E37/E$37,"-") -> 1 | M37: =IFERROR(D37/D$37,"-") -> 1 | N37: =IFERROR(C37/C$37,"-") -> 1 | O37: =IFERROR(B37/B$37,"-") -> 1
A38: Total Liabilities & Equity | B38: 28791 | C38: 44187 | D38: 41182 | E38: 65728 | F38: 111601
A40: Check | B40: =F38-F17 -> 0 | C40: =E38-E17 -> 0 | D40: =D38-D17 -> 0 | E40: =C38-C17 -> 0 | F40: =B38-B17 -> 0

Sheet 03_Historical_CF
A1: Cash Flow statement | I1: Cash Flow statement | T1: NVIDIA Corporation Common-Size Cash Flow Statement: Percentage of Inflows/Outflows Approach
B2: 2023 | C2: 2024 | D2: 2025 | J2: 2023 | K2: 2024 | L2: 2025
A3: Cash flows from operating activities: | I3: Cash flows from operating activities: | L3: % of net revenue
A4: Net income | B4: 4368 | C4: 29760 | D4: 72880 | I4: Net income | J4: =IFERROR(B4/'01_Historical_IS'!E$3," _ ") -> 0.16193371 | K4: =IFERROR(C4/'01_Historical_IS'!F$3," _ ") -> 0.48849348 | L4: =IFERROR(D4/'01_Historical_IS'!G$3," _ ") -> 0.55848027
A5: Adjustments to reconcile net income to net cash provided by operating activities: | I5: Adjustments to reconcile net income to net cash provided by operating activities: | J5: =IFERROR(B5/'01_Historical_IS'!E$3," _ ") -> 0 | K5: =IFERROR(C5/'01_Historical_IS'!F$3," _ ") -> 0 | L5: =IFERROR(D5/'01_Historical_IS'!$G$3," _ ") -> 0
A6: Stock-based compensation expense | B6: 2709 | C6: 3549 | D6: 4737 | I6: Stock-based compensation expense | J6: =IFERROR(B6/'01_Historical_IS'!E$3," _ ") -> 0.10043004 | K6: =IFERROR(C6/'01_Historical_IS'!F$3," _ ") -> 0.058254818 | L6: =IFERROR(D6/'01_Historical_IS'!$G$3," _ ") -> 0.036299685
A7: Depreciation and amortization | B7: 1544 | C7: 1508 | D7: 1864 | I7: Depreciation and amortization | J7: =IFERROR(B7/'01_Historical_IS'!E$3," _ ") -> 0.057240305 | K7: =IFERROR(C7/'01_Historical_IS'!F$3," _ ") -> 0.024752963 | L7: =IFERROR(D7/'01_Historical_IS'!$G$3," _ ") -> 0.014283853
A8: Deferred income taxes | B8: -2164 | C8: -2489 | D8: -4477 | I8: Deferred income taxes | J8: =IFERROR(B8/'01_Historical_IS'!E$3," _ ") -> -0.080225402 | K8: =IFERROR(C8/'01_Historical_IS'!F$3," _ ") -> -0.04085552 | L8: =IFERROR(D8/'01_Historical_IS'!$G$3," _ ") -> -0.034307302
A9: (Gains) losses on non-marketable equity securities and publicly-held equity securities, net | B9: 45 | C9: -238 | D9: -1030 | I9: (Gains) losses on non-marketable equity securities and publicly-held equity securities, net | J9: =IFERROR(B9/'01_Historical_IS'!E$3," _ ") -> 0.0016682732 | K9: =IFERROR(C9/'01_Historical_IS'!F$3," _ ") -> -0.0039066347 | L9: =IFERROR(D9/'01_Historical_IS'!$G$3," _ ") -> -0.0078929018
A10: Acquisition termination cost | B10: 1353 | C10: 0 | D10: 0 | I10: Acquisition termination cost | J10: =IFERROR(B10/'01_Historical_IS'!E$3," _ ") -> 0.050159413 | K10: =IFERROR(C10/'01_Historical_IS'!F$3," _ ") -> 0 | L10: =IFERROR(D10/'01_Historical_IS'!$G$3," _ ") -> 0
A11: Other | B11: -7 | C11: -278 | D11: -502 | I11: Other | J11: =IFERROR(B11/'01_Historical_IS'!E$3," _ ") -> -0.00025950916 | K11: =IFERROR(C11/'01_Historical_IS'!F$3," _ ") -> -0.004563212 | L11: =IFERROR(D11/'01_Historical_IS'!$G$3," _ ") -> -0.0038468317
A12: Changes in operating assets and liabilities, net of acquisitions: | I12: Changes in operating assets and liabilities, net of acquisitions: | J12: =IFERROR(B12/'01_Historical_IS'!E$3," _ ") -> 0 | K12: =IFERROR(C12/'01_Historical_IS'!F$3," _ ") -> 0 | L12: =IFERROR(D12/'01_Historical_IS'!$G$3," _ ") -> 0
A13: Accounts receivable | B13: 822 | C13: -6172 | D13: -13063 | I13: Accounts receivable | J13: =IFERROR(B13/'01_Historical_IS'!E$3," _ ") -> 0.03047379 | K13: =IFERROR(C13/'01_Historical_IS'!F$3," _ ") -> -0.10130987 | L13: =IFERROR(D13/'01_Historical_IS'!$G$3," _ ") -> -0.10010192
A14: Inventories | B14: -2554 | C14: -98 | D14: -4781 | I14: Inventories | J14: =IFERROR(B14/'01_Historical_IS'!E$3," _ ") -> -0.09468377 | K14: =IFERROR(C14/'01_Historical_IS'!F$3," _ ") -> -0.0016086143 | L14: =IFERROR(D14/'01_Historical_IS'!$G$3," _ ") -> -0.036636858
A15: Prepaid expenses and other assets | B15: -1517 | C15: -1522 | D15: -395 | I15: Prepaid expenses and other assets | J15: =IFERROR(B15/'01_Historical_IS'!E$3," _ ") -> -0.056239342 | K15: =IFERROR(C15/'01_Historical_IS'!F$3," _ ") -> -0.024982765 | L15: =IFERROR(D15/'01_Historical_IS'!$G$3," _ ") -> -0.0030268895
A16: Accounts payable | B16: -551 | C16: 1531 | D16: 3357 | I16: Accounts payable | J16: =IFERROR(B16/'01_Historical_IS'!E$3," _ ") -> -0.020427078 | K16: =IFERROR(C16/'01_Historical_IS'!F$3," _ ") -> 0.025130495 | L16: =IFERROR(D16/'01_Historical_IS'!$G$3," _ ") -> 0.025724729
A17: Accrued and other current liabilities | B17: 1341 | C17: 2025 | D17: 4278 | I17: Accrued and other current liabilities | J17: =IFERROR(B17/'01_Historical_IS'!E$3," _ ") -> 0.04971454 | K17: =IFERROR(C17/'01_Historical_IS'!F$3," _ ") -> 0.033239224 | L17: =IFERROR(D17/'01_Historical_IS'!$G$3," _ ") -> 0.032782363
A18: Other long-term liabilities | B18: 252 | C18: 514 | D18: 1221 | I18: Other long-term liabilities | J18: =IFERROR(B18/'01_Historical_IS'!E$3," _ ") -> 0.0093423297 | K18: =IFERROR(C18/'01_Historical_IS'!F$3," _ ") -> 0.0084370178 | L18: =IFERROR(D18/'01_Historical_IS'!$G$3," _ ") -> 0.0093565369
A19: Net cash provided by operating activities | B19: 5641 | C19: 28090 | D19: 64089 | I19: Net cash provided by operating activities | J19: =IFERROR(B19/'01_Historical_IS'!E$3," _ ") -> 0.20912731 | K19: =IFERROR(C19/'01_Historical_IS'!F$3," _ ") -> 0.46108138 | L19: =IFERROR(D19/'01_Historical_IS'!$G$3," _ ") -> 0.49111474
A20: Cash flows from investing activities: | I20: Cash flows from investing activities: | J20: =IFERROR(B20/'01_Historical_IS'!E$3," _ ") -> 0 | K20: =IFERROR(C20/'01_Historical_IS'!F$3," _ ") -> 0 | L20: =IFERROR(D20/'01_Historical_IS'!$G$3," _ ") -> 0
A21: Proceeds from maturities of marketable securities | B21: 19425 | C21: 9732 | D21: 11195 | I21: Proceeds from maturities of marketable securities | J21: =IFERROR(B21/'01_Historical_IS'!E$3," _ ") -> 0.72013791 | K21: =IFERROR(C21/'01_Historical_IS'!F$3," _ ") -> 0.15974525 | L21: =IFERROR(D21/'01_Historical_IS'!$G$3," _ ") -> 0.085787413
A22: Proceeds from sales of marketable securities | B22: 1806 | C22: 50 | D22: 495 | I22: Proceeds from sales of marketable securities | J22: =IFERROR(B22/'01_Historical_IS'!E$3," _ ") -> 0.066953362 | K22: =IFERROR(C22/'01_Historical_IS'!F$3," _ ") -> 0.00082072158 | L22: =IFERROR(D22/'01_Historical_IS'!$G$3," _ ") -> 0.0037931906
A23: Proceeds from sales of non-marketable equity securities | B23: 8 | C23: 1 | D23: 171 | I23: Proceeds from sales of non-marketable equity securities | J23: =IFERROR(B23/'01_Historical_IS'!E$3," _ ") -> 0.00029658189 | K23: =IFERROR(C23/'01_Historical_IS'!F$3," _ ") -> 1.6414432e-05 | L23: =IFERROR(D23/'01_Historical_IS'!$G$3," _ ") -> 0.001310375
A24: Purchases of marketable securities | B24: -11897 | C24: -18211 | D24: -26575 | I24: Purchases of marketable securities | J24: =IFERROR(B24/'01_Historical_IS'!E$3," _ ") -> -0.44105435 | K24: =IFERROR(C24/'01_Historical_IS'!F$3," _ ") -> -0.29892321 | L24: =IFERROR(D24/'01_Historical_IS'!$G$3," _ ") -> -0.20364453
A25: Purchases related to property and equipment and intangible assets (capEX) | B25: -1833 | C25: -1069 | D25: -3236 | I25: Purchases related to property and equipment and intangible assets | J25: =IFERROR(B25/'01_Historical_IS'!E$3," _ ") -> -0.067954326 | K25: =IFERROR(C25/'01_Historical_IS'!F$3," _ ") -> -0.017547027 | L25: =IFERROR(D25/'01_Historical_IS'!$G$3," _ ") -> -0.024797505
A26: Purchases of non-marketable equity securities | B26: -85 | C26: -862 | D26: -1486 | I26: Purchases of non-marketable equity securities | J26: =IFERROR(B26/'01_Historical_IS'!E$3," _ ") -> -0.0031511826 | K26: =IFERROR(C26/'01_Historical_IS'!F$3," _ ") -> -0.01414924 | L26: =IFERROR(D26/'01_Historical_IS'!$G$3," _ ") -> -0.011387235
A27: Acquisitions, net of cash acquired | B27: -49 | C27: -83 | D27: -1007 | I27: Acquisitions, net of cash acquired | J27: =IFERROR(B27/'01_Historical_IS'!E$3," _ ") -> -0.0018165641 | K27: =IFERROR(C27/'01_Historical_IS'!F$3," _ ") -> -0.0013623978 | L27: =IFERROR(D27/'01_Historical_IS'!$G$3," _ ") -> -0.0077166525
A28: Other | B28: 0 | C28: -124 | D28: 22 | I28: Other | J28: =IFERROR(B28/'01_Historical_IS'!E$3," _ ") -> 0 | K28: =IFERROR(C28/'01_Historical_IS'!F$3," _ ") -> -0.0020353895 | L28: =IFERROR(D28/'01_Historical_IS'!$G$3," _ ") -> 0.00016858625
A29: Net cash provided by (used in) investing activities | B29: 7375 | C29: -10566 | D29: -20421 | I29: Net cash provided by (used in) investing activities | J29: =IFERROR(B29/'01_Historical_IS'!E$3," _ ") -> 0.27341143 | K29: =IFERROR(C29/'01_Historical_IS'!F$3," _ ") -> -0.17343488 | L29: =IFERROR(D29/'01_Historical_IS'!$G$3," _ ") -> -0.15648636
A30: Cash flows from financing activities: | I30: Cash flows from financing activities: | J30: =IFERROR(B30/'01_Historical_IS'!E$3," _ ") -> 0 | K30: =IFERROR(C30/'01_Historical_IS'!F$3," _ ") -> 0 | L30: =IFERROR(D30/'01_Historical_IS'!$G$3," _ ") -> 0
A31: Proceeds related to employee stock plans | B31: 355 | C31: 403 | D31: 490 | I31: Proceeds related to employee stock plans | J31: =IFERROR(B31/'01_Historical_IS'!E$3," _ ") -> 0.013160822 | K31: =IFERROR(C31/'01_Historical_IS'!F$3," _ ") -> 0.0066150159 | L31: =IFERROR(D31/'01_Historical_IS'!$G$3," _ ") -> 0.0037548756
A32: Payments related to repurchases of common stock (buyback) | B32: -10039 | C32: -9533 | D32: -33706 | I32: Payments related to repurchases of common stock | J32: =IFERROR(B32/'01_Historical_IS'!E$3," _ ") -> -0.3721732 | K32: =IFERROR(C32/'01_Historical_IS'!F$3," _ ") -> -0.15647878 | L32: =IFERROR(D32/'01_Historical_IS'!$G$3," _ ") -> -0.25828946
A33: Payments related to tax on restricted stock units | B33: -1475 | C33: -2783 | D33: -6930 | I33: Payments related to tax on restricted stock units | J33: =IFERROR(B33/'01_Historical_IS'!E$3," _ ") -> -0.054682287 | K33: =IFERROR(C33/'01_Historical_IS'!F$3," _ ") -> -0.045681363 | L33: =IFERROR(D33/'01_Historical_IS'!$G$3," _ ") -> -0.053104669
A34: Repayment of debt | B34: 0 | C34: -1250 | D34: -1250 | I34: Repayment of debt | J34: =IFERROR(B34/'01_Historical_IS'!E$3," _ ") -> 0 | K34: =IFERROR(C34/'01_Historical_IS'!F$3," _ ") -> -0.020518039 | L34: =IFERROR(D34/'01_Historical_IS'!$G$3," _ ") -> -0.0095787643
A35: Dividends paid | B35: -398 | C35: -395 | D35: -834 | I35: Dividends paid | J35: =IFERROR(B35/'01_Historical_IS'!E$3," _ ") -> -0.014754949 | K35: =IFERROR(C35/'01_Historical_IS'!F$3," _ ") -> -0.0064837005 | L35: =IFERROR(D35/'01_Historical_IS'!$G$3," _ ") -> -0.0063909515
A36: Principal payments on property and equipment and intangible assets | B36: -58 | C36: -74 | D36: -129 | I36: Principal payments on property and equipment and intangible assets | J36: =IFERROR(B36/'01_Historical_IS'!E$3," _ ") -> -0.0021502187 | K36: =IFERROR(C36/'01_Historical_IS'!F$3," _ ") -> -0.0012146679 | L36: =IFERROR(D36/'01_Historical_IS'!$G$3," _ ") -> -0.00098852847
A37: Other | B37: -2 | C37: -1 | D37: 0 | I37: Other | J37: =IFERROR(B37/'01_Historical_IS'!E$3," _ ") -> -7.4145473e-05 | K37: =IFERROR(C37/'01_Historical_IS'!F$3," _ ") -> -1.6414432e-05 | L37: =IFERROR(D37/'01_Historical_IS'!$G$3," _ ") -> 0
A38: Net cash used in financing activities | B38: -11617 | C38: -13633 | D38: -42359 | I38: Net cash used in financing activities | J38: =IFERROR(B38/'01_Historical_IS'!E$3," _ ") -> -0.43067398 | K38: =IFERROR(C38/'01_Historical_IS'!F$3," _ ") -> -0.22377795 | L38: =IFERROR(D38/'01_Historical_IS'!$G$3," _ ") -> -0.3245975
A39: Change in cash and cash equivalents ( Net Cash Flow ) | B39: 1399 | C39: 3891 | D39: 1309 | I39: Change in cash and cash equivalents | J39: =IFERROR(B39/'01_Historical_IS'!E$3," _ ") -> 0.051864759 | K39: =IFERROR(C39/'01_Historical_IS'!F$3," _ ") -> 0.063868553 | L39: =IFERROR(D39/'01_Historical_IS'!$G$3," _ ") -> 0.010030882
A40: Cash and cash equivalents at beginning of period | B40: 1990 | C40: 3389 | D40: 7280 | I40: Cash and cash equivalents at beginning of period | J40: =IFERROR(B40/'01_Historical_IS'!E$3," _ ") -> 0.073774746 | K40: =IFERROR(C40/'01_Historical_IS'!F$3," _ ") -> 0.055628509 | L40: =IFERROR(D40/'01_Historical_IS'!$G$3," _ ") -> 0.055786723
A41: Cash and cash equivalents at end of period | B41: 3389 | C41: 7280 | D41: 8589 | I41: Cash and cash equivalents at end of period | J41: =IFERROR(B41/'01_Historical_IS'!E$3," _ ") -> 0.1256395 | K41: =IFERROR(C41/'01_Historical_IS'!F$3," _ ") -> 0.11949706 | L41: =IFERROR(D41/'01_Historical_IS'!$G$3," _ ") -> 0.065817605
A42: Supplemental disclosures of cash flow information: | I42: Supplemental disclosures of cash flow information: | J42: =IFERROR(B42/'01_Historical_IS'!E$3," _ ") -> 0 | K42: =IFERROR(C42/'01_Historical_IS'!F$3," _ ") -> 0 | L42: =IFERROR(D42/'01_Historical_IS'!$G$3," _ ") -> 0
A43: Cash paid for income taxes, net | B43: 1404 | C43: 6549 | D43: 15118 | I43: Cash paid for income taxes, net | J43: =IFERROR(B43/'01_Historical_IS'!E$3," _ ") -> 0.052050122 | K43: =IFERROR(C43/'01_Historical_IS'!F$3," _ ") -> 0.10749811 | L43: =IFERROR(D43/'01_Historical_IS'!$G$3," _ ") -> 0.11584941
A44: Cash paid for interest | B44: 254 | C44: 252 | D44: 246 | I44: Cash paid for interest | J44: =IFERROR(B44/'01_Historical_IS'!E$3," _ ") -> 0.0094164751 | K44: =IFERROR(C44/'01_Historical_IS'!F$3," _ ") -> 0.0041364368 | L44: =IFERROR(D44/'01_Historical_IS'!$G$3," _ ") -> 0.0018851008
A45: Accumulated Amortization | B45: 699 | C45: 614 | D45: 593 | J45: =IFERROR(B45/'01_Historical_IS'!E$3," _ ") -> 0.025913843 | K45: =IFERROR(C45/'01_Historical_IS'!F$3," _ ") -> 0.010078461 | L45: =IFERROR(D45/'01_Historical_IS'!$G$3," _ ") -> 0.0045441658
B48: 2020 | C48: 2021 | D48: 2022 | E48: 2023 | F48: 2024 | G48: 2025
A49: D&A | B49: 381 | C49: 1098 | D49: 1174 | E49: =B7 -> 1544 | F49: =C7 -> 1508 | G49: =D7 -> 1864
A50: Accumulated Amortization | B50: 25 | C50: 612 | D50: 563 | E50: =B45 -> 699 | F50: =C45 -> 614 | G50: =D45 -> 593
A51: Depriciation | B51: =B49-B50 -> 356 | C51: =C49-C50 -> 486 | D51: =D49-D50 -> 611 | E51: =E49-E50 -> 845 | F51: =F49-F50 -> 894 | G51: =G49-G50 -> 1271
A54: What are the major sources and uses of cash for NVIDIA?
B55: 2023 | C55: 2024 | D55: 2025
A56: Net cash provided by operating activities | B56: 5641 | C56: 28090 | D56: 64089
A57: Net cash provided by (used in) investing activities | B57: 7375 | C57: -10566 | D57: -20421
A58: Net cash used in financing activities | B58: -11617 | C58: -13633 | D58: -42359
A59: Increase in cash | B59: =B56+B57+B58 -> 1399 | C59: =C56+C57+C58 -> 3891 | D59: =D56+D57+D58 -> 1309
A65: FCFF for NVIDIA corporation | B65: 2023 | C65: 2024 | D65: 2025
A66: Net cash provided by operating activities | B66: 5641 | C66: 28090 | D66: 64089
A67: Tax rate | B67: ='04a_Projection_IS'!E96/'04a_Projection_IS'!E95 -> -0.044726142 | C67: ='04a_Projection_IS'!F96/'04a_Projection_IS'!F95 -> 0.11999527 | D67: ='04a_Projection_IS'!G96/'04a_Projection_IS'!G95 -> 0.13264942
A68: interest expense | B68: 262 | C68: 257 | D68: 247
A69: Cash paid for interest, net of tax | B69: =B68*(1-B67) -> 273.71825 | C69: =C68*(1-C67) -> 226.16122 | D69: =D68*(1-D67) -> 214.23559
A70: Capex | B70: =B25 -> -1833 | C70: =C25 -> -1069 | D70: =D25 -> -3236
A71: FCFF | B71: =B66+B69+B70 -> 4081.7182 | C71: =C66+C69+C70 -> 27247.161 | D71: =D66+D69+D70 -> 61067.236 | K71: =SUM(G13:G18) -> 0
A72: FCFF Growth | B72: 0 | C72: =(C71-B71)/B71 -> 5.6754145 | D72: =(D71-C71)/C71 -> 1.241233
B73: ='02_Historical_BS'!D12/'03_Historical_CF'!B71 -> 0.25430467 | C73: ='02_Historical_BS'!E12/'03_Historical_CF'!C71 -> 0.049399642 | D73: ='02_Historical_BS'!F12/'03_Historical_CF'!D71 -> 0.02936108
A76: FCFE for NVIDIA corporation | B76: 2023 | C76: 2024 | D76: 2025
A77: Operating cash flow | B77: 5641 | C77: 28090 | D77: 64089
A78: Capex | B78: =B70 -> -1833 | C78: =C70 -> -1069 | D78: =D70 -> -3236
A79: =A34 -> Repayment of debt | B79: =B34 -> 0 | C79: =C34 -> -1250 | D79: =D34 -> -1250
A80: FCFE | B80: =SUM(B77:B79) -> 3808 | C80: =SUM(C77:C79) -> 25771 | D80: =SUM(D77:D79) -> 59603
A81: FCFE Growth | B81: 0 | C81: =(C80-B80)/B80 -> 5.7675945 | D81: =(D80-C80)/C80 -> 1.3127935
A85: Cash Flow Ratios | B85: 2023 | C85: 2024 | D85: 2025
A86: Performance Ratios
A87: Cash flow to revenue | B87: =B$77/'01_Historical_IS'!E3 -> 0.20912731 | C87: =C$77/'01_Historical_IS'!F3 -> 0.46108138 | D87: =D$77/'01_Historical_IS'!G3 -> 0.49111474
A88: Cash return on assets | B88: =B$77/'02_Historical_BS'!D17 -> 0.13697732 | C88: =C$77/'02_Historical_BS'!E17 -> 0.42736733 | D88: =D$77/'02_Historical_BS'!F17 -> 0.57426905
A89: Cash return on equity | B89: =B$77/'02_Historical_BS'!D37 -> 0.25523732 | C89: =C$77/'02_Historical_BS'!E37 -> 0.65359021 | D89: =D$77/'02_Historical_BS'!F37 -> 0.80790903
A90: Cash flow per share
A91: Coverage Ratios
A92: Debt coverage | B92: =B$77/'02_Historical_BS'!D31 -> 0.2956344 | C92: =C$77/'02_Historical_BS'!E31 -> 1.2347253 | D92: =D$77/'02_Historical_BS'!F31 -> 1.985778
A93: Interest coverage | B93: =(B77+B44+B43)/B44 -> 28.73622 | C93: =(C77+C44+C43)/C44 -> 138.45635 | D93: =(D77+D44+D43)/D44 -> 322.97967
A94: Reinvestment | B94: =B77/-B78 -> 3.0774686 | C94: =C77/-C78 -> 26.276894 | D94: =D77/-D78 -> 19.805006
A95: Debt payment | B95: _ | C95: =C77/-C79 -> 22.472 | D95: =D77/-D79 -> 51.2712
A96: Dividend payment | B96: =B77/-B35 -> 14.173367 | C96: =C77/-C35 -> 71.113924 | D96: =D77/-D35 -> 76.845324
A203: Fiscal Year | C203: FY 2022 | D203: FY 2024
A204: Period Ending | C204: Jan '22 Jan 30, 2022 | D204: Jan '24 Jan 28, 2024
A205: Net Income | C205: 9752 | D205: 29760
A206: Depreciation & Amortization | C206: 1174 | D206: 1508
A207: Loss (Gain) From Sale of Investments | C207: -100 | D207: -238
A208: Stock-Based Compensation | C208: 2004 | D208: 3549
A209: Other Operating Activities | C209: -359 | D209: -2767
A210: Change in Accounts Receivable | C210: -2215 | D210: -6172
A211: Change in Inventory | C211: -774 | D211: -98
A212: Change in Accounts Payable | C212: 568 | D212: 1531
A213: Change in Other Net Operating Assets | C213: -942 | D213: 1017
A214: Operating Cash Flow | C214: 9108 | D214: 28090
A215: Operating Cash Flow Growth | C215: 0.5644 | D215: 3.9796
A216: Capital Expenditures | C216: -976 | D216: -1069
... A238: Change in Net Working Capital | C238: 1862 | D238: 4568

Sheet 04a_Projection_IS
A2: Revenue Growth Analysis | N2: Margin Analysis
A3: ($ in millions) | B3: 2021 | C3: 2022 | D3: 2023 | E3: 2024 | F3: 2025 | G3: 2026F | H3: 2027F | I3: 2028F | J3: 2029F | K3: 2030F | N3: ($ in millions) | O3: 2020 | P3: 2021 | Q3: 2022 | R3: 2023 | S3: 2024 | T3: 2025 | U3: 2026F | V3: 2027F | W3: 2028F | X3: 2029F | Y3: 2030F
A5: Data Center revenue | B5: 6696 | C5: 10613 | D5: 15005 | E5: 47525 | F5: 115186 | G5: =90805+50000+54000 -> 194805 | H5: =G5*(1+H7) -> 276623.1 | I5: =H5*(1+I7) -> 351311.34 | J5: =I5*(1+J7) -> 407521.15 | K5: =J5*(1+K7) -> 497175.8 | N5: Gross Margin, % | O5: ='01_Historical_IS'!B5/'01_Historical_IS'!B3 -> 0.61989375 | P5: ='01_Historical_IS'!C5/'01_Historical_IS'!C3 -> 0.62344828 | Q5: ='01_Historical_IS'!D5/'01_Historical_IS'!D3 -> 0.64929033 | R5: ='01_Historical_IS'!E5/'01_Historical_IS'!E3 -> 0.56928894 | S5: ='01_Historical_IS'!F5/'01_Historical_IS'!F3 -> 0.72717573 | T5: ='01_Historical_IS'!G5/'01_Historical_IS'!G3 -> 0.74988697
A6: Y/Y Growth rate in Data center revenue | C6: =(C5/B5)-1 -> 0.58497611 | D6: =(D5/C5)-1 -> 0.41383209 | E6: =(E5/D5)-1 -> 2.1672776 | F6: =(F5/E5)-1 -> 1.4236928 | N6: Base case | U6: =T5+2% -> 0.76988697 | V6: =U6+2% -> 0.78988697 | W6: =V6+2% -> 0.80988697 | X6: =W6+2% -> 0.82988697 | Y6: =X6+2% -> 0.84988697
A7: Base case | G7: =69% -> 0.69 | H7: 0.42 | I7: 0.27 | J7: 0.16 | K7: 0.22 | N7: Upside case | U7: =U6+5% -> 0.81988697 | V7: =V6+5% -> 0.83988697 | W7: =W6+5% -> 0.85988697 | X7: =X6+5% -> 0.87988697 | Y7: =Y6+5% -> 0.89988697
A8: Upside case | G8: 0.95 | H8: 0.55 | I8: 0.35 | J8: 0.22 | K8: 0.42 | N8: Downside case | U8: 0.66 | V8: 0.655 | W8: 0.65 | X8: 0.65 | Y8: 0.645
A9: Downside case | G9: 0.5 | H9: 0.12 | I9: 0.04 | J9: -0.05 | K9: 0.02
N10: R&D Margin, % | O10: ='01_Historical_IS'!B8/'01_Historical_IS'!B3 -> 0.25911339 | P10: ='01_Historical_IS'!C8/'01_Historical_IS'!C3 -> 0.23532234 | Q10: ='01_Historical_IS'!D8/'01_Historical_IS'!D3 -> 0.19573456 | R10: ='01_Historical_IS'!E8/'01_Historical_IS'!E3 -> 0.27207681 | S10: ='01_Historical_IS'!F8/'01_Historical_IS'!F3 -> 0.14239519 | T10: ='01_Historical_IS'!G8/'01_Historical_IS'!G3 -> 0.098960129
A11: Gaming revenue | B11: 7759 | C11: 12462 | D11: 9067 | E11: 10447 | F11: 11350 | G11: =F11*(1+G13) -> 11917.5 | H11: =G11*(1+H13) -> 12275.025 | I11: =H11*(1+I13) -> 12520.525 | J11: =I11*(1+J13) -> 12770.936 | K11: =J11*(1+K13) -> 13154.064 | N11: Base case | U11: 0.095 | V11: 0.093 | W11: 0.09 | X11: 0.088 | Y11: 0.085
A12: Y/Y Growth rate in Gaming revenue | C12: =(C11/B11)-1 -> 0.60613481 | D12: =(D11/C11)-1 -> -0.27242818 | E12: =(E11/D11)-1 -> 0.15220029 | F12: =(F11/E11)-1 -> 0.086436298 | N12: Upside case | U12: 0.088 | V12: 0.085 | W12: 0.083 | X12: 0.08 | Y12: 0.078
A13: Base case | G13: 0.05 | H13: 0.03 | I13: 0.02 | J13: 0.02 | K13: 0.03 | N13: Downside case | U13: 0.105 | V13: 0.11 | W13: 0.11 | X13: 0.105 | Y13: 0.1
A14: Upside case | G14: 0.15 | H14: 0.1 | I14: 0.08 | J14: 0.05 | K14: 0.07
A15: Downside case | G15: -0.05 | H15: -0.05 | I15: -0.04 | J15: -0.05 | K15: 0.02 | N15: SG&A Margin, % | O15: ='01_Historical_IS'!B9/'01_Historical_IS'!B3 -> 0.10010991 | P15: ='01_Historical_IS'!C9/'01_Historical_IS'!C3 -> 0.11634183 | Q15: ='01_Historical_IS'!D9/'01_Historical_IS'!D3 -> 0.080478561 | R15: ='01_Historical_IS'!E9/'01_Historical_IS'!E3 -> 0.090457478 | S15: ='01_Historical_IS'!F9/'01_Historical_IS'!F3 -> 0.043563901 | T15: ='01_Historical_IS'!G9/'01_Historical_IS'!G3 -> 0.026751573
N16: Base case | U16: 0.025 | V16: 0.024 | W16: 0.023 | X16: 0.022 | Y16: 0.022
A17: Professional Visualization revenue | B17: 1053 | C17: 2111 | D17: 1544 | E17: 1553 | F17: 1878 | G17: =F17*(1+G19) -> 1990.68 | H17: =G17*(1+H19) -> 2130.0276 | I17: =H17*(1+I19) -> 2236.529 | J17: =I17*(1+J19) -> 2325.9901 | K17: =J17*(1+K19) -> 2442.2896 | N17: Upside case | U17: 0.024 | V17: 0.022 | W17: 0.021 | X17: 0.02 | Y17: 0.02
A18: Y/Y Growth rate in Professional Visualization revenue | C18: =(C17/B17)-1 -> 1.0047483 | D18: =(D17/C17)-1 -> -0.26859308 | E18: =(E17/D17)-1 -> 0.0058290155 | F18: =(F17/E17)-1 -> 0.20927238 | N18: Downside case | U18: 0.028 | V18: 0.03 | W18: 0.031 | X18: 0.03 | Y18: 0.03
A19: Base case | G19: 0.06 | H19: 0.07 | I19: 0.05 | J19: 0.04 | K19: 0.05
A20: Upside case | G20: 0.15 | H20: 0.12 | I20: 0.1 | J20: 0.1 | K20: 0.11
A21: Downside case | G21: -0.02 | H21: 0 | I21: -0.03 | J21: -0.02 | K21: 0.02
A23: Automotive revenue | B23: 536 | C23: 566 | D23: 903 | E23: 1091 | F23: 1694 | G23: =F23*(1+G25) -> 2456.3 | H23: =G23*(1+H25) -> 3684.45 | I23: =H23*(1+I25) -> 4974.0075 | J23: =I23*(1+J25) -> 6267.2494 | K23: =J23*(1+K25) -> 8460.7868
A24: Y/Y Growth rate Automotive revenue | C24: =(C23/B23)-1 -> 0.055970149 | D24: =(D23/C23)-1 -> 0.59540636 | E24: =(E23/D23)-1 -> 0.20819491 | F24: =(F23/E23)-1 -> 0.55270394 | M24: % | N24: 2021 | O24: 2022 | P24: 2023 | Q24: 2024 | R24: 2025
A25: Base case | G25: 0.45 | H25: 0.5 | I25: 0.35 | J25: 0.26 | K25: 0.35 | M25: Data Center revenue | N25: =B5/B35 -> 0.40155922 | O25: =C5/C35 -> 0.39433009 | P25: =D5/D35 -> 0.55627641 | Q25: =E5/E35 -> 0.78009586 | R25: =F5/F35 -> 0.88267163
A26: Upside case | G26: 0.65 | H26: 1 | I26: 0.5 | J26: 0.42 | K26: 0.5 | M26: Gaming revenue | N26: =B11/B35 -> 0.46530735 | O26: =C11/C35 -> 0.46303039 | P26: =D11/D35 -> 0.3361385 | Q26: =E11/E35 -> 0.17148157 | R26: =F11/F35 -> 0.08697518
A27: Downside case | G27: 0.1 | H27: 0.05 | I27: 0.05 | J27: 0.03 | K27: 0.07 | M27: Professional Visualization revenue | N27: =B17/B35 -> 0.063148426 | O27: =C17/C35 -> 0.078435015 | P27: =D17/D35 -> 0.057240305 | Q27: =E17/E35 -> 0.025491612 | R27: =F17/F35 -> 0.014391135
M28: Automotive revenue | N28: =B23/B35 -> 0.032143928 | O28: =C23/C35 -> 0.021029947 | P28: =D23/D35 -> 0.033476681 | Q28: =E23/E35 -> 0.017908145 | R28: =F23/F35 -> 0.012981141
A29: OEM and Other revenue | B29: 631 | C29: 1162 | D29: 455 | E29: 306 | F29: 389 | G29: =F29*(1+G31) -> 396.78 | H29: =G29*(1+H31) -> 408.6834 | I29: =H29*(1+I31) -> 416.85707 | J29: =I29*(1+J31) -> 425.19421 | K29: =J29*(1+K31) -> 437.95004 | M29: OEM and Other revenue | N29: =B29/B35 -> 0.037841079 | O29: =C29/C35 -> 0.043174556 | P29: =D29/D35 -> 0.016868095 | Q29: =E29/E35 -> 0.0050228161 | R29: =F29/F35 -> 0.0029809114
A30: Y/Y Growth rate in OEM and Other revenue | C30: =(C29/B29)-1 -> 0.84152139 | D30: =(D29/C29)-1 -> -0.60843373 | E30: =(E29/D29)-1 -> -0.32747253 | F30: =(F29/E29)-1 -> 0.27124183
A31: Base case | G31: 0.02 | H31: 0.03 | I31: 0.02 | J31: 0.02 | K31: 0.03
A32: Upside case | G32: 0.1 | H32: 0.12 | I32: 0.08 | J32: 0.06 | K32: 0.07
A33: Downside case | G33: -0.05 | H33: -0.03 | I33: -0.04 | J33: -0.03 | K33: -0.05
A35: Total Revenue | B35: =B5+B11+B17+B23+B29 -> 16675 | C35: =C5+C11+C17+C23+C29 -> 26914 | D35: =D5+D11+D17+D23+D29 -> 26974 | E35: =E5+E11+E17+E23+E29 -> 60922 | F35: =F5+F11+F17+F23+F29 -> 130497 | G35: =G5+G11+G17+G23+G29 -> 211566.26 | H35: =H5+H11+H17+H23+H29 -> 295121.29 | I35: =I5+I11+I17+I23+I29 -> 371459.26 | ... K35: =K5+K11+K17+K23+K29 -> 521670.89
A36: Y/Y Growth rate in Total revenue | C36: =(C35/B35)-1 -> 0.61403298 | D36: =(D35/C35)-1 -> 0.002229323 | E36: =(E35/D35)-1 -> 1.2585453 | F36: =(F35/E35)-1 -> 1.1420341 | G36: =(G35/F35)-1 -> 0.62123466 | H36: =(H35/G35)-1 -> 0.3949355 | I36: =(I35/H35)-1 -> 0.25866643 | J36: =(J35/I35)-1 -> 0.15574054 | K36: =(K35/J35)-1 -> 0.21513653
A41: Assumptions of Assumed Yield ( % return on investments)
B42: 2026 F | C42: 2027 F | D42: 2028 F | E42: 2029 F | F42: 2030 F | H42: Cash & Short-Term Investments % of revenue
A43: Assumed Yield, % | I43: 2026 F | J43: 2027 F | K43: 2028 F | L43: 2029 F | M43: 2030 F
A44: Base case | B44: 0.0345 | C44: 0.0325 | D44: 0.0325 | E44: 0.031 | F44: 0.031 | H44: %
A45: Upside case | B45: =B44-0.5% -> 0.0295 | C45: =C44-0.5% -> 0.0275 | D45: =D44-0.5% -> 0.0275 | E45: =E44-0.5% -> 0.026 | F45: =F44-0.5% -> 0.026 | H45: Base case | I45: 0.28 | J45: 0.25 | K45: 0.23 | L45: 0.22 | M45: 0.21
A46: Downside case | B46: =B44+0.5% -> 0.0395 | C46: =C44+0.5% -> 0.0375 | D46: =D44+0.5% -> 0.0375 | E46: =E44+0.5% -> 0.036 | F46: =F44+0.5% -> 0.036 | H46: Upside case | I46: 0.3 | J46: 0.28 | K46: 0.27 | L46: 0.26 | M46: 0.25
H47: Downside case | I47: 0.25 | J47: 0.22 | K47: 0.2 | L47: 0.19 | M47: 0.18
A50: Interest Income projections
B51: 2021A | C51: 2022A | D51: 2023A | E51: 2024A | F51: 2025A | G51: 2026 F | H51: 2027 F | I51: 2028 F | J51: 2029 F | K51: 2030 F
A52: Revenue | B52: =C81 -> 16675 | C52: =D81 -> 26914 | D52: =E81 -> 26974 | E52: =F81 -> 60922 | F52: =G81 -> 130497 | G52: =H81 -> 211566.26 | H52: =I81 -> 295121.29 | I52: =J81 -> 371459.26 | ... K52: =L81 -> 521670.89
A53: Cash & Short-Term Investments | B53: ='02_Historical_BS'!B6 -> 11561 | C53: ='02_Historical_BS'!C6 -> 21208 | D53: ='02_Historical_BS'!D6 -> 13296 | E53: ='02_Historical_BS'!E6 -> 25984 | F53: ='02_Historical_BS'!F6 -> 43210 | G53: =G52*G55 -> 59238.553 | H53: =H52*H55 -> 73780.321 | I53: =I52*I55 -> 85435.629 | J53: =J52*J55 -> 94448.315 | K53: =K52*K55 -> 109550.89
A54: Average Cash & Short-Term Investments | B54: 0 | C54: =AVERAGE(C53,D53) -> 17252 | D54: =AVERAGE(D53,E53) -> 19640 | E54: =AVERAGE(E53,F53) -> 34597 | F54: =AVERAGE(F53,G53) -> 51224.276 | G54: =AVERAGE(G53,H53) -> 66509.437 | H54: =AVERAGE(H53,I53) -> 79607.975 | I54: =AVERAGE(I53,J53) -> 89941.972 | J54: =AVERAGE(J53,K53) -> 101999.6 | K54: =AVERAGE(K53,Y44) -> 109550.89
A55: Cash & Short-Term Investments % of revenue | B55: =B53/B52 -> 0.69331334 | C55: =C53/C52 -> 0.78799138 | D55: =D53/D52 -> 0.49291911 | E55: =E53/E52 -> 0.42651259 | F55: =F53/F52 -> 0.33111872 | G55: =I45 -> 0.28 | H55: =J45 -> 0.25 | I55: =K45 -> 0.23 | J55: =L45 -> 0.22 | K55: =M45 -> 0.21
A57: Assumed Yield | B57: =B58/B53 -> 0.0049303693 | C57: =C58/C53 -> 0.0013674085 | D57: =D58/D53 -> 0.020081227 | E57: =E58/E53 -> 0.033328202 | F57: =F58/F53 -> 0.041333025 | G57: =B44 -> 0.0345 | H57: =C44 -> 0.0325 | I57: =D44 -> 0.0325 | J57: =E44 -> 0.031 | K57: =F44 -> 0.031
A58: Interest income | B58: =C91 -> 57 | C58: =D91 -> 29 | D58: =E91 -> 267 | E58: =F91 -> 866 | F58: =G91 -> 1786 | G58: =(G52*G55)*G57 -> 2043.7301 | H58: =(H52*H55)*H57 -> 2397.8604 | I58: =(I52*I55)*I57 -> 2776.6579 | J58: =(J52*J55)*J57 -> 2927.8978 | K58: =(K52*K55)*K57 -> 3396.0775
A60: Effective tax rate assumptions
B61: 2026 F | C61: 2027 F | D61: 2028 F | E61: 2029 F | F61: 2030 F | Y61: =Y56+Y60 -> 0
A62: ETR, %
A63: Base case | B63: =15% -> 0.15 | C63: 0.145 | D63: 0.145 | E63: 0.14 | F63: 0.14
A64: Upside case | B64: 0.13 | C64: 0.125 | D64: 0.125 | E64: 0.12 | F64: 0.12
A65: Downside case | B65: 0.16 | C65: 0.17 | D65: 0.17 | E65: 0.175 | F65: 0.18
A68: Income tax expense (benefit) projections
B69: 2021A | C69: 2022A | D69: 2023A | E69: 2024A | F69: 2025A | G69: 2026 F | H69: 2027 F | I69: 2028 F | J69: 2029 F | K69: 2030 F
A70: Income before income tax | B70: =C95 -> 4409 | C70: =D95 -> 9941 | D70: =E95 -> 4181 | E70: =F95 -> 33818 | F70: =G95 -> 84026 | G70: =H95 -> 140974.31 | H70: =I95 -> 201734.1 | I70: =J95 -> 262529.63 | ... K70: =L95 -> 391778.52
A71: ETR | B71: =C96/C95 -> 0.017464278 | C71: =D96/D95 -> 0.019012172 | D71: =E96/E95 -> -0.044726142 | E71: =F96/F95 -> 0.11999527 | F71: =G96/G95 -> 0.13264942 | G71: =B63 -> 0.15 | H71: =C63 -> 0.145 | I71: =D63 -> 0.145 | J71: =E63 -> 0.14 | K71: =F63 -> 0.14
A72: =A96 -> Income tax expense (benefit) | B72: =B70*B71 -> 77 | C72: =C70*C71 -> 189 | D72: =D70*D71 -> -187 | E72: =E70*E71 -> 4058 | F72: =F70*F71 -> 11146 | G72: =G70*G71 -> 21146.147 | H72: =H70*H71 -> 29251.445 | I72: =I70*I71 -> 38066.796 | ... K72: =K70*K71 -> 54848.993
A79: Income Statement | B79: Historical | H79: Projected
B80: 2020A | C80: 2021A | D80: 2022A | E80: 2023A | F80: 2024A | G80: 2025A | H80: 2026 F | I80: 2027 F | J80: 2028 F | K80: 2029 F | L80: 2030 F
A81: Revenue | B81: 10918 | C81: 16675 | D81: 26914 | E81: 26974 | F81: 60922 | G81: 130497 | H81: =G35 -> 211566.26 | I81: =H35 -> 295121.29 | J81: =I35 -> 371459.26 | K81: =J35 -> 429310.52 | L81: =K35 -> 521670.89
A82: Cost of revenue( COGS) | B82: 4150 | C82: 6279 | D82: 9439 | E82: 11618 | F82: 16621 | G82: 32639 | H82: =(1-U6)*H81 -> 48684.153 | I82: =(1-V6)*I81 -> 62008.827 | J82: =(1-W6)*J81 -> 70619.244 | K82: =(1-X6)*K81 -> 73031.313 | L82: =(1-Y6)*L81 -> 78309.598
A83: Gross profit | B83: =B81-B82 -> 6768 | C83: =C81-C82 -> 10396 | D83: =D81-D82 -> 17475 | E83: 15356 | F83: 44301 | G83: 97858 | H83: =H81-H82 -> 162882.11 | I83: =I81-I82 -> 233112.46 | J83: =J81-J82 -> 300840.01 | K83: =K81-K82 -> 356279.21 | L83: =L81-L82 -> 443361.3
B84: 0 | C84: =(C83/B83)-1 -> 0.53605201 | D84: =(D83/C83)-1 -> 0.68093497 | E84: =(E83/D83)-1 -> -0.12125894 | F84: =(F83/E83)-1 -> 1.884931 | G84: =(G83/F83)-1 -> 1.2089343 | H84: =(H83/G83)-1 -> 0.66447411 | I84: =(I83/H83)-1 -> 0.43117291 | J84: =(J83/I83)-1 -> 0.29053596 | ... L84: =(L83/K83)-1 -> 0.24442091
A85: Operating expenses
A86: Research and development | B86: ='10_GrowthRates'!I46 -> 0 | C86: ='10_GrowthRates'!J46 -> 0 | D86: ='10_GrowthRates'!K46 -> 0 | E86: 7339 | F86: 8675 | G86: 12914 | H86: =U11*H81 -> 20098.795 | I86: =V11*I81 -> 27446.28 | J86: =W11*J81 -> 33431.333 | K86: =X11*K81 -> 37779.326 | L86: =Y11*L81 -> 44342.026
A87: Sales, general and administrative | B87: 1093 | C87: 1940 | D87: 2166 | E87: 2440 | F87: 2654 | G87: 3491 | H87: =U16*H81 -> 5289.1565 | I87: =V16*I81 -> 7082.9109 | J87: =W16*J81 -> 8543.5629 | K87: =X16*K81 -> 9444.8315 | L87: =Y16*L81 -> 11476.76
A88: Acquisition termination cost | B88: 0 | C88: 0 | D88: 0 | E88: 1353 | F88: 0 | G88: 0 | H88: 0 | I88: 0 | J88: 0 | K88: 0 | L88: 0
A89: Total operating expenses ( EBIT) | B89: 3922 | C89: 5864 | D89: 7434 | E89: 11132 | F89: 11329 | G89: 16405 | H89: =SUM(H86:H88) -> 25387.951 | I89: =SUM(I86:I88) -> 34529.19 | J89: =SUM(J86:J88) -> 41974.896 | K89: =SUM(K86:K88) -> 47224.157 | L89: =SUM(L86:L88) -> 55818.786
A90: Operating income | B90: =B83-B89 -> 2846 | C90: =C83-C89 -> 4532 | D90: =D83-D89 -> 10041 | E90: 4224 | F90: 32972 | G90: 81453 | H90: =H83-H89 -> 137494.16 | I90: =I83-I89 -> 198583.27 | J90: =J83-J89 -> 258865.12 | K90: =K83-K89 -> 309055.05 | L90: =L83-L89 -> 387542.51
A91: Interest income | B91: 178 | C91: 57 | D91: 29 | E91: 267 | F91: 866 | G91: 1786 | H91: =G58 -> 2043.7301 | I91: =H58 -> 2397.8604 | J91: =I58 -> 2776.6579 | K91: =J58 -> 2927.8978 | L91: =K58 -> 3396.0775
A92: Interest expense | B92: -52 | C92: -184 | D92: -236 | E92: -262 | F92: -257 | G92: -247 | H92: ='13_DebtSchedule'!I11 -> -263.5753 | I92: ='13_DebtSchedule'!J11 -> -247.0253 | J92: ='13_DebtSchedule'!K11 -> -112.1432 | K92: ='13_DebtSchedule'!L11 -> -101.8932 | L92: ='13_DebtSchedule'!M11 -> -160.0659
A93: Other, net | B93: -2 | C93: 4 | D93: 107 | E93: -48 | F93: 237 | G93: 1034 | H93: ='00_Assumptions'!$C$39 -> 1700 | I93: ='00_Assumptions'!$D$39 -> 1000 | J93: ='00_Assumptions'!$E$39 -> 1000 | K93: ='00_Assumptions'!$F$39 -> 1000 | L93: ='00_Assumptions'!$G$39 -> 1000
A94: Other income (expense), net | B94: =SUM(B91:B93) -> 124 | C94: =SUM(C91:C93) -> -123 | D94: =SUM(D91:D93) -> -100 | E94: -43 | F94: 846 | G94: 2573 | H94: =SUM(H91:H93) -> 3480.1548 | I94: =SUM(I91:I93) -> 3150.8351 | J94: =SUM(J91:J93) -> 3664.5147 | K94: =SUM(K91:K93) -> 3826.0046 | L94: =SUM(L91:L93) -> 4236.0116
A95: Income before income tax ( EBT) | B95: 2970 | C95: 4409 | D95: 9941 | E95: 4181 | F95: 33818 | G95: 84026 | H95: =H90+H94 -> 140974.31 | I95: =I90+I94 -> 201734.1 | J95: =J90+J94 -> 262529.63 | K95: =K90+K94 -> 312881.05 | L95: =L90+L94 -> 391778.52
A96: Income tax expense (benefit) | B96: 174 | C96: 77 | D96: 189 | E96: -187 | F96: 4058 | G96: 11146 | H96: =G72 -> 21146.147 | I96: =H72 -> 29251.445 | J96: =I72 -> 38066.796 | K96: =J72 -> 43803.348 | L96: =K72 -> 54848.993
A97: Net income | B97: 2796 | C97: 4332 | D97: 9752 | E97: 4368 | F97: 29760 | G97: 72880 | H97: =H95-H96 -> 119828.16 | I97: =I95-I96 -> 172482.66 | J97: =J95-J96 -> 224462.83 | K97: =K95-K96 -> 269077.71 | L97: =L95-L96 -> 336929.53
G101: 72880

Sheet 04b_Projection_BS
A1: Balance Sheet | B1: Historical | G1: Projected
A2: ($ in millions) | B2: 2021 | C2: 2022 | D2: 2023 | E2: 2024 | F2: 2025 | G2: 2026F | H2: 2027F | I2: 2028F | J2: 2029F | K2: 2030F
A3: Cash & Short-Term Investments | B3: 11561 | C3: 21208 | D3: 13296 | E3: 25984 | F3: 43210 | G3: ='04a_Projection_IS'!G53 -> 59238.553 | H3: ='04a_Projection_IS'!H53 -> 73780.321 | I3: ='04a_Projection_IS'!I53 -> 85435.629 | J3: ='04a_Projection_IS'!J53 -> 94448.315 | K3: ='04a_Projection_IS'!K53 -> 109550.89
A4: Receivables | B4: 2429 | C4: 4650 | D4: 3827 | E4: 9999 | F4: 23065 | G4: ='09_WorkingCapital'!G9 -> 36814.144 | H4: ='09_WorkingCapital'!H9 -> 50544.805 | I4: ='09_WorkingCapital'!I9 -> 62601.352 | J4: ='09_WorkingCapital'!J9 -> 71174.728 | K4: ='09_WorkingCapital'!K9 -> 85057.776
A5: Inventory | B5: 1826 | C5: 2605 | D5: 5159 | E5: 5282 | F5: 10080 | G5: ='09_WorkingCapital'!G10 -> 14671.937 | H5: ='09_WorkingCapital'!H10 -> 17838.156 | I5: ='09_WorkingCapital'!I10 -> 19347.738 | J5: ='09_WorkingCapital'!J10 -> 19008.15 | K5: ='09_WorkingCapital'!K10 -> 19309.216
A6: Prepaid Expenses | B6: 239 | C6: 366 | D6: 791 | E6: 3080 | F6: 3771 | G6: ='09_WorkingCapital'!G11 -> 5074.263 | H6: ='09_WorkingCapital'!H11 -> 5865.4371 | I6: ='09_WorkingCapital'!I11 -> 5870.9843 | J6: ='09_WorkingCapital'!J11 -> 5666.8989 | K6: ='09_WorkingCapital'!K11 -> 5581.8786
A7: Total Current Assets | B7: 16055 | C7: 28829 | D7: 23073 | E7: 44345 | F7: 80126 | G7: =SUM(G3:G6) -> 115798.9 | H7: =SUM(H3:H6) -> 148028.72 | I7: =SUM(I3:I6) -> 173255.7 | J7: =SUM(J3:J6) -> 190298.09 | K7: =SUM(K3:K6) -> 219499.76
A8: Property, Plant & Equipment | B8: ='02_Historical_BS'!B11 -> 2149 | C8: ='02_Historical_BS'!C11 -> 2778 | D8: ='02_Historical_BS'!D11 -> 3807 | E8: ='02_Historical_BS'!E11 -> 3914 | F8: ='02_Historical_BS'!F11 -> 6283 | G8: ='12_FixedAssets'!I15 -> 9937.7902 | H8: ='12_FixedAssets'!J15 -> 17492.895 | I8: ='12_FixedAssets'!K15 -> 27494.62 | J8: ='12_FixedAssets'!L15 -> 38164.672 | K8: ='12_FixedAssets'!M15 -> 50711.1
A9: Operating lease assets | B9: 707 | C9: 829 | D9: 1038 | E9: 1346 | F9: 1793 | G9: =F9 -> 1793 | H9: =G9 -> 1793 | I9: =H9 -> 1793 | J9: =I9 -> 1793 | K9: =J9 -> 1793
A10: Goodwill | B10: 4193 | C10: 4349 | D10: 4372 | E10: 4430 | F10: 5188 | G10: =F10 -> 5188 | H10: =G10 -> 5188 | I10: =H10 -> 5188 | J10: =I10 -> 5188 | K10: =J10 -> 5188
A11: Intangible Assets , net | B11: 2737 | C11: 2339 | D11: 1676 | E11: 1112 | F11: 807 | G11: ='12_FixedAssets'!I27 -> 1214.6385 | H11: ='12_FixedAssets'!J27 -> 2111.9043 | I11: ='12_FixedAssets'!K27 -> 3498.8829 | J11: ='12_FixedAssets'!L27 -> 5013.4008 | K11: ='12_FixedAssets'!M27 -> 6756.215
A12: Other Assets | B12: ='02_Historical_BS'!B15+'02_Historical_BS'!B16 -> 2950 | C12: ='02_Historical_BS'!C15+'02_Historical_BS'!C16 -> 5063 | D12: ='02_Historical_BS'!D15+'02_Historical_BS'!D16 -> 7216 | E12: ='02_Historical_BS'!E15+'02_Historical_BS'!E16 -> 10581 | F12: ='02_Historical_BS'!F15+'02_Historical_BS'!F16 -> 17404 | G12: =F12 -> 17404 | H12: =G12 -> 17404 | I12: =H12 -> 17404 | J12: =I12 -> 17404 | K12: =J12 -> 17404
A13: Total Assets | B13: =SUM(B7:B12) -> 28791 | C13: 44187 | D13: 41182 | E13: 65728 | F13: 111601 | G13: =G7+G8+G9+G10+G11+G12 -> 151336.33 | H13: =H7+H8+H9+H10+H11+H12 -> 192018.52 | I13: =I7+I8+I9+I10+I11+I12 -> 228634.21 | J13: =J7+J8+J9+J10+J11+J12 -> 257861.16 | K13: =K7+K8+K9+K10+K11+K12 -> 301352.07
A14: Accounts Payable | B14: 1149 | C14: 1783 | D14: 1193 | E14: 2699 | F14: 6310 | G14: ='09_WorkingCapital'!B14 -> 1149 | H14: ='09_WorkingCapital'!C14 -> 1783 | I14: ='09_WorkingCapital'!D14 -> 1193 | J14: ='09_WorkingCapital'!E14 -> 2699 | K14: ='09_WorkingCapital'!F14 -> 6310
A15: Accrued Expenses | B15: 297 | C15: 409 | D15: 530 | E15: 675 | F15: 848 | G15: ='09_WorkingCapital'!B15 -> 2776 | H15: ='09_WorkingCapital'!C15 -> 2552 | I15: ='09_WorkingCapital'!D15 -> 5370 | J15: ='09_WorkingCapital'!E15 -> 7932 | K15: ='09_WorkingCapital'!F15 -> 11737
A16: Short-Term Debt | B16: 999 | C16: 0 | D16: 1250 | E16: 1250 | F16: 0 | G16: =-'13_DebtSchedule'!I7 -> 1000 | H16: =-'13_DebtSchedule'!J7 -> 0 | I16: =-'13_DebtSchedule'!K7 -> 1250 | J16: =-'13_DebtSchedule'!L7 -> 0 | K16: =-'13_DebtSchedule'!M7 -> 1500
A17: Current Portion of Leases | B17: 0 | C17: 144 | D17: 176 | E17: 228 | F17: 288 | G17: =G38 -> 530.25789 | H17: =H38 -> 772.51577 | I17: =I38 -> 1014.7737 | J17: =J38 -> 1257.0315 | K17: =K38 -> 1499.2894
A18: Current Income Taxes Payable | B18: 0 | C18: 132 | D18: 467 | E18: 296 | F18: 881 | G18: =G51 -> 1671.4297 | H18: =H51 -> 2312.0871 | I18: =I51 -> 3008.8684 | J18: =J51 -> 3462.2958 | K18: =K51 -> 4335.3636
A19: Other Current Liabilities | B19: ='02_Historical_BS'!B23+'02_Historical_BS'!B24 -> 1480 | C19: ='02_Historical_BS'!C23+'02_Historical_BS'!C24 -> 1867 | D19: ='02_Historical_BS'!D23+'02_Historical_BS'!D24 -> 2947 | E19: ='02_Historical_BS'!E23+'02_Historical_BS'!E24 -> 5483 | F19: ='02_Historical_BS'!F23+'02_Historical_BS'!F24 -> 9720 | G19: =G55 -> 9366.8572 | H19: =H55 -> 13544.462 | I19: =I55 -> 17649.805 | J19: =J55 -> 21328.095 | K19: =K55 -> 24848.653
A20: Total Current Liabilities | B20: 3925 | C20: 4335 | D20: 6563 | E20: 10631 | F20: 18047 | G20: =SUM(G14:G19) -> 16493.545 | H20: =SUM(H14:H19) -> 20964.065 | I20: =SUM(I14:I19) -> 29486.447 | J20: =SUM(J14:J19) -> 36678.423 | K20: =SUM(K14:K19) -> 50230.306
A21: Long-Term Debt | B21: 5964 | C21: 10946 | D21: 9703 | E21: 8459 | F21: 8463 | G21: ='13_DebtSchedule'!I8 -> 7463 | H21: ='13_DebtSchedule'!J8 -> 7463 | I21: ='13_DebtSchedule'!K8 -> 6213 | J21: ='13_DebtSchedule'!L8 -> 6213 | K21: ='13_DebtSchedule'!M8 -> 4713
A22: Long-Term Leases | B22: 634 | C22: 741 | D22: 902 | E22: 1119 | F22: 1519 | G22: =G39 -> 2796.7421 | H22: =H39 -> 4074.4842 | I22: =I39 -> 5352.2263 | J22: =J39 -> 6629.9685 | K22: =K39 -> 7907.7106
A23: Other Long-Term Liabilities | B23: ='02_Historical_BS'!B28+'02_Historical_BS'!B29+'02_Historical_BS'!B30 -> 1375 | C23: ='02_Historical_BS'!C28+'02_Historical_BS'!C29+'02_Historical_BS'!C30 -> 1553 | D23: ='02_Historical_BS'!D28+'02_Historical_BS'!D29+'02_Historical_BS'!D30 -> 1913 | E23: ='02_Historical_BS'!E28+'02_Historical_BS'!E29+'02_Historical_BS'!E30 -> 2541 | F23: ='02_Historical_BS'!F28+'02_Historical_BS'!F29+'02_Historical_BS'!F30 -> 4245 | G23: =F23 -> 4245 | H23: =G23 -> 4245 | I23: =H23 -> 4245 | J23: =I23 -> 4245 | K23: =J23 -> 4245
A24: Total Liabilities | B24: 11898 | C24: 17575 | D24: 19081 | E24: 22750 | F24: 32274 | G24: =SUM(G20:G23) -> 30998.287 | H24: =SUM(H20:H23) -> 36746.549 | I24: =SUM(I20:I23) -> 45296.673 | J24: =SUM(J20:J23) -> 53766.391 | K24: =SUM(K20:K23) -> 67096.017
A25: Common Stock | B25: 3 | C25: 3 | D25: 2 | E25: 25 | F25: 24 | G25: =F25 -> 24 | H25: =G25 -> 24 | I25: =H25 -> 24 | J25: =I25 -> 24 | K25: =J25 -> 24
A26: Additional Paid-In Capital | B26: 8719 | C26: 10385 | D26: 11971 | E26: 13109 | F26: 11237 | G26: =F26+E65 -> 16314.59 | H26: =G26+F65 -> 21921.895 | I26: =H26+G65 -> 28236.702 | J26: =I26+H65 -> 35105.67 | K26: =J26+I65 -> 43452.405
A27: Retained Earnings | B27: 18908 | C27: 16235 | D27: 10171 | E27: 29817 | F27: 68038 | G27: =G80 -> 186667.88 | H27: =H80 -> 357598.2 | I27: =I80 -> 580040.87 | J27: =J80 -> 846965.95 | K27: =K80 -> 1181200
A28: Treasury Stock | B28: -10756 | C28: 0 | D28: 0 | E28: 0 | F28: 0 | G28: =F28 -> 0 | H28: =G28 -> 0 | I28: =H28 -> 0 | J28: =I28 -> 0 | K28: =J28 -> 0
A29: Comprehensive Income & Other | B29: 19 | C29: -11 | D29: -43 | E29: 27 | F29: 28 | G29: =F29 -> 28 | H29: =G29 -> 28 | I29: =H29 -> 28 | J29: =I29 -> 28 | K29: =J29 -> 28
A30: Shareholders' Equity | B30: 16893 | C30: 26612 | D30: 22101 | E30: 42978 | F30: 79327 | G30: =SUM(G25:G29) -> 203034.47 | H30: =SUM(H25:H29) -> 379572.09 | I30: =SUM(I25:I29) -> 608329.57 | J30: =SUM(J25:J29) -> 882123.62 | K30: =SUM(K25:K29) -> 1224704.4
A31: Total Liabilities & Equity | B31: 28791 | C31: 44187 | D31: 41182 | E31: 65728 | F31: 111601 | G31: =G30+G24 -> 234032.76 | H31: =H30+H24 -> 416318.64 | I31: =I30+I24 -> 653626.24 | J31: =J30+J24 -> 935890.01 | K31: =K30+K24 -> 1291800.5
A33: Check | B33: =B13-B31 -> 0 | C33: =C13-C31 -> 0 | D33: =D13-D31 -> 0 | E33: =E13-E31 -> 0 | F33: =F13-F31 -> 0
A36: Leasing Model
B37: 2021 A | C37: 2022 A | D37: 2023 A | E37: 2024 A | F37: 2025 A | G37: 2026 F | H37: 2027 F | I37: 2028 F | J37: 2029 F | K37: 2030 F
A38: Current Portion of Leases | B38: =B17 -> 0 | C38: =C17 -> 144 | D38: =D17 -> 176 | E38: =E17 -> 228 | F38: =F17 -> 288 | G38: =G41*G40 -> 530.25789 | H38: =H41*H40 -> 772.51577 | I38: =I41*I40 -> 1014.7737 | J38: =J41*J40 -> 1257.0315 | K38: =K41*K40 -> 1499.2894
A39: Long-Term Leases | B39: =B22 -> 634 | C39: =C22 -> 741 | D39: =D22 -> 902 | E39: =E22 -> 1119 | F39: =F22 -> 1519 | G39: =G40-G38 -> 2796.7421 | H39: =H40-H38 -> 4074.4842 | I39: =I40-I38 -> 5352.2263 | J39: =J40-J38 -> 6629.9685 | K39: =K40-K38 -> 7907.7106
A40: Total of Leases | B40: =SUM(B38:B39) -> 634 | C40: =SUM(C38:C39) -> 885 | D40: =SUM(D38:D39) -> 1078 | E40: =SUM(E38:E39) -> 1347 | F40: =SUM(F38:F39) -> 1807 | G40: =G45 -> 3327 | H40: =H45 -> 4847 | I40: =I45 -> 6367 | J40: =J45 -> 7887 | K40: =K45 -> 9407
A41: Current Portion of Leases % | B41: =B38/B40 -> 0 | C41: =C38/C40 -> 0.16271186 | D41: =D38/D40 -> 0.16326531 | E41: =E38/E40 -> 0.16926503 | F41: =F38/F40 -> 0.15938019 | G41: =F41 -> 0.15938019 | H41: =G41 -> 0.15938019 | I41: =H41 -> 0.15938019 | J41: =I41 -> 0.15938019 | K41: =J41 -> 0.15938019
A43: Opening Lease Liability | B43: 0 | C43: =B45 -> 634 | D43: =C45 -> 885 | E43: =D45 -> 1078 | F43: =E45 -> 1347 | G43: =F45 -> 1807 | H43: =G45 -> 3327 | I43: =H45 -> 4847 | J43: =I45 -> 6367 | K43: =J45 -> 7887
A44: New Leases | B44: 0 | C44: =C45-C43 -> 251 | D44: =D45-D43 -> 193 | E44: =E45-E43 -> 269 | F44: =F45-F43 -> 460 | G44: =G47 -> 1520 | H44: =H47 -> 1520 | I44: =I47 -> 1520 | J44: =J47 -> 1520 | K44: =K47 -> 1520
A45: Total Lease Liabilities | B45: =B40 -> 634 | C45: =C40 -> 885 | D45: =D40 -> 1078 | E45: =E40 -> 1347 | F45: =F40 -> 1807 | G45: =SUM(G43:G44) -> 3327 | H45: =SUM(H43:H44) -> 4847 | I45: =SUM(I43:I44) -> 6367 | J45: =SUM(J43:J44) -> 7887 | K45: =SUM(K43:K44) -> 9407
A47: New lease obligations ( 7600$ over 5 years) | B47: 0 | C47: 0 | D47: 0 | E47: 0 | F47: 0 | G47: =7600/5 -> 1520 | H47: =7600/5 -> 1520 | I47: =7600/5 -> 1520 | J47: =7600/5 -> 1520 | K47: =7600/5 -> 1520
A50: ='04a_Projection_IS'!A72 -> Income tax expense (benefit) | B50: ='04a_Projection_IS'!B72 -> 77 | C50: ='04a_Projection_IS'!C72 -> 189 | D50: ='04a_Projection_IS'!D72 -> -187 | E50: ='04a_Projection_IS'!E72 -> 4058 | F50: ='04a_Projection_IS'!F72 -> 11146 | G50: ='04a_Projection_IS'!G72 -> 21146.147 | H50: ='04a_Projection_IS'!H72 -> 29251.445 | ... K50: ='04a_Projection_IS'!K72 -> 54848.993
A51: =A18 -> Current Income Taxes Payable | B51: 0 | C51: =C18 -> 132 | D51: =D18 -> 467 | E51: =E18 -> 296 | F51: =F18 -> 881 | G51: =G50*G52 -> 1671.4297 | H51: =H50*H52 -> 2312.0871 | I51: =I50*I52 -> 3008.8684 | J51: =J50*J52 -> 3462.2958 | K51: =K50*K52 -> 4335.3636
B52: =B51/B50 -> 0 | C52: =C51/C50 -> 0.6984127 | D52: =D51/D50 -> -2.4973262 | E52: =E51/E50 -> 0.072942336 | F52: =F51/F50 -> 0.079041809 | G52: =F52 -> 0.079041809 | H52: =G52 -> 0.079041809 | I52: =H52 -> 0.079041809 | J52: =I52 -> 0.079041809 | K52: =J52 -> 0.079041809
A55: =A19 -> Other Current Liabilities | B55: =B19 -> 1480 | C55: =C19 -> 1867 | D55: =D19 -> 2947 | E55: =E19 -> 5483 | F55: =F19 -> 9720 | G55: =G56*G57 -> 9366.8572 | H55: =H56*H57 -> 13544.462 | I55: =I56*I57 -> 17649.805 | J55: =J56*J57 -> 21328.095 | K55: =K56*K57 -> 24848.653
A56: ='09_WorkingCapital'!A7 -> Total operating expenses | B56: ='09_WorkingCapital'!B7 -> 5864 | C56: ='09_WorkingCapital'!C7 -> 7434 | D56: ='09_WorkingCapital'!D7 -> 11132 | E56: ='09_WorkingCapital'!E7 -> 11329 | F56: ='09_WorkingCapital'!F7 -> 16405 | G56: ='09_WorkingCapital'!G7 -> 25387.951 | H56: ='09_WorkingCapital'!H7 -> 34529.19 | ... K56: ='09_WorkingCapital'!K7 -> 55818.786
A57: current liabilities % OpEx | B57: =B55/B56 -> 0.25238745 | C57: =C55/C56 -> 0.2511434 | D57: =D55/D56 -> 0.2647323 | E57: =E55/E56 -> 0.48397917 | F57: =F55/F56 -> 0.59250229 | G57: =AVERAGE(B57:F57) -> 0.36894892 | H57: =AVERAGE(C57:G57) -> 0.39226121 | I57: =AVERAGE(D57:H57) -> 0.42048478 | J57: =AVERAGE(E57:I57) -> 0.45163527 | K57: =AVERAGE(F57:J57) -> 0.44516649
A60: Assumptions :
B62: 2023 A | C62: 2024 A | D62: 2025 A | E62: 2026 F | F62: 2027 F | G62: 2028 F | H62: 2029 F | I62: 2030 F
A63: Revenue | B63: ='04a_Projection_IS'!E81 -> 26974 | C63: ='04a_Projection_IS'!F81 -> 60922 | D63: ='04a_Projection_IS'!G81 -> 130497 | E63: ='04a_Projection_IS'!H81 -> 211566.26 | F63: ='04a_Projection_IS'!I81 -> 295121.29 | G63: ='04a_Projection_IS'!J81 -> 371459.26 | H63: ='04a_Projection_IS'!K81 -> 429310.52 | I63: ='04a_Projection_IS'!L81 -> 521670.89
A64: YoY % | C64: =(C63/B63)-1 -> 1.2585453 | D64: =(D63/C63)-1 -> 1.1420341 | E64: =(E63/D63)-1 -> 0.62123466 | F64: =(F63/E63)-1 -> 0.3949355 | G64: =(G63/F63)-1 -> 0.25866643 | H64: =(H63/G63)-1 -> 0.15574054 | I64: =(I63/H63)-1 -> 0.21513653
A65: ='03_Historical_CF'!A6 -> Stock-based compensation expense | B65: ='03_Historical_CF'!B6 -> 2709 | C65: ='03_Historical_CF'!C6 -> 3549 | D65: ='03_Historical_CF'!D6 -> 4737 | E65: =E63*E66 -> 5077.5902 | F65: =F63*F66 -> 5607.3044 | G65: =G63*G66 -> 6314.8074 | H65: =H63*H66 -> 6868.9683 | I65: =I63*I66 -> 8346.7343
A66: SBC % of Revenue | B66: =B65/'04a_Projection_IS'!E81 -> 0.10043004 | C66: =C65/'04a_Projection_IS'!F81 -> 0.058254818 | D66: =D65/'04a_Projection_IS'!G81 -> 0.036299685 | E66: =B71 -> 0.024 | F66: =C71 -> 0.019 | G66: =D71 -> 0.017 | H66: =E71 -> 0.016 | I66: =F71 -> 0.016
A67: YoY % | B67: 0 | C67: =(C65/B65)-1 -> 0.31007752 | D67: =(D65/C65)-1 -> 0.33474218 | E67: =(E65/D65)-1 -> 0.071899987 | F67: =(F65/E65)-1 -> 0.10432393 | G67: =(G65/F65)-1 -> 0.12617523 | H67: =(H65/G65)-1 -> 0.087755801 | I67: =(I65/H65)-1 -> 0.21513653
A69: Assumptions | B69: =E62 -> 2026 F | C69: =F62 -> 2027 F | D69: =G62 -> 2028 F | E69: =H62 -> 2029 F | F69: =I62 -> 2030 F
A70: =A66 -> SBC % of Revenue
A71: Base case | B71: 0.024 | C71: 0.019 | D71: 0.017 | E71: 0.016 | F71: 0.016
A72: Upside case | B72: 0.025 | C72: 0.021 | D72: 0.019 | E72: 0.019 | F72: 0.019
A73: Downside case | B73: 0.023 | C73: 0.018 | D73: 0.015 | E73: 0.014 | F73: 0.013
B76: =B2 -> 2021 | C76: =C2 -> 2022 | D76: =B62 -> 2023 A | E76: =C62 -> 2024 A | F76: =D62 -> 2025 A | G76: =E62 -> 2026 F | H76: =F62 -> 2027 F | I76: =G62 -> 2028 F | J76: =H62 -> 2029 F | K76: =I62 -> 2030 F
A77: Retained Earnings, BoP | G77: =F80 -> 68038 | H77: =G80 -> 186667.88 | I77: =H80 -> 357598.2 | J77: =I80 -> 580040.87 | K77: =J80 -> 846965.95
A78: Plus: Net Income | G78: ='04a_Projection_IS'!H97 -> 119828.16 | H78: ='04a_Projection_IS'!I97 -> 172482.66 | I78: ='04a_Projection_IS'!J97 -> 224462.83 | J78: ='04a_Projection_IS'!K97 -> 269077.71 | K78: ='04a_Projection_IS'!L97 -> 336929.53
A79: Less: Dividends | B79: 395 | C79: 399 | D79: =-'03_Historical_CF'!B35 -> 398 | E79: =-'03_Historical_CF'!C35 -> 395 | F79: =-'03_Historical_CF'!D35 -> 834 | G79: =G78*G82 -> 1198.2816 | H79: =H78*H82 -> 1552.3439 | I79: =I78*I82 -> 2020.1655 | J79: =J78*J82 -> 2152.6217 | K79: =K78*K82 -> 2695.4362
A80: Retained Earnings, EoP | B80: =B27 -> 18908 | C80: =C27 -> 16235 | D80: =D27 -> 10171 | E80: =E27 -> 29817 | F80: =F27 -> 68038 | G80: =(G77+G78)-G79 -> 186667.88 | H80: =(H77+H78)-H79 -> 357598.2 | I80: =(I77+I78)-I79 -> 580040.87 | J80: =(J77+J78)-J79 -> 846965.95 | K80: =(K77+K78)-K79 -> 1181200
A82: Dividend Payout Ratio, % | B82: =B79/'04a_Projection_IS'!C97 -> 0.091181902 | C82: =C79/'04a_Projection_IS'!D97 -> 0.040914684 | D82: =D79/'04a_Projection_IS'!E97 -> 0.091117216 | E82: =E79/'04a_Projection_IS'!F97 -> 0.013272849 | F82: =F79/'04a_Projection_IS'!G97 -> 0.011443469 | G82: =B87 -> 0.01 | H82: =C87 -> 0.009 | I82: =D87 -> 0.009 | J82: =E87 -> 0.008 | K82: =F87 -> 0.008
A85: Assumptions | B85: =B69 -> 2026 F | C85: =C69 -> 2027 F | D85: =D69 -> 2028 F | E85: =E69 -> 2029 F | F85: =F69 -> 2030 F
A86: =A82 -> Dividend Payout Ratio, %
A87: Base case | B87: 0.01 | C87: 0.009 | D87: 0.009 | E87: 0.008 | F87: 0.008
A88: Upside case | B88: 0.012 | C88: 0.015 | D88: 0.02 | E88: 0.025 | F88: 0.03
A89: Downside case | B89: 0.009 | C89: 0.008 | D89: 0.007 | E89: 0.006 | F89: 0.006

Sheet 04c_Projection_CF
A1: Cash Flow statement
B2: 2023 | C2: 2024 | D2: 2025 | E2: 2026F | F2: 2027F | G2: 2028F | H2: 2029F | I2: 2030F
A3: Cash flows from operating activities:
A4: Net income | B4: 4368 | C4: 29760 | D4: 72880 | E4: ='04a_Projection_IS'!H97 -> 119828.16 | F4: ='04a_Projection_IS'!I97 -> 172482.66 | G4: ='04a_Projection_IS'!J97 -> 224462.83 | H4: ='04a_Projection_IS'!K97 -> 269077.71 | I4: ='04a_Projection_IS'!L97 -> 336929.53
A5: Adjustments to reconcile net income to net cash provided by operating activities:
A6: Stock-based compensation expense | B6: 2709 | C6: 3549 | D6: 4737 | E6: ='04b_Projection_BS'!E65 -> 5077.5902 | F6: ='04b_Projection_BS'!F65 -> 5607.3044 | G6: ='04b_Projection_BS'!G65 -> 6314.8074 | H6: ='04b_Projection_BS'!H65 -> 6868.9683 | I6: ='04b_Projection_BS'!I65 -> 8346.7343
A7: Depreciation and amortization | B7: 1544 | C7: 1508 | D7: 1864 | E7: ='11_DA'!B19 -> 3046.1976 | F7: ='11_DA'!C19 -> 4816.9738 | G7: ='11_DA'!D19 -> 6921.4049 | H7: ='11_DA'!E19 -> 9077.668 | I7: ='11_DA'!F19 -> 11117.025
A8: Deferred income taxes | B8: -2164 | C8: -2489 | D8: -4477 | E8: -4477 | F8: -4477 | G8: -4477 | H8: -4477 | I8: -4477
A9: (Gains) losses on non-marketable equity securities and publicly-held equity securities, net | B9: 45 | C9: -238 | D9: -1030 | E9: -1030 | F9: -1030 | G9: -1030 | H9: -1030 | I9: -1030
A10: Acquisition termination cost | B10: 1353 | C10: 0 | D10: 0 | E10: 0 | F10: 0 | G10: 0 | H10: 0 | I10: 0
A11: Other | B11: -7 | C11: -278 | D11: -502 | E11: -502 | F11: -502 | G11: -502 | H11: -502 | I11: -502
A12: Changes in operating assets and liabilities, net of acquisitions:
A13: Accounts receivable | B13: 822 | C13: -6172 | D13: -13063 | E13: =-('09_WorkingCapital'!G9-'09_WorkingCapital'!F9) -> -13749.144 | F13: =-('09_WorkingCapital'!H9-'09_WorkingCapital'!G9) -> -13730.661 | G13: =-('09_WorkingCapital'!I9-'09_WorkingCapital'!H9) -> -12056.548 | H13: =-('09_WorkingCapital'!J9-'09_WorkingCapital'!I9) -> -8573.3751 | I13: =-('09_WorkingCapital'!K9-'09_WorkingCapital'!J9) -> -13883.048
A14: Inventories | B14: -2554 | C14: -98 | D14: -4781 | E14: =-('09_WorkingCapital'!G10-'09_WorkingCapital'!F10) -> -4591.9365 | F14: =-('09_WorkingCapital'!H10-'09_WorkingCapital'!G10) -> -3166.2193 | G14: =-('09_WorkingCapital'!I10-'09_WorkingCapital'!H10) -> -1509.5824 | H14: =-('09_WorkingCapital'!J10-'09_WorkingCapital'!I10) -> 339.58819 | I14: =-('09_WorkingCapital'!K10-'09_WorkingCapital'!J10) -> -301.06601
A15: Prepaid expenses and other assets | B15: -1517 | C15: -1522 | D15: -395 | E15: =-('09_WorkingCapital'!G11-'09_WorkingCapital'!F11) -> -1303.263 | F15: =-('09_WorkingCapital'!H11-'09_WorkingCapital'!G11) -> -791.17411 | G15: =-('09_WorkingCapital'!I11-'09_WorkingCapital'!H11) -> -5.5472358 | H15: =-('09_WorkingCapital'!J11-'09_WorkingCapital'!I11) -> 204.08543 | I15: =-('09_WorkingCapital'!K11-'09_WorkingCapital'!J11) -> 85.020301
A16: Accounts payable | B16: -551 | C16: 1531 | D16: 3357 | E16: ='09_WorkingCapital'!G14-'09_WorkingCapital'!F14 -> 2968.5801 | F16: ='09_WorkingCapital'!H14-'09_WorkingCapital'!G14 -> 2369.6262 | G16: ='09_WorkingCapital'!I14-'09_WorkingCapital'!H14 -> 1423.9684 | H16: ='09_WorkingCapital'!J14-'09_WorkingCapital'!I14 -> 246.40701 | I16: ='09_WorkingCapital'!K14-'09_WorkingCapital'!J14 -> 748.04397
A17: Accrued and other current liabilities | B17: 1341 | C17: 2025 | D17: 4278 | E17: ='09_WorkingCapital'!G15-'09_WorkingCapital'!F15 -> 5989.6187 | F17: ='09_WorkingCapital'!H15-'09_WorkingCapital'!G15 -> 5376.4462 | G17: ='09_WorkingCapital'!I15-'09_WorkingCapital'!H15 -> 3842.4825 | H17: ='09_WorkingCapital'!J15-'09_WorkingCapital'!I15 -> 1833.4767 | I17: ='09_WorkingCapital'!K15-'09_WorkingCapital'!J15 -> 3320.0062
A18: Other long-term liabilities | B18: 252 | C18: 514 | D18: 1221 | E18: ='04b_Projection_BS'!G23-'04b_Projection_BS'!F23 -> 0 | F18: ='04b_Projection_BS'!H23-'04b_Projection_BS'!G23 -> 0 | G18: ='04b_Projection_BS'!I23-'04b_Projection_BS'!H23 -> 0 | H18: ='04b_Projection_BS'!J23-'04b_Projection_BS'!I23 -> 0 | I18: ='04b_Projection_BS'!K23-'04b_Projection_BS'!J23 -> 0
A19: Net cash provided by operating activities | B19: 5641 | C19: 28090 | D19: 64089 | E19: =SUM(E4:E18) -> 111256.81 | F19: =SUM(F4:F18) -> 166955.95 | G19: =SUM(G4:G18) -> 223384.82 | H19: =SUM(H4:H18) -> 273065.53 | I19: =SUM(I4:I18) -> 340353.24
A20: Cash flows from investing activities:
A21: Proceeds from maturities of marketable securities | B21: 19425 | C21: 9732 | D21: 11195 | E21: 0 | F21: 0 | G21: 0 | H21: 0 | I21: 0
A22: Proceeds from sales of marketable securities | B22: 1806 | C22: 50 | D22: 495 | E22: 0 | F22: 0 | G22: 0 | H22: 0 | I22: 0
A23: Proceeds from sales of non-marketable equity securities | B23: 8 | C23: 1 | D23: 171 | E23: 0 | F23: 0 | G23: 0 | H23: 0 | I23: 0
A24: Purchases of marketable securities | B24: -11897 | C24: -18211 | D24: -26575 | E24: 0 | F24: 0 | G24: 0 | H24: 0 | I24: 0
A25: Purchases related to property and equipment and intangible assets (capEX) | B25: -1833 | C25: -1069 | D25: -3236 | E25: =-'12_FixedAssets'!I6 -> -6346.9878 | F25: =-'12_FixedAssets'!J6 -> -9443.8812 | G25: =-'12_FixedAssets'!K6 -> -12258.155 | H25: =-'12_FixedAssets'!L6 -> -12879.316 | I25: =-'12_FixedAssets'!M6 -> -14606.785
A26: Purchases of non-marketable equity securities | B26: -85 | C26: -862 | D26: -1486 | E26: 0 | F26: 0 | G26: 0 | H26: 0 | I26: 0
A27: Acquisitions, net of cash acquired | B27: -49 | C27: -83 | D27: -1007 | E27: 0 | F27: 0 | G27: 0 | H27: 0 | I27: 0
A28: Other | B28: 0 | C28: -124 | D28: 22 | E28: 0 | F28: 0 | G28: 0 | H28: 0 | I28: 0
A29: Net cash provided by (used in) investing activities | B29: 7375 | C29: -10566 | D29: -20421 | E29: =SUM(E21:E28) -> -6346.9878 | F29: =SUM(F21:F28) -> -9443.8812 | G29: =SUM(G21:G28) -> -12258.155 | H29: =SUM(H21:H28) -> -12879.316 | I29: =SUM(I21:I28) -> -14606.785
A30: Cash flows from financing activities:
A31: Proceeds related to employee stock plans | B31: 355 | C31: 403 | D31: 490 | E31: 0 | F31: 0 | G31: 0 | H31: 0 | I31: 0
A32: Payments related to repurchases of common stock (buyback) | B32: -10039 | C32: -9533 | D32: -33706 | E32: 0 | F32: 0 | G32: 0 | H32: 0 | I32: 0
A33: Payments related to tax on restricted stock units | B33: -1475 | C33: -2783 | D33: -6930 | E33: 0 | F33: 0 | G33: 0 | H33: 0 | I33: 0
A34: Repayment of debt | B34: 0 | C34: -1250 | D34: -1250 | E34: ='13_DebtSchedule'!I7 -> -1000 | F34: ='13_DebtSchedule'!J7 -> 0 | G34: ='13_DebtSchedule'!K7 -> -1250 | H34: ='13_DebtSchedule'!L7 -> 0 | I34: ='13_DebtSchedule'!M7 -> -1500
A35: Dividends paid | B35: -398 | C35: -395 | D35: -834 | E35: =-'04b_Projection_BS'!G79 -> -1198.2816 | F35: =-'04b_Projection_BS'!H79 -> -1552.3439 | G35: =-'04b_Projection_BS'!I79 -> -2020.1655 | H35: =-'04b_Projection_BS'!J79 -> -2152.6217 | I35: =-'04b_Projection_BS'!K79 -> -2695.4362
A36: Principal payments on property and equipment and intangible assets | B36: -58 | C36: -74 | D36: -129 | E36: 0 | F36: 0 | G36: 0 | H36: 0 | I36: 0
A37: Other | B37: -2 | C37: -1 | D37: 0 | E37: 0 | F37: 0 | G37: 0 | H37: 0 | I37: 0
A38: Net cash used in financing activities | B38: -11617 | C38: -13633 | D38: -42359 | E38: =SUM(E31:E37) -> -2198.2816 | F38: =SUM(F31:F37) -> -1552.3439 | G38: =SUM(G31:G37) -> -3270.1655 | H38: =SUM(H31:H37) -> -2152.6217 | I38: =SUM(I31:I37) -> -4195.4362
A39: Change in cash and cash equivalents ( Net Cash Flow ) | B39: 1399 | C39: 3891 | D39: 1309 | E39: =E19+E29+E38 -> 102711.54 | F39: =F19+F29+F38 -> 155959.73 | G39: =G19+G29+G38 -> 207856.5 | H39: =H19+H29+H38 -> 258033.59 | I39: =I19+I29+I38 -> 321551.02

Sheet 05a_FCFF
B2: Unlevered Free Cash Flow
B3: Fiscal Year | C3: 2023 | D3: 2024 | E3: 2025 | F3: 2026F | G3: 2027F | H3: 2028F | I3: 2029F | J3: 2030F
B4: Revenue | C4: ='04a_Projection_IS'!E81 -> 26974 | D4: ='04a_Projection_IS'!F81 -> 60922 | E4: ='04a_Projection_IS'!G81 -> 130497 | F4: ='04a_Projection_IS'!H81 -> 211566.26 | G4: ='04a_Projection_IS'!I81 -> 295121.29 | H4: ='04a_Projection_IS'!J81 -> 371459.26 | I4: ='04a_Projection_IS'!K81 -> 429310.52 | J4: ='04a_Projection_IS'!L81 -> 521670.89
B5: COGS | C5: ='04a_Projection_IS'!E82 -> 11618 | D5: ='04a_Projection_IS'!F82 -> 16621 | E5: ='04a_Projection_IS'!G82 -> 32639 | F5: ='04a_Projection_IS'!H82 -> 48684.153 | G5: ='04a_Projection_IS'!I82 -> 62008.827 | H5: ='04a_Projection_IS'!J82 -> 70619.244 | I5: ='04a_Projection_IS'!K82 -> 73031.313 | J5: ='04a_Projection_IS'!L82 -> 78309.598
B6: Gross Profit | C6: ='04a_Projection_IS'!E83 -> 15356 | D6: ='04a_Projection_IS'!F83 -> 44301 | E6: ='04a_Projection_IS'!G83 -> 97858 | F6: ='04a_Projection_IS'!H83 -> 162882.11 | G6: ='04a_Projection_IS'!I83 -> 233112.46 | H6: ='04a_Projection_IS'!J83 -> 300840.01 | I6: ='04a_Projection_IS'!K83 -> 356279.21 | J6: ='04a_Projection_IS'!L83 -> 443361.3
B7: ='04a_Projection_IS'!A86 -> Research and development | C7: ='04a_Projection_IS'!E86 -> 7339 | D7: ='04a_Projection_IS'!F86 -> 8675 | E7: ='04a_Projection_IS'!G86 -> 12914 | F7: ='04a_Projection_IS'!H86 -> 20098.795 | G7: ='04a_Projection_IS'!I86 -> 27446.28 | H7: ='04a_Projection_IS'!J86 -> 33431.333 | I7: ='04a_Projection_IS'!K86 -> 37779.326 | J7: ='04a_Projection_IS'!L86 -> 44342.026
B8: ='04a_Projection_IS'!A87 -> Sales, general and administrative | C8: ='04a_Projection_IS'!E87 -> 2440 | D8: ='04a_Projection_IS'!F87 -> 2654 | E8: ='04a_Projection_IS'!G87 -> 3491 | F8: ='04a_Projection_IS'!H87 -> 5289.1565 | G8: ='04a_Projection_IS'!I87 -> 7082.9109 | H8: ='04a_Projection_IS'!J87 -> 8543.5629 | I8: ='04a_Projection_IS'!K87 -> 9444.8315 | J8: ='04a_Projection_IS'!L87 -> 11476.76
B9: ='04a_Projection_IS'!A88 -> Acquisition termination cost | C9: ='04a_Projection_IS'!E88 -> 1353 | D9: ='04a_Projection_IS'!F88 -> 0 | E9: ='04a_Projection_IS'!G88 -> 0 | F9: ='04a_Projection_IS'!H88 -> 0 | G9: ='04a_Projection_IS'!I88 -> 0 | H9: ='04a_Projection_IS'!J88 -> 0 | I9: ='04a_Projection_IS'!K88 -> 0 | J9: ='04a_Projection_IS'!L88 -> 0
B10: Total operating expenses | C10: ='04a_Projection_IS'!E89 -> 11132 | D10: ='04a_Projection_IS'!F89 -> 11329 | E10: ='04a_Projection_IS'!G89 -> 16405 | F10: ='04a_Projection_IS'!H89 -> 25387.951 | G10: ='04a_Projection_IS'!I89 -> 34529.19 | H10: ='04a_Projection_IS'!J89 -> 41974.896 | I10: ='04a_Projection_IS'!K89 -> 47224.157 | J10: ='04a_Projection_IS'!L89 -> 55818.786
B11: EBITDA | C11: =C6-C10 -> 4224 | D11: =D6-D10 -> 32972 | E11: =E6-E10 -> 81453 | F11: =F6-F10 -> 137494.16 | G11: =G6-G10 -> 198583.27 | H11: =H6-H10 -> 258865.12 | I11: =I6-I10 -> 309055.05 | J11: =J6-J10 -> 387542.51
B12: Depreciation & Amortization | C12: ='04c_Projection_CF'!B7 -> 1544 | D12: ='04c_Projection_CF'!C7 -> 1508 | E12: ='04c_Projection_CF'!D7 -> 1864 | F12: ='04c_Projection_CF'!E7 -> 3046.1976 | G12: ='04c_Projection_CF'!F7 -> 4816.9738 | H12: ='04c_Projection_CF'!G7 -> 6921.4049 | I12: ='04c_Projection_CF'!H7 -> 9077.668 | J12: ='04c_Projection_CF'!I7 -> 11117.025
B13: Operating Profit (EBIT) | C13: =C11-C12 -> 2680 | D13: =D11-D12 -> 31464 | E13: =E11-E12 -> 79589 | F13: =F11-F12 -> 134447.96 | G13: =G11-G12 -> 193766.29 | H13: =H11-H12 -> 251943.71 | I13: =I11-I12 -> 299977.38 | J13: =J11-J12 -> 376425.49
B14: Operating Taxes | C14: ='04a_Projection_IS'!E96 -> -187 | D14: ='04a_Projection_IS'!F96 -> 4058 | E14: ='04a_Projection_IS'!G96 -> 11146 | F14: ='04a_Projection_IS'!H96 -> 21146.147 | G14: ='04a_Projection_IS'!I96 -> 29251.445 | H14: ='04a_Projection_IS'!J96 -> 38066.796 | I14: ='04a_Projection_IS'!K96 -> 43803.348 | J14: ='04a_Projection_IS'!L96 -> 54848.993
B15: NOPAT (Net Operating Profit After Taxes) | C15: =C13-C14 -> 2867 | D15: =D13-D14 -> 27406 | E15: =E13-E14 -> 68443 | F15: =F13-F14 -> 113301.81 | G15: =G13-G14 -> 164514.85 | H15: =H13-H14 -> 213876.91 | I15: =I13-I14 -> 256174.03 | J15: =J13-J14 -> 321576.49
B16: (+) Depreciation & Amortization | C16: =C12 -> 1544 | D16: =D12 -> 1508 | E16: =E12 -> 1864 | F16: =F12 -> 3046.1976 | G16: =G12 -> 4816.9738 | H16: =H12 -> 6921.4049 | I16: =I12 -> 9077.668 | J16: =J12 -> 11117.025
B17: (-) Capital Expenditures | C17: ='04c_Projection_CF'!B25 -> -1833 | D17: ='04c_Projection_CF'!C25 -> -1069 | E17: ='04c_Projection_CF'!D25 -> -3236 | F17: ='04c_Projection_CF'!E25 -> -6346.9878 | G17: ='04c_Projection_CF'!F25 -> -9443.8812 | H17: ='04c_Projection_CF'!G25 -> -12258.155 | I17: ='04c_Projection_CF'!H25 -> -12879.316 | J17: ='04c_Projection_CF'!I25 -> -14606.785
B18: (-) Change in NWC | C18: ='09_WorkingCapital'!D19 -> -72 | D18: ='09_WorkingCapital'!E19 -> 4516 | E18: ='09_WorkingCapital'!F19 -> 11139 | F18: ='09_WorkingCapital'!G19 -> 10686.145 | G18: ='09_WorkingCapital'!H19 -> 9941.9818 | H18: ='09_WorkingCapital'!I19 -> 8305.2265 | I18: ='09_WorkingCapital'!J19 -> 5949.8178 | J18: ='09_WorkingCapital'!K19 -> 10031.044
B19: NWC | C19: ='09_WorkingCapital'!D18 -> 3214 | D19: ='09_WorkingCapital'!E18 -> 7730 | E19: ='09_WorkingCapital'!F18 -> 18869 | F19: ='09_WorkingCapital'!G18 -> 29555.145 | G19: ='09_WorkingCapital'!H18 -> 39497.126 | H19: ='09_WorkingCapital'!I18 -> 47802.353 | I19: ='09_WorkingCapital'!J18 -> 53752.171 | J19: ='09_WorkingCapital'!K18 -> 63783.214
B20: Unlevered Free Cash Flow | C20: =C15+C16+C17-C18 -> 2650 | D20: =D15+D16+D17-D18 -> 23329 | E20: =E15+E16+E17-E18 -> 55932 | F20: =F15+F16+F17-F18 -> 99314.877 | G20: =G15+G16+G17-G18 -> 149945.96 | H20: =H15+H16+H17-H18 -> 200234.94 | I20: =I15+I16+I17-I18 -> 246422.57 | J20: =J15+J16+J17-J18 -> 308055.69

Sheet 05b_DCF
A1: DCF Model
B3: Unlevered Free Cash Flow
B4: Fiscal Year | E4: 2023 | F4: 2024 | G4: 2025 | H4: 2026F | I4: 2027F | J4: 2028F | K4: 2029F | L4: 2030F
B5: Unlevered Free Cash Flow | E5: ='05a_FCFF'!C20 -> 2650 | F5: ='05a_FCFF'!D20 -> 23329 | G5: ='05a_FCFF'!E20 -> 55932 | H5: ='05a_FCFF'!F20 -> 99314.877 | I5: ='05a_FCFF'!G20 -> 149945.96 | J5: ='05a_FCFF'!H20 -> 200234.94 | K5: ='05a_FCFF'!I20 -> 246422.57 | L5: ='05a_FCFF'!J20 -> 308055.69
B7: Projection Year | H7: 1 | I7: 2 | J7: 3 | K7: 4 | L7: 5
B8: Present Value of Free Cash Flow | H8: =H5/(1+$C$14)^H7 -> 87956.021 | I8: =I5/(1+$C$14)^I7 -> 117608.12 | J8: =J5/(1+$C$14)^J7 -> 139089.28 | K8: =K5/(1+$C$14)^K7 -> 151595.23 | L8: =L5/(1+$C$14)^L7 -> 167836.17
B10: Implied Share Price Calculation | G10: Sensitivity Analysis -> Entreprise Value
B11: Sum of PV of FCF | C11: =SUM(H8:L8) -> 664084.81
B12: GDP Growth | C12: 3% - 5% | I12: Growth Rate
B13: Growth Rate (g) | C13: 0.04 | H13: =C17 -> 2622182.4 | I13: =J13-0.5% -> 0.02 | J13: =K13-0.5% -> 0.025 | K13: =L13-0.5% -> 0.03 | L13: =M13-0.5% -> 0.035 | M13: =C13 -> 0.04 | N13: =M13+0.5% -> 0.045 | O13: =N13+0.5% -> 0.05 | P13: =O13+0.5% -> 0.055 | Q13: =P13+0.5% -> 0.06
B14: WACC | C14: ='15_WACC'!F19 -> 0.12914245 | G14: WACC | H14: =H15-0.5% -> 0.10914245 | I14: 2804478.7 | J14: 2475582.6 | K14: 2304342.7 | L14: 2229502.2 | M14: 2229502.2 | N14: 2304342.7 | O14: 2475582.6 | P14: 2804478.7 | Q14: 3464990.5
B15: Terminal Value | C15: =C28 -> 3593999.4 | H15: =H16-0.5% -> 0.11414245 | I15: 3439958.3 | J15: 2952122.7 | K15: 2708908.1 | L15: 2604816.4 | M15: 2604816.4 | N15: 2708908.1 | O15: 2952122.7 | P15: 3439958.3 | Q15: 4510882.9
B16: PV of Terminal Value | C16: =C15/(1+C14)^L7 -> 1958097.6 | H16: =H17-0.5% -> 0.11914245 | I16: 4031162.5 | J16: 3372261.7 | K16: 3056186.9 | L16: 2923330.2 | M16: 2923330.2 | N16: 3056186.9 | O16: 3372261.7 | P16: 4031162.5 | Q16: 5606275.9
B17: Entreprise Value | C17: =C11+C16 -> 2622182.4 | H17: =H18-0.5% -> 0.12414245 | I17: 4402565.8 | J17: 3625533.4 | K17: 3261423.9 | L17: 3110003.5 | M17: 3110003.5 | N17: 3261423.9 | O17: 3625533.4 | P17: 4402565.8 | Q17: 6365007.6
B18: (-) Current net Debt | C18: =C38 -> -32940 | H18: =C14 -> 0.12914245 | I18: 4402565.8 | J18: 3625533.4 | K18: 3261423.9 | L18: 3110003.5 | M18: 3110003.5 | N18: 3261423.9 | O18: 3625533.4 | P18: 4402565.8 | Q18: 6365007.6
B19: Equity Value | C19: =C17-C18 -> 2655122.4 | H19: =H18+0.5% -> 0.13414245 | I19: 4031162.5 | J19: 3372261.7 | K19: 3056186.9 | L19: 2923330.2 | M19: 2923330.2 | N19: 3056186.9 | O19: 3372261.7 | P19: 4031162.5 | Q19: 5606275.9
B20: Diluted Shares Outstanding | C20: 24300 | H20: =H19+0.5% -> 0.13914245 | I20: 3439958.3 | J20: 2952122.7 | K20: 2708908.1 | L20: 2604816.4 | M20: 2604816.4 | N20: 2708908.1 | O20: 2952122.7 | P20: 3439958.3 | Q20: 4510882.9
B21: Implied Share Price | C21: =C19/C20 -> 109.26429 | H21: =H20+0.5% -> 0.14414245 | I21: 2804478.7 | J21: 2475582.6 | K21: 2304342.7 | L21: 2229502.2 | M21: 2229502.2 | N21: 2304342.7 | O21: 2475582.6 | P21: 2804478.7 | Q21: 3464990.5
H22: =H21+0.5% -> 0.14914245 | I22: 2232611.9 | J22: 2022809 | K22: 1909007.6 | L22: 1858240.9 | M22: 1858240.9 | N22: 1909007.6 | O22: 2022809 | P22: 2232611.9 | Q22: 2622182.4
B24: Terminal Value
B25: Propetuity Growth model
B26: FCF_5 | C26: =L5 -> 308055.69 | G26: Sensitivity Analysis -> Implied share Price
B27: g | C27: =C13 -> 0.04
B28: Terminal Value | C28: =C26*(1+C27)/(C14-C27) -> 3593999.4 | I28: Growth Rate
H29: =C21 -> 109.26429 | I29: =J29-0.5% -> 0.02 | J29: =K29-0.5% -> 0.025 | K29: =L29-0.5% -> 0.03 | L29: =M29-0.5% -> 0.035 | M29: 0.04 | N29: =M29+0.5% -> 0.045 | O29: =N29+0.5% -> 0.05 | P29: =O29+0.5% -> 0.055 | Q29: =P29+0.5% -> 0.06
B30: Current net Debt | G30: WACC | H30: =H31-0.5% -> 0.1091 | I30: 116.82761 | J30: 122.41793 | K30: 128.71499 | L30: 135.86185 | M30: 144.04299 | N30: 153.50044 | O30: 164.55814 | P30: 177.65977 | Q30: 193.42976
B31: Short term-Debt | C31: ='02_Historical_BS'!F20 -> 0 | H31: =H32-0.5% -> 0.1141 | I31: 109.98189 | J31: 114.88904 | K31: 120.37968 | L31: 126.56445 | M31: 133.58387 | N31: 141.61914 | O31: 150.90795 | P31: 161.76847 | Q31: 174.63649
B32: Current Portion of Long-Term Debt | C32: 0 | H32: =H33-0.5% -> 0.1191 | I32: 103.83883 | J32: 108.17248 | K32: 112.99251 | L32: 118.38568 | M32: 124.46066 | N32: 131.35547 | O32: 139.24809 | P32: 148.37201 | Q32: 159.03974
B33: Current Portion of Leases | C33: ='02_Historical_BS'!F21 -> 288 | H33: =H34-0.5% -> 0.1241 | I33: 98.296902 | J33: 102.14502 | K33: 106.40209 | L33: 111.13693 | M33: 116.43478 | N33: 122.40239 | O33: 129.17535 | P33: 136.92848 | Q33: 145.89114
B34: Long-Term Debt | C34: ='02_Historical_BS'!F26 -> 8463 | H34: 0.1291 | I34: 93.273227 | J34: 96.707129 | K34: 100.48754 | L34: 104.66969 | M34: 109.32123 | N34: 114.52585 | O34: 120.38846 | P34: 127.04224 | Q34: 134.65895
B35: Long-Term Leases | C35: ='02_Historical_BS'!F27 -> 1519 | H35: =H34+0.5% -> 0.1341 | I35: 88.699445 | J35: 91.777506 | K35: 95.15125 | L35: 98.865432 | M35: 102.97432 | N35: 107.54436 | O35: 112.65781 | P35: 118.41771 | Q35: 124.95493
B36: Total Debt | C36: =SUM(C31:C35) -> 10270 | H36: =H35+0.5% -> 0.1391 | I36: 84.518686 | J36: 87.289122 | K36: 90.313493 | L36: 93.628391 | M36: 97.277788 | N36: 101.31501 | O36: 105.80534 | P36: 110.82959 | Q36: 116.48903
B37: (-) Cash and cash equivalents | C37: ='02_Historical_BS'!F6 -> 43210 | H37: =H36+0.5% -> 0.1441 | I37: 80.683247 | J37: 83.186205 | K37: 85.908528 | L37: 88.880376 | M37: 92.137704 | N37: 95.723724 | O37: 99.690829 | P37: 104.10318 | Q37: 109.04018
B38: Current net Debt | C38: =C36-C37 -> -32940 | H38: =H37+0.5% -> 0.1491 | I38: 77.152825 | J38: 79.421977 | K38: 81.881654 | L38: 84.556904 | M38: 87.477364 | N38: 90.678367 | O38: 94.202379 | P38: 98.100886 | Q38: 102.43694
B41: Terminal Value — EV/EBITDA Exit Multiple Method
B42: Input / Metric | C42: Value | D42: Formula / Note
B43: FY2030 EBITDA ($M) | C43: ='05a_FCFF'!J11 -> 387542.51 | D43: FCFF sheet row 11, col J (2030F) — EBIT + D&A
B44: Exit Multiple (peer median EV/EBITDA) | C44: 22.3 | D44: Peer median: AMD 68.3x, Intel 22.3x, QCOM 13.0x, AVGO 52.0x, TSMC 14.3x → median 22.3x
B45: Implied Terminal EV ($M) | C45: =C43*C44 -> 8642198 | D45: FY2030 EBITDA × Exit Multiple
B46: PV of Terminal EV ($M) | C46: =C45/(1+C14)^5 -> 4708477.9 | D46: Discounted at WACC over 5-year horizon
B47: Enterprise Value — Exit Multiple ($M) | C47: =C11+C46 -> 5372562.7 | D47: Sum of PV FCFs (C11) + PV Terminal EV
B48: (-) Net Debt ($M) | C48: =C38 -> -32940 | D48: From net debt bridge (negative = net cash)
B49: Equity Value — Exit Multiple ($M) | C49: =C47-C48 -> 5405502.7 | D49: EV minus Net Debt
B50: Diluted Shares Outstanding | C50: =C20 -> 24300 | D50: Same as Gordon Growth base
B51: Implied Share Price — Exit Multiple ✦ | C51: =C49/C50 -> 222.44867 | D51: Equity Value / Diluted Shares
B53: Valuation Cross-Check — Gordon Growth vs Exit Multiple
B54: Gordon Growth implied price | C54: =C21 -> 109.26429 | D54: See 06_Sensitivity for full WACC×g range
B55: Exit Multiple implied price | C55: =C51 -> 222.44867 | D55: See 06_Sensitivity for full WACC×g range
B56: Difference (Exit − Gordon) | C56: =C55-C54 -> 113.18438 | D56: See 06_Sensitivity for full WACC×g range
B57: Average of both methods | C57: =AVERAGE(C54,C55) -> 165.85648 | D57: See 06_Sensitivity for full WACC×g range

Sheet 06_Sensitivity
A1: NVIDIA Sensitivity Analysis — WACC × Terminal Growth Rate
A2: NVIDIA Football field analysis - valuation summary
A3: Implied Share Price ($) — Gordon Growth Terminal Value
A4: WACC \ g | B4: 0.02 | C4: 0.025 | D4: 0.03 | E4: 0.035 | F4: 0.04 | G4: 0.045 | H4: 0.05 | I4: 0.055 | J4: 0.06
A5: 0.109 | B5: =('05b_DCF'!$C$11+('05a_FCFF'!$J$20*(1+0.02)/(0.109-0.02))/(1+0.109)^5-'05b_DCF'!$C$38)/'05b_DCF'!$C$20 -> 115.29562 | C5: =('05b_DCF'!$C$11+('05a_FCFF'!$J$20*(1+0.025)/(0.109-0.025))/(1+0.109)^5-'05b_DCF'!$C$38)/'05b_DCF'!$C$20 -> 120.9009 | D5: =('05b_DCF'!$C$11+('05a_FCFF'!$J$20*(1+0.03)/(0.109-0.03))/(1+0.109)^5-'05b_DCF'!$C$38)/'05b_DCF'!$C$20 -> 127.21571 | E5: =('05b_DCF'!$C$11+('05a_FCFF'!$J$20*(1+0.035)/(0.109-0.035))/(1+0.109)^5-'05b_DCF'!$C$38)/'05b_DCF'!$C$20 -> 134.38387 | F5: =('05b_DCF'!$C$11+('05a_FCFF'!$J$20*(1+0.04)/(0.109-0.04))/(1+0.109)^5-'05b_DCF'!$C$38)/'05b_DCF'!$C$20 -> 142.5909 | G5: =('05b_DCF'!$C$11+('05a_FCFF'!$J$20*(1+0.045)/(0.109-0.045))/(1+0.109)^5-'05b_DCF'!$C$38)/'05b_DCF'!$C$20 -> 152.08028 | H5: =('05b_DCF'!$C$11+('05a_FCFF'!$J$20*(1+0.05)/(0.109-0.05))/(1+0.109)^5-'05b_DCF'!$C$38)/'05b_DCF'!$C$20 -> 163.17803 | I5: =('05b_DCF'!$C$11+('05a_FCFF'!$J$20*(1+0.055)/(0.109-0.055))/(1+0.109)^5-'05b_DCF'!$C$38)/'05b_DCF'!$C$20 -> 176.33091 | J5: =('05b_DCF'!$C$11+('05a_FCFF'!$J$20*(1+0.06)/(0.109-0.06))/(1+0.109)^5-'05b_DCF'!$C$38)/'05b_DCF'!$C$20 -> 192.16806
A6: 0.114 | B6: =('05b_DCF'!$C$11+('05a_FCFF'!$J$20*(1+0.02)/(0.114-0.02))/(1+0.114)^5-'05b_DCF'!$C$38)/'05b_DCF'!$C$20 -> 108.86475 | C6: =('05b_DCF'!$C$11+('05a_FCFF'!$J$20*(1+0.025)/(0.114-0.025))/(1+0.114)^5-'05b_DCF'!$C$38)/'05b_DCF'!$C$20 -> 113.7844 | D6: =('05b_DCF'!$C$11+('05a_FCFF'!$J$20*(1+0.03)/(0.114-0.03))/(1+0.114)^5-'05b_DCF'!$C$38)/'05b_DCF'!$C$20 -> 119.28973 | E6: =('05b_DCF'!$C$11+('05a_FCFF'!$J$20*(1+0.035)/(0.114-0.035))/(1+0.114)^5-'05b_DCF'!$C$38)/'05b_DCF'!$C$20 -> 125.49193 | F6: =('05b_DCF'!$C$11+('05a_FCFF'!$J$20*(1+0.04)/(0.114-0.04))/(1+0.114)^5-'05b_DCF'!$C$38)/'05b_DCF'!$C$20 -> 132.53227 | G6: =('05b_DCF'!$C$11+('05a_FCFF'!$J$20*(1+0.045)/(0.114-0.045))/(1+0.114)^5-'05b_DCF'!$C$38)/'05b_DCF'!$C$20 -> 140.59294 | H6: =('05b_DCF'!$C$11+('05a_FCFF'!$J$20*(1+0.05)/(0.114-0.05))/(1+0.114)^5-'05b_DCF'!$C$38)/'05b_DCF'!$C$20 -> 149.9131 | I6: =('05b_DCF'!$C$11+('05a_FCFF'!$J$20*(1+0.055)/(0.114-0.055))/(1+0.114)^5-'05b_DCF'!$C$38)/'05b_DCF'!$C$20 -> 160.81294 | J6: =('05b_DCF'!$C$11+('05a_FCFF'!$J$20*(1+0.06)/(0.114-0.06))/(1+0.114)^5-'05b_DCF'!$C$38)/'05b_DCF'!$C$20 -> 173.73127
A7: 0.119 | B7: =('05b_DCF'!$C$11+('05a_FCFF'!$J$20*(1+0.02)/(0.119-0.02))/(1+0.119)^5-'05b_DCF'!$C$38)/'05b_DCF'!$C$20 -> 103.12949 | C7: =('05b_DCF'!$C$11+('05a_FCFF'!$J$20*(1+0.025)/(0.119-0.025))/(1+0.119)^5-'05b_DCF'!$C$38)/'05b_DCF'!$C$20 -> 107.47368 | D7: =('05b_DCF'!$C$11+('05a_FCFF'!$J$20*(1+0.03)/(0.119-0.03))/(1+0.119)^5-'05b_DCF'!$C$38)/'05b_DCF'!$C$20 -> 112.30599 | E7: =('05b_DCF'!$C$11+('05a_FCFF'!$J$20*(1+0.035)/(0.119-0.035))/(1+0.119)^5-'05b_DCF'!$C$38)/'05b_DCF'!$C$20 -> 117.71358 | F7: =('05b_DCF'!$C$11+('05a_FCFF'!$J$20*(1+0.04)/(0.119-0.04))/(1+0.119)^5-'05b_DCF'!$C$38)/'05b_DCF'!$C$20 -> 123.80567 | G7: =('05b_DCF'!$C$11+('05a_FCFF'!$J$20*(1+0.045)/(0.119-0.045))/(1+0.119)^5-'05b_DCF'!$C$38)/'05b_DCF'!$C$20 -> 130.72101 | H7: =('05b_DCF'!$C$11+('05a_FCFF'!$J$20*(1+0.05)/(0.119-0.05))/(1+0.119)^5-'05b_DCF'!$C$38)/'05b_DCF'!$C$20 -> 138.63858 | I7: =('05b_DCF'!$C$11+('05a_FCFF'!$J$20*(1+0.055)/(0.119-0.055))/(1+0.119)^5-'05b_DCF'!$C$38)/'05b_DCF'!$C$20 -> 147.79327 | J7: =('05b_DCF'!$C$11+('05a_FCFF'!$J$20*(1+0.06)/(0.119-0.06))/(1+0.119)^5-'05b_DCF'!$C$38)/'05b_DCF'!$C$20 -> 158.4996
A8: 0.124 | B8: =('05b_DCF'!$C$11+('05a_FCFF'!$J$20*(1+0.02)/(0.124-0.02))/(1+0.124)^5-'05b_DCF'!$C$38)/'05b_DCF'!$C$20 -> 97.988138 | C8: =('05b_DCF'!$C$11+('05a_FCFF'!$J$20*(1+0.025)/(0.124-0.025))/(1+0.124)^5-'05b_DCF'!$C$38)/'05b_DCF'!$C$20 -> 101.84522 | D8: =('05b_DCF'!$C$11+('05a_FCFF'!$J$20*(1+0.03)/(0.124-0.03))/(1+0.124)^5-'05b_DCF'!$C$38)/'05b_DCF'!$C$20 -> 106.11264 | E8: =('05b_DCF'!$C$11+('05a_FCFF'!$J$20*(1+0.035)/(0.124-0.035))/(1+0.124)^5-'05b_DCF'!$C$38)/'05b_DCF'!$C$20 -> 110.85953 | F8: =('05b_DCF'!$C$11+('05a_FCFF'!$J$20*(1+0.04)/(0.124-0.04))/(1+0.124)^5-'05b_DCF'!$C$38)/'05b_DCF'!$C$20 -> 116.17154 | G8: =('05b_DCF'!$C$11+('05a_FCFF'!$J$20*(1+0.045)/(0.124-0.045))/(1+0.124)^5-'05b_DCF'!$C$38)/'05b_DCF'!$C$20 -> 122.15595 | H8: =('05b_DCF'!$C$11+('05a_FCFF'!$J$20*(1+0.05)/(0.124-0.05))/(1+0.124)^5-'05b_DCF'!$C$38)/'05b_DCF'!$C$20 -> 128.94906 | I8: =('05b_DCF'!$C$11+('05a_FCFF'!$J$20*(1+0.055)/(0.124-0.055))/(1+0.124)^5-'05b_DCF'!$C$38)/'05b_DCF'!$C$20 -> 136.72669 | J8: =('05b_DCF'!$C$11+('05a_FCFF'!$J$20*(1+0.06)/(0.124-0.06))/(1+0.124)^5-'05b_DCF'!$C$38)/'05b_DCF'!$C$20 -> 145.71956
A9: 0.129 | B9: =('05b_DCF'!$C$11+('05a_FCFF'!$J$20*(1+0.02)/(0.129-0.02))/(1+0.129)^5-'05b_DCF'!$C$38)/'05b_DCF'!$C$20 -> 93.357732 | C9: =('05b_DCF'!$C$11+('05a_FCFF'!$J$20*(1+0.025)/(0.129-0.025))/(1+0.129)^5-'05b_DCF'!$C$38)/'05b_DCF'!$C$20 -> 96.799308 | D9: =('05b_DCF'!$C$11+('05a_FCFF'!$J$20*(1+0.03)/(0.129-0.03))/(1+0.129)^5-'05b_DCF'!$C$38)/'05b_DCF'!$C$20 -> 100.58852 | E9: =('05b_DCF'!$C$11+('05a_FCFF'!$J$20*(1+0.035)/(0.129-0.035))/(1+0.129)^5-'05b_DCF'!$C$38)/'05b_DCF'!$C$20 -> 104.78084 | F9: =('05b_DCF'!$C$11+('05a_FCFF'!$J$20*(1+0.04)/(0.129-0.04))/(1+0.129)^5-'05b_DCF'!$C$38)/'05b_DCF'!$C$20 -> 109.4442 | G9: =('05b_DCF'!$C$11+('05a_FCFF'!$J$20*(1+0.045)/(0.129-0.045))/(1+0.129)^5-'05b_DCF'!$C$38)/'05b_DCF'!$C$20 -> 114.66273 | H9: =('05b_DCF'!$C$11+('05a_FCFF'!$J$20*(1+0.05)/(0.129-0.05))/(1+0.129)^5-'05b_DCF'!$C$38)/'05b_DCF'!$C$20 -> 120.54183 | I9: =('05b_DCF'!$C$11+('05a_FCFF'!$J$20*(1+0.055)/(0.129-0.055))/(1+0.129)^5-'05b_DCF'!$C$38)/'05b_DCF'!$C$20 -> 127.2154 | J9: =('05b_DCF'!$C$11+('05a_FCFF'!$J$20*(1+0.06)/(0.129-0.06))/(1+0.129)^5-'05b_DCF'!$C$38)/'05b_DCF'!$C$20 -> 134.85616 | K9: Football Field Analysis - Data
A10: 0.134 | B10: =('05b_DCF'!$C$11+('05a_FCFF'!$J$20*(1+0.02)/(0.134-0.02))/(1+0.134)^5-'05b_DCF'!$C$38)/'05b_DCF'!$C$20 -> 89.16989 | C10: =('05b_DCF'!$C$11+('05a_FCFF'!$J$20*(1+0.025)/(0.134-0.025))/(1+0.134)^5-'05b_DCF'!$C$38)/'05b_DCF'!$C$20 -> 92.254565 | D10: =('05b_DCF'!$C$11+('05a_FCFF'!$J$20*(1+0.03)/(0.134-0.03))/(1+0.134)^5-'05b_DCF'!$C$38)/'05b_DCF'!$C$20 -> 95.635843 | E10: =('05b_DCF'!$C$11+('05a_FCFF'!$J$20*(1+0.035)/(0.134-0.035))/(1+0.134)^5-'05b_DCF'!$C$38)/'05b_DCF'!$C$20 -> 99.358665 | F10: =('05b_DCF'!$C$11+('05a_FCFF'!$J$20*(1+0.04)/(0.134-0.04))/(1+0.134)^5-'05b_DCF'!$C$38)/'05b_DCF'!$C$20 -> 103.47753 | G10: =('05b_DCF'!$C$11+('05a_FCFF'!$J$20*(1+0.045)/(0.134-0.045))/(1+0.134)^5-'05b_DCF'!$C$38)/'05b_DCF'!$C$20 -> 108.05919 | H10: =('05b_DCF'!$C$11+('05a_FCFF'!$J$20*(1+0.05)/(0.134-0.05))/(1+0.134)^5-'05b_DCF'!$C$38)/'05b_DCF'!$C$20 -> 113.18629 | I10: =('05b_DCF'!$C$11+('05a_FCFF'!$J$20*(1+0.055)/(0.134-0.055))/(1+0.134)^5-'05b_DCF'!$C$38)/'05b_DCF'!$C$20 -> 118.96238 | J10: =('05b_DCF'!$C$11+('05a_FCFF'!$J$20*(1+0.06)/(0.134-0.06))/(1+0.134)^5-'05b_DCF'!$C$38)/'05b_DCF'!$C$20 -> 125.51903 | M10: OpenLow | N10: Low | O10: OpenHigh | P10: High
A11: 0.139 | B11: =('05b_DCF'!$C$11+('05a_FCFF'!$J$20*(1+0.02)/(0.139-0.02))/(1+0.139)^5-'05b_DCF'!$C$38)/'05b_DCF'!$C$20 -> 85.367765 | C11: =('05b_DCF'!$C$11+('05a_FCFF'!$J$20*(1+0.025)/(0.139-0.025))/(1+0.139)^5-'05b_DCF'!$C$38)/'05b_DCF'!$C$20 -> 88.143936 | D11: =('05b_DCF'!$C$11+('05a_FCFF'!$J$20*(1+0.03)/(0.139-0.03))/(1+0.139)^5-'05b_DCF'!$C$38)/'05b_DCF'!$C$20 -> 91.174802 | E11: =('05b_DCF'!$C$11+('05a_FCFF'!$J$20*(1+0.035)/(0.139-0.035))/(1+0.139)^5-'05b_DCF'!$C$38)/'05b_DCF'!$C$20 -> 94.497097 | F11: =('05b_DCF'!$C$11+('05a_FCFF'!$J$20*(1+0.04)/(0.139-0.04))/(1+0.139)^5-'05b_DCF'!$C$38)/'05b_DCF'!$C$20 -> 98.154978 | G11: =('05b_DCF'!$C$11+('05a_FCFF'!$J$20*(1+0.045)/(0.139-0.045))/(1+0.139)^5-'05b_DCF'!$C$38)/'05b_DCF'!$C$20 -> 102.202 | H11: =('05b_DCF'!$C$11+('05a_FCFF'!$J$20*(1+0.05)/(0.139-0.05))/(1+0.139)^5-'05b_DCF'!$C$38)/'05b_DCF'!$C$20 -> 106.70373 | I11: =('05b_DCF'!$C$11+('05a_FCFF'!$J$20*(1+0.055)/(0.139-0.055))/(1+0.139)^5-'05b_DCF'!$C$38)/'05b_DCF'!$C$20 -> 111.74139 | J11: =('05b_DCF'!$C$11+('05a_FCFF'!$J$20*(1+0.06)/(0.139-0.06))/(1+0.139)^5-'05b_DCF'!$C$38)/'05b_DCF'!$C$20 -> 117.41673 | K11: DCF Bear | M11: =MIN('05b_DCF'!I30:I38) -> 77.152825 | N11: =M11 -> 77.152825 | O11: =MAX('05b_DCF'!I30:I38) -> 116.82761 | P11: =O11 -> 116.82761
A12: 0.144 | B12: =('05b_DCF'!$C$11+('05a_FCFF'!$J$20*(1+0.02)/(0.144-0.02))/(1+0.144)^5-'05b_DCF'!$C$38)/'05b_DCF'!$C$20 -> 81.903714 | C12: =('05b_DCF'!$C$11+('05a_FCFF'!$J$20*(1+0.025)/(0.144-0.025))/(1+0.144)^5-'05b_DCF'!$C$38)/'05b_DCF'!$C$20 -> 84.411672 | D12: =('05b_DCF'!$C$11+('05a_FCFF'!$J$20*(1+0.03)/(0.144-0.03))/(1+0.144)^5-'05b_DCF'!$C$38)/'05b_DCF'!$C$20 -> 87.139626 | E12: =('05b_DCF'!$C$11+('05a_FCFF'!$J$20*(1+0.035)/(0.144-0.035))/(1+0.144)^5-'05b_DCF'!$C$38)/'05b_DCF'!$C$20 -> 90.117851 | F12: =('05b_DCF'!$C$11+('05a_FCFF'!$J$20*(1+0.04)/(0.144-0.04))/(1+0.144)^5-'05b_DCF'!$C$38)/'05b_DCF'!$C$20 -> 93.382444 | G12: =('05b_DCF'!$C$11+('05a_FCFF'!$J$20*(1+0.045)/(0.144-0.045))/(1+0.144)^5-'05b_DCF'!$C$38)/'05b_DCF'!$C$20 -> 96.976794 | H12: =('05b_DCF'!$C$11+('05a_FCFF'!$J$20*(1+0.05)/(0.144-0.05))/(1+0.144)^5-'05b_DCF'!$C$38)/'05b_DCF'!$C$20 -> 100.95352 | I12: =('05b_DCF'!$C$11+('05a_FCFF'!$J$20*(1+0.055)/(0.144-0.055))/(1+0.144)^5-'05b_DCF'!$C$38)/'05b_DCF'!$C$20 -> 105.37707 | J12: =('05b_DCF'!$C$11+('05a_FCFF'!$J$20*(1+0.06)/(0.144-0.06))/(1+0.144)^5-'05b_DCF'!$C$38)/'05b_DCF'!$C$20 -> 110.32724 | K12: DCF Base | M12: =MIN('05b_DCF'!M30:M38) -> 87.477364 | N12: =M12 -> 87.477364 | O12: =MAX('05b_DCF'!M30:M38) -> 144.04299 | P12: =O12 -> 144.04299
A13: 0.149 | B13: =('05b_DCF'!$C$11+('05a_FCFF'!$J$20*(1+0.02)/(0.149-0.02))/(1+0.149)^5-'05b_DCF'!$C$38)/'05b_DCF'!$C$20 -> 78.737514 | C13: =('05b_DCF'!$C$11+('05a_FCFF'!$J$20*(1+0.025)/(0.149-0.025))/(1+0.149)^5-'05b_DCF'!$C$38)/'05b_DCF'!$C$20 -> 81.011048 | D13: =('05b_DCF'!$C$11+('05a_FCFF'!$J$20*(1+0.03)/(0.149-0.03))/(1+0.149)^5-'05b_DCF'!$C$38)/'05b_DCF'!$C$20 -> 83.475635 | E13: =('05b_DCF'!$C$11+('05a_FCFF'!$J$20*(1+0.035)/(0.149-0.035))/(1+0.149)^5-'05b_DCF'!$C$38)/'05b_DCF'!$C$20 -> 86.156414 | F13: =('05b_DCF'!$C$11+('05a_FCFF'!$J$20*(1+0.04)/(0.149-0.04))/(1+0.149)^5-'05b_DCF'!$C$38)/'05b_DCF'!$C$20 -> 89.083136 | G13: =('05b_DCF'!$C$11+('05a_FCFF'!$J$20*(1+0.045)/(0.149-0.045))/(1+0.149)^5-'05b_DCF'!$C$38)/'05b_DCF'!$C$20 -> 92.291274 | H13: =('05b_DCF'!$C$11+('05a_FCFF'!$J$20*(1+0.05)/(0.149-0.05))/(1+0.149)^5-'05b_DCF'!$C$38)/'05b_DCF'!$C$20 -> 95.823466 | I13: =('05b_DCF'!$C$11+('05a_FCFF'!$J$20*(1+0.055)/(0.149-0.055))/(1+0.149)^5-'05b_DCF'!$C$38)/'05b_DCF'!$C$20 -> 99.731423 | J13: =('05b_DCF'!$C$11+('05a_FCFF'!$J$20*(1+0.06)/(0.149-0.06))/(1+0.149)^5-'05b_DCF'!$C$38)/'05b_DCF'!$C$20 -> 104.07848 | K13: DCF Bull | M13: =MIN('05b_DCF'!Q30:Q38) -> 102.43694 | N13: =M13 -> 102.43694 | O13: =MAX('05b_DCF'!Q30:Q38) -> 193.42976 | P13: =O13 -> 193.42976
K14: Comps | M14: ='17_ComparableAnalysis'!O25 -> 133.9646 | N14: =M14 -> 133.9646 | O14: ='17_ComparableAnalysis'!N25 -> 137.10838 | P14: =O14 -> 137.10838
A15: Enterprise Value ($M) — Gordon Growth Terminal Value
A16: WACC \ g | B16: 0.02 | C16: 0.025 | D16: 0.03 | E16: 0.035 | F16: 0.04 | G16: 0.045 | H16: 0.05 | I16: 0.055 | J16: 0.06
A17: 0.109 | B17: ='05b_DCF'!$C$11+('05a_FCFF'!$J$20*(1+0.02)/(0.109-0.02))/(1+0.109)^5 -> 2768743.5 | C17: ='05b_DCF'!$C$11+('05a_FCFF'!$J$20*(1+0.025)/(0.109-0.025))/(1+0.109)^5 -> 2904951.8 | D17: ='05b_DCF'!$C$11+('05a_FCFF'!$J$20*(1+0.03)/(0.109-0.03))/(1+0.109)^5 -> 3058401.7 | E17: ='05b_DCF'!$C$11+('05a_FCFF'!$J$20*(1+0.035)/(0.109-0.035))/(1+0.109)^5 -> 3232588.1 | F17: ='05b_DCF'!$C$11+('05a_FCFF'!$J$20*(1+0.04)/(0.109-0.04))/(1+0.109)^5 -> 3432018.9 | G17: ='05b_DCF'!$C$11+('05a_FCFF'!$J$20*(1+0.045)/(0.109-0.045))/(1+0.109)^5 -> 3662610.8 | H17: ='05b_DCF'!$C$11+('05a_FCFF'!$J$20*(1+0.05)/(0.109-0.05))/(1+0.109)^5 -> 3932286 | I17: ='05b_DCF'!$C$11+('05a_FCFF'!$J$20*(1+0.055)/(0.109-0.055))/(1+0.109)^5 -> 4251901.1 | J17: ='05b_DCF'!$C$11+('05a_FCFF'!$J$20*(1+0.06)/(0.109-0.06))/(1+0.109)^5 -> 4636743.8
A18: 0.114 | B18: ='05b_DCF'!$C$11+('05a_FCFF'!$J$20*(1+0.02)/(0.114-0.02))/(1+0.114)^5 -> 2612473.5 | C18: ='05b_DCF'!$C$11+('05a_FCFF'!$J$20*(1+0.025)/(0.114-0.025))/(1+0.114)^5 -> 2732021 | D18: ='05b_DCF'!$C$11+('05a_FCFF'!$J$20*(1+0.03)/(0.114-0.03))/(1+0.114)^5 -> 2865800.4 | E18: ='05b_DCF'!$C$11+('05a_FCFF'!$J$20*(1+0.035)/(0.114-0.035))/(1+0.114)^5 -> 3016513.9 | F18: ='05b_DCF'!$C$11+('05a_FCFF'!$J$20*(1+0.04)/(0.114-0.04))/(1+0.114)^5 -> 3187594 | G18: ='05b_DCF'!$C$11+('05a_FCFF'!$J$20*(1+0.045)/(0.114-0.045))/(1+0.114)^5 -> 3383468.4 | H18: ='05b_DCF'!$C$11+('05a_FCFF'!$J$20*(1+0.05)/(0.114-0.05))/(1+0.114)^5 -> 3609948.2 | I18: ='05b_DCF'!$C$11+('05a_FCFF'!$J$20*(1+0.055)/(0.114-0.055))/(1+0.114)^5 -> 3874814.4 | J18: ='05b_DCF'!$C$11+('05a_FCFF'!$J$20*(1+0.06)/(0.114-0.06))/(1+0.114)^5 -> 4188729.8 | K18: NVIDIA
A19: 0.119 | B19: ='05b_DCF'!$C$11+('05a_FCFF'!$J$20*(1+0.02)/(0.119-0.02))/(1+0.119)^5 -> 2473106.5 | C19: ='05b_DCF'!$C$11+('05a_FCFF'!$J$20*(1+0.025)/(0.119-0.025))/(1+0.119)^5 -> 2578670.5 | D19: ='05b_DCF'!$C$11+('05a_FCFF'!$J$20*(1+0.03)/(0.119-0.03))/(1+0.119)^5 -> 2696095.6 | E19: ='05b_DCF'!$C$11+('05a_FCFF'!$J$20*(1+0.035)/(0.119-0.035))/(1+0.119)^5 -> 2827500 | F19: ='05b_DCF'!$C$11+('05a_FCFF'!$J$20*(1+0.04)/(0.119-0.04))/(1+0.119)^5 -> 2975537.7 | G19: ='05b_DCF'!$C$11+('05a_FCFF'!$J$20*(1+0.045)/(0.119-0.045))/(1+0.119)^5 -> 3143580.6 | H19: ='05b_DCF'!$C$11+('05a_FCFF'!$J$20*(1+0.05)/(0.119-0.05))/(1+0.119)^5 -> 3335977.5 | I19: ='05b_DCF'!$C$11+('05a_FCFF'!$J$20*(1+0.055)/(0.119-0.055))/(1+0.119)^5 -> 3558436.4 | J19: ='05b_DCF'!$C$11+('05a_FCFF'!$J$20*(1+0.06)/(0.119-0.06))/(1+0.119)^5 -> 3818600.2 | K19: Recommendation | M19: "Hold"
A20: 0.124 | B20: ='05b_DCF'!$C$11+('05a_FCFF'!$J$20*(1+0.02)/(0.124-0.02))/(1+0.124)^5 -> 2348171.8 | C20: ='05b_DCF'!$C$11+('05a_FCFF'!$J$20*(1+0.025)/(0.124-0.025))/(1+0.124)^5 -> 2441898.9 | D20: ='05b_DCF'!$C$11+('05a_FCFF'!$J$20*(1+0.03)/(0.124-0.03))/(1+0.124)^5 -> 2545597.1 | E20: ='05b_DCF'!$C$11+('05a_FCFF'!$J$20*(1+0.035)/(0.124-0.035))/(1+0.124)^5 -> 2660946.7 | F20: ='05b_DCF'!$C$11+('05a_FCFF'!$J$20*(1+0.04)/(0.124-0.04))/(1+0.124)^5 -> 2790028.4 | G20: ='05b_DCF'!$C$11+('05a_FCFF'!$J$20*(1+0.045)/(0.124-0.045))/(1+0.124)^5 -> 2935449.5 | H20: ='05b_DCF'!$C$11+('05a_FCFF'!$J$20*(1+0.05)/(0.124-0.05))/(1+0.124)^5 -> 3100522.2 | I20: ='05b_DCF'!$C$11+('05a_FCFF'!$J$20*(1+0.055)/(0.124-0.055))/(1+0.124)^5 -> 3289518.5 | J20: ='05b_DCF'!$C$11+('05a_FCFF'!$J$20*(1+0.06)/(0.124-0.06))/(1+0.124)^5 -> 3508045.4 | K20: Current Price | M20: 183
A21: 0.129 | B21: ='05b_DCF'!$C$11+('05a_FCFF'!$J$20*(1+0.02)/(0.129-0.02))/(1+0.129)^5 -> 2235652.9 | C21: ='05b_DCF'!$C$11+('05a_FCFF'!$J$20*(1+0.025)/(0.129-0.025))/(1+0.129)^5 -> 2319283.2 | D21: ='05b_DCF'!$C$11+('05a_FCFF'!$J$20*(1+0.03)/(0.129-0.03))/(1+0.129)^5 -> 2411361 | E21: ='05b_DCF'!$C$11+('05a_FCFF'!$J$20*(1+0.035)/(0.129-0.035))/(1+0.129)^5 -> 2513234.3 | F21: ='05b_DCF'!$C$11+('05a_FCFF'!$J$20*(1+0.04)/(0.129-0.04))/(1+0.129)^5 -> 2626554 | G21: ='05b_DCF'!$C$11+('05a_FCFF'!$J$20*(1+0.045)/(0.129-0.045))/(1+0.129)^5 -> 2753364.2 | H21: ='05b_DCF'!$C$11+('05a_FCFF'!$J$20*(1+0.05)/(0.129-0.05))/(1+0.129)^5 -> 2896226.4 | I21: ='05b_DCF'!$C$11+('05a_FCFF'!$J$20*(1+0.055)/(0.129-0.055))/(1+0.129)^5 -> 3058394.2 | J21: ='05b_DCF'!$C$11+('05a_FCFF'!$J$20*(1+0.06)/(0.129-0.06))/(1+0.129)^5 -> 3244064.6 | K21: Target Price | M21: 110
A22: 0.134 | B22: ='05b_DCF'!$C$11+('05a_FCFF'!$J$20*(1+0.02)/(0.134-0.02))/(1+0.134)^5 -> 2133888.3 | C22: ='05b_DCF'!$C$11+('05a_FCFF'!$J$20*(1+0.025)/(0.134-0.025))/(1+0.134)^5 -> 2208845.9 | D22: ='05b_DCF'!$C$11+('05a_FCFF'!$J$20*(1+0.03)/(0.134-0.03))/(1+0.134)^5 -> 2291011 | E22: ='05b_DCF'!$C$11+('05a_FCFF'!$J$20*(1+0.035)/(0.134-0.035))/(1+0.134)^5 -> 2381475.5 | F22: ='05b_DCF'!$C$11+('05a_FCFF'!$J$20*(1+0.04)/(0.134-0.04))/(1+0.134)^5 -> 2481564 | G22: ='05b_DCF'!$C$11+('05a_FCFF'!$J$20*(1+0.045)/(0.134-0.045))/(1+0.134)^5 -> 2592898.3 | H22: ='05b_DCF'!$C$11+('05a_FCFF'!$J$20*(1+0.05)/(0.134-0.05))/(1+0.134)^5 -> 2717486.8 | I22: ='05b_DCF'!$C$11+('05a_FCFF'!$J$20*(1+0.055)/(0.134-0.055))/(1+0.134)^5 -> 2857845.9 | J22: ='05b_DCF'!$C$11+('05a_FCFF'!$J$20*(1+0.06)/(0.134-0.06))/(1+0.134)^5 -> 3017172.5 | K22: UP/DOWNSIDE | M22: =M21/M20-1 -> -0.3989071
A23: 0.139 | B23: ='05b_DCF'!$C$11+('05a_FCFF'!$J$20*(1+0.02)/(0.139-0.02))/(1+0.139)^5 -> 2041496.7 | C23: ='05b_DCF'!$C$11+('05a_FCFF'!$J$20*(1+0.025)/(0.139-0.025))/(1+0.139)^5 -> 2108957.7 | D23: ='05b_DCF'!$C$11+('05a_FCFF'!$J$20*(1+0.03)/(0.139-0.03))/(1+0.139)^5 -> 2182607.7 | E23: ='05b_DCF'!$C$11+('05a_FCFF'!$J$20*(1+0.035)/(0.139-0.035))/(1+0.139)^5 -> 2263339.5 | F23: ='05b_DCF'!$C$11+('05a_FCFF'!$J$20*(1+0.04)/(0.139-0.04))/(1+0.139)^5 -> 2352226 | G23: ='05b_DCF'!$C$11+('05a_FCFF'!$J$20*(1+0.045)/(0.139-0.045))/(1+0.139)^5 -> 2450568.5 | H23: ='05b_DCF'!$C$11+('05a_FCFF'!$J$20*(1+0.05)/(0.139-0.05))/(1+0.139)^5 -> 2559960.7 | I23: ='05b_DCF'!$C$11+('05a_FCFF'!$J$20*(1+0.055)/(0.139-0.055))/(1+0.139)^5 -> 2682375.8 | J23: ='05b_DCF'!$C$11+('05a_FCFF'!$J$20*(1+0.06)/(0.139-0.06))/(1+0.139)^5 -> 2820286.5
A24: 0.144 | B24: ='05b_DCF'!$C$11+('05a_FCFF'!$J$20*(1+0.02)/(0.144-0.02))/(1+0.144)^5 -> 1957320.3 | C24: ='05b_DCF'!$C$11+('05a_FCFF'!$J$20*(1+0.025)/(0.144-0.025))/(1+0.144)^5 -> 2018263.6 | D24: ='05b_DCF'!$C$11+('05a_FCFF'!$J$20*(1+0.03)/(0.144-0.03))/(1+0.144)^5 -> 2084552.9 | E24: ='05b_DCF'!$C$11+('05a_FCFF'!$J$20*(1+0.035)/(0.144-0.035))/(1+0.144)^5 -> 2156923.8 | F24: ='05b_DCF'!$C$11+('05a_FCFF'!$J$20*(1+0.04)/(0.144-0.04))/(1+0.144)^5 -> 2236253.4 | G24: ='05b_DCF'!$C$11+('05a_FCFF'!$J$20*(1+0.045)/(0.144-0.045))/(1+0.144)^5 -> 2323596.1 | H24: ='05b_DCF'!$C$11+('05a_FCFF'!$J$20*(1+0.05)/(0.144-0.05))/(1+0.144)^5 -> 2420230.6 | I24: ='05b_DCF'!$C$11+('05a_FCFF'!$J$20*(1+0.055)/(0.144-0.055))/(1+0.144)^5 -> 2527722.8 | J24: ='05b_DCF'!$C$11+('05a_FCFF'!$J$20*(1+0.06)/(0.144-0.06))/(1+0.144)^5 -> 2648011.8
A25: 0.149 | B25: ='05b_DCF'!$C$11+('05a_FCFF'!$J$20*(1+0.02)/(0.149-0.02))/(1+0.149)^5 -> 1880381.6 | C25: ='05b_DCF'!$C$11+('05a_FCFF'!$J$20*(1+0.025)/(0.149-0.025))/(1+0.149)^5 -> 1935628.5 | D25: ='05b_DCF'!$C$11+('05a_FCFF'!$J$20*(1+0.03)/(0.149-0.03))/(1+0.149)^5 -> 1995517.9 | E25: ='05b_DCF'!$C$11+('05a_FCFF'!$J$20*(1+0.035)/(0.149-0.035))/(1+0.149)^5 -> 2060660.9 | F25: ='05b_DCF'!$C$11+('05a_FCFF'!$J$20*(1+0.04)/(0.149-0.04))/(1+0.149)^5 -> 2131780.2 | G25: ='05b_DCF'!$C$11+('05a_FCFF'!$J$20*(1+0.045)/(0.149-0.045))/(1+0.149)^5 -> 2209738 | H25: ='05b_DCF'!$C$11+('05a_FCFF'!$J$20*(1+0.05)/(0.149-0.05))/(1+0.149)^5 -> 2295570.2 | I25: ='05b_DCF'!$C$11+('05a_FCFF'!$J$20*(1+0.055)/(0.149-0.055))/(1+0.149)^5 -> 2390533.6 | J25: ='05b_DCF'!$C$11+('05a_FCFF'!$J$20*(1+0.06)/(0.149-0.06))/(1+0.149)^5 -> 2496167
C26: Shares Out | E26: 24.30B | K26: Industry | L26: Sector
A27: ■ Dark green = base case (WACC 12.9% / g 4.0%) ■ Yellow row = base WACC ■ Blue shading = alternating rows | K27: Semiconductors | L27: Technology
C28: Revenue (ttm) | E28: 165.22B | K28: IPO Date | L28: Employees
C29: Net income (ttm) | E29: 86.6B | K29: 36182 | L29: 36000
C30: EPS (ttm) | E30: 3.51 | K30: Stock exchange | L30: Ticker symbol
C31: PE Ratio | E31: 51.4 | K31: NASDAQ | L31: NVDA
C32: EV/EBITDA | E32: 44.8
C33: Dividend | E33: 0.04
C34: ROE (%) | E34: 0.92

Sheet 07_Adjustments
A1: NVIDIA Corporation — Non-Recurring Items & Model Adjustments
A2: Documents all one-time, non-recurring, and adjusted items excluded from or adjusted within the DCF model. Per Phase A spec — all items with justifications.
A4: Section 1 — One-Time / Non-Recurring Items (Historical)
A5: # | B5: Item | C5: FY Year | D5: Amount ($M) | E5: P&L Line | F5: Justification / Treatment | G5: Source
A6: 1 | B6: Arm Holdings Acquisition Termination Fee | C6: FY2023 | D6: 1,350 | E6: Acquisition termination cost (OPEX) | F6: One-time charge: NVIDIA terminated its $40B Arm acquisition in Feb 2022 due to regulatory opposition. Fee paid to SoftBank. TREATMENT: Included in FY2023 historical EBIT but EXCLUDED from FY2024F+ projections (zeroed in 04a row 88). Excluded from FCFF normalised EBIT in 05a row 9. | G6: NVIDIA 10-K FY2023, Note 2
A7: 2 | B7: Deferred Income Tax Benefit (FY2023) | C7: FY2023 | D7: (2,164) | E7: Income tax (CF Statement) | F7: Large non-cash deferred tax benefit in FY2023 drove negative effective tax rate (-4.5%). TREATMENT: Reflected in historical data only. Forward ETR normalised to 15% base case (00_Assumptions row 36). | G7: NVIDIA 10-K FY2023, Cash Flow
A8: 3 | B8: Gains on Non-Marketable Equity Securities | C8: FY2024–FY2025 | D8: 238 / 1,030 | E8: Other income (below EBIT) | F8: Non-cash gains on strategic equity investments (AI/startup portfolio). TREATMENT: Included in historical 'Other, net'. Not projected forward in base case — excluded from FCFF unlevered framework. FY2026F+ Other net assumption = $1,000M flat (conservative). | G8: NVIDIA 10-K FY2024-FY2025
A11: Section 2 — Model Normalisation Notes
A12: # | B12: Topic | C12: Normalisation Applied | D12: Rationale
A13: 1 | B13: Stock-Based Compensation (SBC) | C13: Added back in CFO but NOT in FCFF (unlevered framework). SBC FY2025 = $4,737M (~3.6% revenue). Not projected separately — treated as operating cost already embedded in EBIT margins. | D13: Standard FCFF treatment: SBC is non-cash but real economic cost.
A14: 2 | B14: Capex as % of Revenue | C14: FY2026F: 3.0% of revenue (linked to 00_Assumptions!C42 / named range Capex_pct). Historical: FY2023=6.8%, FY2024=1.8%, FY2025=2.5%. 3.0% forward reflects NVIDIA's asset-light fabless model. | D14: Fabless model = low capex intensity vs. foundries (TSMC capex ~25%+).
A15: 3 | B15: D&A Projection | C15: FY2026F D&A = $3,046M (from 11_DA schedule, 5-yr avg useful life). Grows with capex additions. Linked directly from DA schedule. | D15: D&A must track capex spend; using fixed asset roll-forward is most accurate.

Sheet 07_CommonSize
A1: Common-size Balance Sheet
A2: Year | B2: 2021 | C2: 2022 | D2: 2023 | E2: 2024 | F2: 2025
A3: ='02_Historical_BS'!J4 -> Cash & Equivalents | B3: ='02_Historical_BS'!O4 -> 0.029418916 | C3: ='02_Historical_BS'!N4 -> 0.04503587 | D3: ='02_Historical_BS'!M4 -> 0.082293235 | E3: ='02_Historical_BS'!L4 -> 0.11075949 | F3: ='02_Historical_BS'!K4 -> 0.076961676
A4: ='02_Historical_BS'!J5 -> Short-Term Investments | B4: ='02_Historical_BS'!O5 -> 0.37213018 | C4: ='02_Historical_BS'!N5 -> 0.4349243 | D4: ='02_Historical_BS'!M5 -> 0.24056627 | E4: ='02_Historical_BS'!L5 -> 0.2845667 | F4: ='02_Historical_BS'!K5 -> 0.31022123
A5: ='02_Historical_BS'!J6 -> Cash & Short-Term Investments | B5: ='02_Historical_BS'!O6 -> 0.4015491 | C5: ='02_Historical_BS'!N6 -> 0.47996017 | D5: ='02_Historical_BS'!M6 -> 0.3228595 | E5: ='02_Historical_BS'!L6 -> 0.39532619 | F5: ='02_Historical_BS'!K6 -> 0.38718291
A6: ='02_Historical_BS'!J7 -> Receivables | B6: ='02_Historical_BS'!O7 -> 0.084366642 | C6: ='02_Historical_BS'!N7 -> 0.10523457 | D6: ='02_Historical_BS'!M7 -> 0.09292895 | E6: ='02_Historical_BS'!L7 -> 0.15212695 | F6: ='02_Historical_BS'!K7 -> 0.20667378
A7: ='02_Historical_BS'!J8 -> Inventory | B7: ='02_Historical_BS'!O8 -> 0.063422597 | C7: ='02_Historical_BS'!N8 -> 0.058953991 | D7: ='02_Historical_BS'!M8 -> 0.12527318 | E7: ='02_Historical_BS'!L8 -> 0.08036149 | F7: ='02_Historical_BS'!K8 -> 0.090321771
A8: ='02_Historical_BS'!J9 -> Prepaid Expenses | B8: ='02_Historical_BS'!O9 -> 0.0083012052 | C8: ='02_Historical_BS'!N9 -> 0.0082829792 | D8: ='02_Historical_BS'!M9 -> 0.019207421 | E8: ='02_Historical_BS'!L9 -> 0.046859786 | F8: ='02_Historical_BS'!K9 -> 0.03379002
A9: ='02_Historical_BS'!J10 -> Total Current Assets | B9: ='02_Historical_BS'!O10 -> 0.55763954 | C9: ='02_Historical_BS'!N10 -> 0.65243171 | D9: ='02_Historical_BS'!M10 -> 0.56026905 | E9: ='02_Historical_BS'!L10 -> 0.67467442 | F9: ='02_Historical_BS'!K10 -> 0.71796848
A10: ='02_Historical_BS'!J11 -> Property, Plant & Equipment | B10: ='02_Historical_BS'!O11 -> 0.074641381 | C10: ='02_Historical_BS'!N11 -> 0.06286917 | D10: ='02_Historical_BS'!M11 -> 0.0924433 | E10: ='02_Historical_BS'!L11 -> 0.059548442 | F10: ='02_Historical_BS'!K11 -> 0.056298779
A11: ='02_Historical_BS'!J12 -> Long-Term Investments | B11: ='02_Historical_BS'!O12 -> 0.024556285 | C11: ='02_Historical_BS'!N12 -> 0.018761174 | D11: ='02_Historical_BS'!M12 -> 0.025205187 | E11: ='02_Historical_BS'!L12 -> 0.020478335 | F11: ='02_Historical_BS'!K12 -> 0.016066164
A12: ='02_Historical_BS'!J13 -> Goodwill | B12: ='02_Historical_BS'!O13 -> 0.14563579 | C12: ='02_Historical_BS'!N13 -> 0.098422613 | D12: ='02_Historical_BS'!M13 -> 0.10616289 | E12: ='02_Historical_BS'!L13 -> 0.067398978 | F12: ='02_Historical_BS'!K13 -> 0.046487039
A13: ='02_Historical_BS'!J14 -> Other Intangible Assets | B13: ='02_Historical_BS'!O14 -> 0.09506443 | C13: ='02_Historical_BS'!N14 -> 0.052934121 | D13: ='02_Historical_BS'!M14 -> 0.040697392 | E13: ='02_Historical_BS'!L14 -> 0.016918208 | F13: ='02_Historical_BS'!K14 -> 0.007231118
A14: ='02_Historical_BS'!J15 -> Long-Term Deferred Tax Assets | B14: ='02_Historical_BS'!O15 -> 0.02799486 | C14: ='02_Historical_BS'!N15 -> 0.027655193 | D14: ='02_Historical_BS'!M15 -> 0.082463212 | E14: ='02_Historical_BS'!L15 -> 0.092517648 | F14: ='02_Historical_BS'!K15 -> 0.098377255
... A36: ='02_Historical_BS'!J37 -> Shareholders' Equity | B36: ='02_Historical_BS'!O37 -> 1 | C36: ='02_Historical_BS'!N37 -> 1 | D36: ='02_Historical_BS'!M37 -> 1 | E36: ='02_Historical_BS'!L37 -> 1 | F36: ='02_Historical_BS'!K37 -> 1
A39: Common-Size Income Statements
B40: 2020 | C40: 2021 | D40: 2022 | E40: 2023 | F40: 2024 | G40: 2025
A41: Revenue | B41: ='01_Historical_IS'!B3/'01_Historical_IS'!B3 -> 1 | C41: ='01_Historical_IS'!C3/'01_Historical_IS'!C3 -> 1 | D41: ='01_Historical_IS'!D3/'01_Historical_IS'!D3 -> 1 | E41: ='01_Historical_IS'!E3/'01_Historical_IS'!E3 -> 1 | F41: ='01_Historical_IS'!F3/'01_Historical_IS'!F3 -> 1 | G41: ='01_Historical_IS'!G3/'01_Historical_IS'!G3 -> 1
A42: Cost of revenue | B42: ='01_Historical_IS'!B4/'01_Historical_IS'!B3 -> 0.38010625 | C42: ='01_Historical_IS'!C4/'01_Historical_IS'!C3 -> 0.37655172 | D42: ='01_Historical_IS'!D4/'01_Historical_IS'!D3 -> 0.35070967 | E42: ='01_Historical_IS'!E4/'01_Historical_IS'!E3 -> 0.43071106 | F42: ='01_Historical_IS'!F4/'01_Historical_IS'!F3 -> 0.27282427 | G42: ='01_Historical_IS'!G4/'01_Historical_IS'!G3 -> 0.25011303
A44: Gross profit | B44: ='01_Historical_IS'!B5/'01_Historical_IS'!B3 -> 0.61989375 | C44: ='01_Historical_IS'!C5/'01_Historical_IS'!C3 -> 0.62344828 | D44: ='01_Historical_IS'!D5/'01_Historical_IS'!D3 -> 0.64929033 | E44: ='01_Historical_IS'!E5/'01_Historical_IS'!E3 -> 0.56928894 | F44: ='01_Historical_IS'!F5/'01_Historical_IS'!F3 -> 0.72717573 | G44: ='01_Historical_IS'!G5/'01_Historical_IS'!G3 -> 0.74988697
A45: Operating expenses
A46: Research and development | B46: ='01_Historical_IS'!B8/'01_Historical_IS'!B3 -> 0.25911339 | C46: ='01_Historical_IS'!C8/'01_Historical_IS'!C3 -> 0.23532234 | D46: ='01_Historical_IS'!D8/'01_Historical_IS'!D3 -> 0.19573456 | E46: ='01_Historical_IS'!E8/'01_Historical_IS'!E3 -> 0.27207681 | F46: ='01_Historical_IS'!F8/'01_Historical_IS'!F3 -> 0.14239519 | G46: ='01_Historical_IS'!G8/'01_Historical_IS'!G3 -> 0.098960129
A47: Sales, general and administrative | B47: ='01_Historical_IS'!B9/'01_Historical_IS'!B3 -> 0.10010991 | C47: ='01_Historical_IS'!C9/'01_Historical_IS'!C3 -> 0.11634183 | D47: ='01_Historical_IS'!D9/'01_Historical_IS'!D3 -> 0.080478561 | E47: ='01_Historical_IS'!E9/'01_Historical_IS'!E3 -> 0.090457478 | F47: ='01_Historical_IS'!F9/'01_Historical_IS'!F3 -> 0.043563901 | G47: ='01_Historical_IS'!G9/'01_Historical_IS'!G3 -> 0.026751573
A48: Acquisition termination cost
A49: Total operating expenses | B49: ='01_Historical_IS'!B11/'01_Historical_IS'!B3 -> 0.3592233 | C49: ='01_Historical_IS'!C11/'01_Historical_IS'!C3 -> 0.35166417 | D49: ='01_Historical_IS'!D11/'01_Historical_IS'!D3 -> 0.27621312 | E49: ='01_Historical_IS'!E11/'01_Historical_IS'!E3 -> 0.41269371 | F49: ='01_Historical_IS'!F11/'01_Historical_IS'!F3 -> 0.1859591 | G49: ='01_Historical_IS'!G11/'01_Historical_IS'!G3 -> 0.1257117
A50: EBIT (Operating income) | B50: ='01_Historical_IS'!B12/'01_Historical_IS'!B3 -> 0.26067045 | C50: ='01_Historical_IS'!C12/'01_Historical_IS'!C3 -> 0.27178411 | D50: ='01_Historical_IS'!D12/'01_Historical_IS'!D3 -> 0.37307721 | E50: ='01_Historical_IS'!E12/'01_Historical_IS'!E3 -> 0.15659524 | F50: ='01_Historical_IS'!F12/'01_Historical_IS'!F3 -> 0.54121664 | G50: ='01_Historical_IS'!G12/'01_Historical_IS'!G3 -> 0.62417527
A51: Interest income | B51: ='01_Historical_IS'!B15/'01_Historical_IS'!B3 -> 0.016303352 | C51: ='01_Historical_IS'!C15/'01_Historical_IS'!C3 -> 0.0034182909 | D51: ='01_Historical_IS'!D15/'01_Historical_IS'!D3 -> 0.0010775061 | E51: ='01_Historical_IS'!E15/'01_Historical_IS'!E3 -> 0.0098984207 | F51: ='01_Historical_IS'!F15/'01_Historical_IS'!F3 -> 0.014214898 | G51: ='01_Historical_IS'!G15/'01_Historical_IS'!G3 -> 0.013686138
A52: Interest expense | B52: ='01_Historical_IS'!B16/'01_Historical_IS'!B3 -> -0.0047627771 | C52: ='01_Historical_IS'!C16/'01_Historical_IS'!C3 -> -0.011034483 | D52: ='01_Historical_IS'!D16/'01_Historical_IS'!D3 -> -0.0087686706 | E52: ='01_Historical_IS'!E16/'01_Historical_IS'!E3 -> -0.009713057 | F52: ='01_Historical_IS'!F16/'01_Historical_IS'!F3 -> -0.0042185089 | G52: ='01_Historical_IS'!G16/'01_Historical_IS'!G3 -> -0.0018927638
A53: Other, net | B53: ='01_Historical_IS'!B17/'01_Historical_IS'!B3 -> -0.00018318373 | C53: ='01_Historical_IS'!C17/'01_Historical_IS'!C3 -> 0.00023988006 | D53: ='01_Historical_IS'!D17/'01_Historical_IS'!D3 -> 0.0039756261 | E53: ='01_Historical_IS'!E17/'01_Historical_IS'!E3 -> -0.0017794914 | F53: ='01_Historical_IS'!F17/'01_Historical_IS'!F3 -> 0.0038902203 | G53: ='01_Historical_IS'!G17/'01_Historical_IS'!G3 -> 0.0079235538
A54: Other income (expense), net | B54: ='01_Historical_IS'!B18/'01_Historical_IS'!B3 -> 0.011357391 | C54: ='01_Historical_IS'!C18/'01_Historical_IS'!C3 -> -0.0073763118 | D54: ='01_Historical_IS'!D18/'01_Historical_IS'!D3 -> -0.0037155384 | E54: ='01_Historical_IS'!E18/'01_Historical_IS'!E3 -> -0.0015941277 | F54: ='01_Historical_IS'!F18/'01_Historical_IS'!F3 -> 0.013886609 | G54: ='01_Historical_IS'!G18/'01_Historical_IS'!G3 -> 0.019716928
A55: Income before income tax | B55: ='01_Historical_IS'!B19/'01_Historical_IS'!B3 -> 0.27202784 | C55: ='01_Historical_IS'!C19/'01_Historical_IS'!C3 -> 0.2644078 | D55: ='01_Historical_IS'!D19/'01_Historical_IS'!D3 -> 0.36936167 | E55: ='01_Historical_IS'!E19/'01_Historical_IS'!E3 -> 0.15500111 | F55: ='01_Historical_IS'!F19/'01_Historical_IS'!F3 -> 0.55510325 | G55: ='01_Historical_IS'!G19/'01_Historical_IS'!G3 -> 0.6438922
A56: Income tax expense (benefit) | B56: ='01_Historical_IS'!B20/'01_Historical_IS'!B3 -> 0.015936985 | C56: ='01_Historical_IS'!C20/'01_Historical_IS'!C3 -> 0.0046176912 | D56: ='01_Historical_IS'!D20/'01_Historical_IS'!D3 -> 0.0070223675 | E56: ='01_Historical_IS'!E20/'01_Historical_IS'!E3 -> -0.0069326018 | F56: ='01_Historical_IS'!F20/'01_Historical_IS'!F3 -> 0.066609763 | G56: ='01_Historical_IS'!G20/'01_Historical_IS'!G3 -> 0.085411925
A57: Net income | B57: ='01_Historical_IS'!B21/'01_Historical_IS'!B3 -> 0.25609086 | C57: ='01_Historical_IS'!C21/'01_Historical_IS'!C3 -> 0.2597901 | D57: ='01_Historical_IS'!D21/'01_Historical_IS'!D3 -> 0.3623393 | E57: ='01_Historical_IS'!E21/'01_Historical_IS'!E3 -> 0.16193371 | F57: ='01_Historical_IS'!F21/'01_Historical_IS'!F3 -> 0.48849348 | G57: ='01_Historical_IS'!G21/'01_Historical_IS'!G3 -> 0.55848027
A60: Common-size Cashflow statement
A61: Year | B61: 2023 | C61: 2024 | D61: 2025 | E61: 2024 | F61: 2025
A62: ='03_Historical_CF'!I4 -> Net income | B62: ='03_Historical_CF'!J4 -> 0.16193371 | C62: ='03_Historical_CF'!K4 -> 0.48849348 | D62: ='03_Historical_CF'!L4 -> 0.55848027
A63: ='03_Historical_CF'!I5 -> Adjustments to reconcile net income to net cash provided by operating activities:
A64: ='03_Historical_CF'!I6 -> Stock-based compensation expense | B64: ='03_Historical_CF'!J6 -> 0.10043004 | C64: ='03_Historical_CF'!K6 -> 0.058254818 | D64: ='03_Historical_CF'!L6 -> 0.036299685
A65: ='03_Historical_CF'!I7 -> Depreciation and amortization | B65: ='03_Historical_CF'!J7 -> 0.057240305 | C65: ='03_Historical_CF'!K7 -> 0.024752963 | D65: ='03_Historical_CF'!L7 -> 0.014283853
A66: ='03_Historical_CF'!I8 -> Deferred income taxes | B66: ='03_Historical_CF'!J8 -> -0.080225402 | C66: ='03_Historical_CF'!K8 -> -0.04085552 | D66: ='03_Historical_CF'!L8 -> -0.034307302
A67: ='03_Historical_CF'!I9 -> (Gains) losses on non-marketable equity securities and publicly-held equity securities, net | B67: ='03_Historical_CF'!J9 -> 0.0016682732 | C67: ='03_Historical_CF'!K9 -> -0.0039066347 | D67: ='03_Historical_CF'!L9 -> -0.0078929018
A68: ='03_Historical_CF'!I10 -> Acquisition termination cost | B68: ='03_Historical_CF'!J10 -> 0.050159413 | C68: ='03_Historical_CF'!K10 -> 0 | D68: ='03_Historical_CF'!L10 -> 0
A69: ='03_Historical_CF'!I11 -> Other | B69: ='03_Historical_CF'!J11 -> -0.00025950916 | C69: ='03_Historical_CF'!K11 -> -0.004563212 | D69: ='03_Historical_CF'!L11 -> -0.0038468317
A70: ='03_Historical_CF'!I12 -> Changes in operating assets and liabilities, net of acquisitions:
A71: ='03_Historical_CF'!I13 -> Accounts receivable | B71: ='03_Historical_CF'!J13 -> 0.03047379 | C71: ='03_Historical_CF'!K13 -> -0.10130987 | D71: ='03_Historical_CF'!L13 -> -0.10010192
A72: ='03_Historical_CF'!I14 -> Inventories | B72: ='03_Historical_CF'!J14 -> -0.09468377 | C72: ='03_Historical_CF'!K14 -> -0.0016086143 | D72: ='03_Historical_CF'!L14 -> -0.036636858
A73: ='03_Historical_CF'!I15 -> Prepaid expenses and other assets | B73: ='03_Historical_CF'!J15 -> -0.056239342 | C73: ='03_Historical_CF'!K15 -> -0.024982765 | D73: ='03_Historical_CF'!L15 -> -0.0030268895
A74: ='03_Historical_CF'!I16 -> Accounts payable | B74: ='03_Historical_CF'!J16 -> -0.020427078 | C74: ='03_Historical_CF'!K16 -> 0.025130495 | D74: ='03_Historical_CF'!L16 -> 0.025724729
A75: ='03_Historical_CF'!I17 -> Accrued and other current liabilities | B75: ='03_Historical_CF'!J17 -> 0.04971454 | C75: ='03_Historical_CF'!K17 -> 0.033239224 | D75: ='03_Historical_CF'!L17 -> 0.032782363
A76: ='03_Historical_CF'!I18 -> Other long-term liabilities | B76: ='03_Historical_CF'!J18 -> 0.0093423297 | C76: ='03_Historical_CF'!K18 -> 0.0084370178 | D76: ='03_Historical_CF'!L18 -> 0.0093565369
A77: ='03_Historical_CF'!I19 -> Net cash provided by operating activities | B77: ='03_Historical_CF'!J19 -> 0.20912731 | C77: ='03_Historical_CF'!K19 -> 0.46108138 | D77: ='03_Historical_CF'!L19 -> 0.49111474
A78: ='03_Historical_CF'!I20 -> Cash flows from investing activities:
A79: ='03_Historical_CF'!I21 -> Proceeds from maturities of marketable securities | B79: ='03_Historical_CF'!J21 -> 0.72013791 | C79: ='03_Historical_CF'!K21 -> 0.15974525 | D79: ='03_Historical_CF'!L21 -> 0.085787413
A80: ='03_Historical_CF'!I22 -> Proceeds from sales of marketable securities | B80: ='03_Historical_CF'!J22 -> 0.066953362 | C80: ='03_Historical_CF'!K22 -> 0.00082072158 | D80: ='03_Historical_CF'!L22 -> 0.0037931906
A81: ='03_Historical_CF'!I23 -> Proceeds from sales of non-marketable equity securities | B81: ='03_Historical_CF'!J23 -> 0.00029658189 | C81: ='03_Historical_CF'!K23 -> 1.6414432e-05 | D81: ='03_Historical_CF'!L23 -> 0.001310375
A82: ='03_Historical_CF'!I24 -> Purchases of marketable securities | B82: ='03_Historical_CF'!J24 -> -0.44105435 | C82: ='03_Historical_CF'!K24 -> -0.29892321 | D82: ='03_Historical_CF'!L24 -> -0.20364453
A83: ='03_Historical_CF'!I25 -> Purchases related to property and equipment and intangible assets | B83: ='03_Historical_CF'!J25 -> -0.067954326 | C83: ='03_Historical_CF'!K25 -> -0.017547027 | D83: ='03_Historical_CF'!L25 -> -0.024797505
A84: ='03_Historical_CF'!I26 -> Purchases of non-marketable equity securities | B84: ='03_Historical_CF'!J26 -> -0.0031511826 | C84: ='03_Historical_CF'!K26 -> -0.01414924 | D84: ='03_Historical_CF'!L26 -> -0.011387235
A85: ='03_Historical_CF'!I27 -> Acquisitions, net of cash acquired | B85: ='03_Historical_CF'!J27 -> -0.0018165641 | C85: ='03_Historical_CF'!K27 -> -0.0013623978 | D85: ='03_Historical_CF'!L27 -> -0.0077166525
A86: ='03_Historical_CF'!I28 -> Other | B86: ='03_Historical_CF'!J28 -> 0 | C86: ='03_Historical_CF'!K28 -> -0.0020353895 | D86: ='03_Historical_CF'!L28 -> 0.00016858625
A87: ='03_Historical_CF'!I29 -> Net cash provided by (used in) investing activities | B87: ='03_Historical_CF'!J29 -> 0.27341143 | C87: ='03_Historical_CF'!K29 -> -0.17343488 | D87: ='03_Historical_CF'!L29 -> -0.15648636
A88: ='03_Historical_CF'!I30 -> Cash flows from financing activities:
A89: ='03_Historical_CF'!I31 -> Proceeds related to employee stock plans | B89: ='03_Historical_CF'!J31 -> 0.013160822 | C89: ='03_Historical_CF'!K31 -> 0.0066150159 | D89: ='03_Historical_CF'!L31 -> 0.0037548756
A90: ='03_Historical_CF'!I32 -> Payments related to repurchases of common stock | B90: ='03_Historical_CF'!J32 -> -0.3721732 | C90: ='03_Historical_CF'!K32 -> -0.15647878 | D90: ='03_Historical_CF'!L32 -> -0.25828946
A91: ='03_Historical_CF'!I33 -> Payments related to tax on restricted stock units | B91: ='03_Historical_CF'!J33 -> -0.054682287 | C91: ='03_Historical_CF'!K33 -> -0.045681363 | D91: ='03_Historical_CF'!L33 -> -0.053104669
A92: ='03_Historical_CF'!I34 -> Repayment of debt | B92: ='03_Historical_CF'!J34 -> 0 | C92: ='03_Historical_CF'!K34 -> -0.020518039 | D92: ='03_Historical_CF'!L34 -> -0.0095787643
A93: ='03_Historical_CF'!I35 -> Dividends paid | B93: ='03_Historical_CF'!J35 -> -0.014754949 | C93: ='03_Historical_CF'!K35 -> -0.0064837005 | D93: ='03_Historical_CF'!L35 -> -0.0063909515
A94: ='03_Historical_CF'!I36 -> Principal payments on property and equipment and intangible assets | B94: ='03_Historical_CF'!J36 -> -0.0021502187 | C94: ='03_Historical_CF'!K36 -> -0.0012146679 | D94: ='03_Historical_CF'!L36 -> -0.00098852847
A95: ='03_Historical_CF'!I37 -> Other | B95: ='03_Historical_CF'!J37 -> -7.4145473e-05 | C95: ='03_Historical_CF'!K37 -> -1.6414432e-05 | D95: ='03_Historical_CF'!L37 -> 0
A96: ='03_Historical_CF'!I38 -> Net cash used in financing activities | B96: ='03_Historical_CF'!J38 -> -0.43067398 | C96: ='03_Historical_CF'!K38 -> -0.22377795 | D96: ='03_Historical_CF'!L38 -> -0.3245975
A97: ='03_Historical_CF'!I39 -> Change in cash and cash equivalents | B97: ='03_Historical_CF'!J39 -> 0.051864759 | C97: ='03_Historical_CF'!K39 -> 0.063868553 | D97: ='03_Historical_CF'!L39 -> 0.010030882
A98: ='03_Historical_CF'!I40 -> Cash and cash equivalents at beginning of period | B98: ='03_Historical_CF'!J40 -> 0.073774746 | C98: ='03_Historical_CF'!K40 -> 0.055628509 | D98: ='03_Historical_CF'!L40 -> 0.055786723
A99: ='03_Historical_CF'!I41 -> Cash and cash equivalents at end of period | B99: ='03_Historical_CF'!J41 -> 0.1256395 | C99: ='03_Historical_CF'!K41 -> 0.11949706 | D99: ='03_Historical_CF'!L41 -> 0.065817605
A100: ='03_Historical_CF'!I42 -> Supplemental disclosures of cash flow information:
A101: ='03_Historical_CF'!I43 -> Cash paid for income taxes, net | B101: ='03_Historical_CF'!J43 -> 0.052050122 | C101: ='03_Historical_CF'!K43 -> 0.10749811 | D101: ='03_Historical_CF'!L43 -> 0.11584941
A102: ='03_Historical_CF'!I44 -> Cash paid for interest | B102: ='03_Historical_CF'!J44 -> 0.0094164751 | C102: ='03_Historical_CF'!K44 -> 0.0041364368 | D102: ='03_Historical_CF'!L44 -> 0.0018851008

Sheet 08_RatioAnalysis
A1: Ratio Analysis of NVIDIA | K1: Return and Solvency Ratios
A2: Years | C2: 2020 | D2: 2021 | E2: 2022 | F2: 2023 | G2: 2024 | H2: 2025 | K2: Return on Capital Employed (ROCE) | M2: 0 | N2: =('01_Historical_IS'!C12/('02_Historical_BS'!B17-'02_Historical_BS'!B25)) -> 0.1822569 | O2: =('01_Historical_IS'!D12/('02_Historical_BS'!C17-'02_Historical_BS'!C25)) -> 0.25195724 | P2: =('01_Historical_IS'!E12/('02_Historical_BS'!D17-'02_Historical_BS'!D25)) -> 0.12201392 | Q2: =('01_Historical_IS'!F12/('02_Historical_BS'!E17-'02_Historical_BS'!E25)) -> 0.59843549 | R2: =('01_Historical_IS'!G12/('02_Historical_BS'!F17-'02_Historical_BS'!F25)) -> 0.87065224
A3: Growth Analysis | K3: Retained Earnings% | M3: 0 | N3: ='02_Historical_BS'!B34/'01_Historical_IS'!C21 -> 4.3647276 | O3: ='02_Historical_BS'!C34/'01_Historical_IS'!D21 -> 1.6647867 | P3: ='02_Historical_BS'!D34/'01_Historical_IS'!E21 -> 2.3285256 | Q3: ='02_Historical_BS'!E34/'01_Historical_IS'!F21 -> 1.0019153 | R3: ='02_Historical_BS'!F34/'01_Historical_IS'!G21 -> 0.93356202
A4: SalesGrowth | C4: ='10_GrowthRates'!I3 -> -0.068111984 | D4: ='10_GrowthRates'!J3 -> 0.52729438 | E4: ='10_GrowthRates'!K3 -> 0.61403298 | F4: ='10_GrowthRates'!L3 -> 0.002229323 | G4: ='10_GrowthRates'!M3 -> 1.2585453 | H4: ='10_GrowthRates'!N3 -> 1.1420341 | K4: Return on Equity% (ROE) | M4: 0 | N4: ='01_Historical_IS'!C21/'02_Historical_BS'!B37 -> 0.25643758 | O4: ='01_Historical_IS'!D21/'02_Historical_BS'!C37 -> 0.36645123 | P4: ='01_Historical_IS'!E21/'02_Historical_BS'!D37 -> 0.19763812 | Q4: ='01_Historical_IS'!F21/'02_Historical_BS'!E37 -> 0.6924473 | R4: ='01_Historical_IS'!G21/'02_Historical_BS'!F37 -> 0.91872881
A5: GrossMargin | C5: 0 | D5: =('01_Historical_IS'!C5/'01_Historical_IS'!B5)-1 -> 0.53605201 | E5: =('01_Historical_IS'!D5/'01_Historical_IS'!C5)-1 -> 0.68093497 | F5: =('01_Historical_IS'!E5/'01_Historical_IS'!D5)-1 -> -0.12125894 | G5: =('01_Historical_IS'!F5/'01_Historical_IS'!E5)-1 -> 1.884931 | H5: =('01_Historical_IS'!G5/'01_Historical_IS'!F5)-1 -> 1.2089343 | K5: Self Sustained Growth Rate | M5: 0 | N5: =N3*N4 -> 1.1192802 | O5: =O3*O4 -> 0.61006313 | P5: =P3*P4 -> 0.46020542 | Q5: =Q3*Q4 -> 0.69377356 | R5: =R3*R4 -> 0.85769032
A6: EBITDA Growth | C6: 0 | D6: =('01_Historical_IS'!C14/'01_Historical_IS'!B14)-1 -> 0.74465448 | E6: =('01_Historical_IS'!D14/'01_Historical_IS'!C14)-1 -> 0.9920071 | F6: =('01_Historical_IS'!E14/'01_Historical_IS'!D14)-1 -> -0.48568881 | G6: =('01_Historical_IS'!F14/'01_Historical_IS'!E14)-1 -> 4.9778086 | H6: =('01_Historical_IS'!G14/'01_Historical_IS'!F14)-1 -> 1.4163863 | K6: Interest Coverage Ratio | M6: ='01_Historical_IS'!B12/-'01_Historical_IS'!B16 -> 54.730769 | N6: ='01_Historical_IS'!C12/-'01_Historical_IS'!C16 -> 24.630435 | O6: ='01_Historical_IS'!D12/-'01_Historical_IS'!D16 -> 42.54661 | P6: ='01_Historical_IS'!E12/-'01_Historical_IS'!E16 -> 16.122137 | Q6: ='01_Historical_IS'!F12/-'01_Historical_IS'!F16 -> 128.29572 | R6: ='01_Historical_IS'!G12/-'01_Historical_IS'!G16 -> 329.76923
A7: EBIT Growth | C7: 0 | D7: =('01_Historical_IS'!C12/'01_Historical_IS'!B12)-1 -> 0.5924104 | E7: =('01_Historical_IS'!D12/'01_Historical_IS'!C12)-1 -> 1.2155781 | F7: =('01_Historical_IS'!E12/'01_Historical_IS'!D12)-1 -> -0.57932477 | G7: =('01_Historical_IS'!F12/'01_Historical_IS'!E12)-1 -> 6.8058712 | H7: =('01_Historical_IS'!G12/'01_Historical_IS'!F12)-1 -> 1.4703688
A8: Net Profit Growth | C8: 0 | D8: =('01_Historical_IS'!C21/'01_Historical_IS'!B21)-1 -> 0.54935622 | E8: =('01_Historical_IS'!D21/'01_Historical_IS'!C21)-1 -> 1.2511542 | F8: =('01_Historical_IS'!E21/'01_Historical_IS'!D21)-1 -> -0.55209188 | G8: =('01_Historical_IS'!F21/'01_Historical_IS'!E21)-1 -> 5.8131868 | H8: =('01_Historical_IS'!G21/'01_Historical_IS'!F21)-1 -> 1.4489247 | K8: Operational Efficiency Ratios
K9: Debtor Turnover Ratio | N9: ='01_Historical_IS'!C3/'02_Historical_BS'!B7 -> 6.864965 | O9: ='01_Historical_IS'!D3/'02_Historical_BS'!C7 -> 5.787957 | P9: ='01_Historical_IS'!E3/'02_Historical_BS'!D7 -> 7.0483407 | Q9: ='01_Historical_IS'!F3/'02_Historical_BS'!E7 -> 6.0928093 | R9: ='01_Historical_IS'!G3/'02_Historical_BS'!F7 -> 5.6577932
A10: Profitability Ratio | K10: Creditor Turnover Ratio | N10: ='01_Historical_IS'!C4/'02_Historical_BS'!B18 -> 5.464752 | O10: ='01_Historical_IS'!D4/'02_Historical_BS'!C18 -> 5.2938867 | P10: ='01_Historical_IS'!E4/'02_Historical_BS'!D18 -> 9.7384744 | Q10: ='01_Historical_IS'!F4/'02_Historical_BS'!E18 -> 6.1582067 | R10: ='01_Historical_IS'!G4/'02_Historical_BS'!F18 -> 5.1725832
A11: Gross Margin | C11: ='01_Historical_IS'!B5/'01_Historical_IS'!B3 -> 0.61989375 | D11: ='01_Historical_IS'!C5/'01_Historical_IS'!C3 -> 0.62344828 | E11: ='01_Historical_IS'!D5/'01_Historical_IS'!D3 -> 0.64929033 | F11: ='01_Historical_IS'!E5/'01_Historical_IS'!E3 -> 0.56928894 | G11: ='01_Historical_IS'!F5/'01_Historical_IS'!F3 -> 0.72717573 | H11: ='01_Historical_IS'!G5/'01_Historical_IS'!G3 -> 0.74988697 | K11: Inventory Turnover | N11: ='01_Historical_IS'!C4/'02_Historical_BS'!B8 -> 3.4386637 | O11: ='01_Historical_IS'!D4/'02_Historical_BS'!C8 -> 3.6234165 | P11: ='01_Historical_IS'!E4/'02_Historical_BS'!D8 -> 2.2519868 | Q11: ='01_Historical_IS'!F4/'02_Historical_BS'!E8 -> 3.1467247 | R11: ='01_Historical_IS'!G4/'02_Historical_BS'!F8 -> 3.237996
A12: Operating Margin | C12: ='01_Historical_IS'!B12/'01_Historical_IS'!B3 -> 0.26067045 | D12: ='01_Historical_IS'!C12/'01_Historical_IS'!C3 -> 0.27178411 | E12: ='01_Historical_IS'!D12/'01_Historical_IS'!D3 -> 0.37307721 | F12: ='01_Historical_IS'!E12/'01_Historical_IS'!E3 -> 0.15659524 | G12: ='01_Historical_IS'!F12/'01_Historical_IS'!F3 -> 0.54121664 | H12: ='01_Historical_IS'!G12/'01_Historical_IS'!G3 -> 0.62417527 | K12: Fixed Asset Turnover | N12: ='01_Historical_IS'!C3/'12_FixedAssets'!D12 -> 14.782801 | O12: ='01_Historical_IS'!D3/'12_FixedAssets'!E12 -> 8.61248 | P12: ='01_Historical_IS'!E3/'12_FixedAssets'!F12 -> 5.8499241 | Q12: ='01_Historical_IS'!F3/'12_FixedAssets'!G12 -> 12.494258 | R12: ='01_Historical_IS'!G3/'12_FixedAssets'!H12 -> 18.251329
A13: EBITDA Margin | C13: ='01_Historical_IS'!B14/'01_Historical_IS'!B3 -> 0.29556695 | D13: ='01_Historical_IS'!C14/'01_Historical_IS'!C3 -> 0.33763118 | E13: ='01_Historical_IS'!D14/'01_Historical_IS'!D3 -> 0.41669763 | F13: ='01_Historical_IS'!E14/'01_Historical_IS'!E3 -> 0.21383555 | G13: ='01_Historical_IS'!F14/'01_Historical_IS'!F3 -> 0.5659696 | H13: ='01_Historical_IS'!G14/'01_Historical_IS'!G3 -> 0.63845912 | K13: Capital Turnover Ratio | N13: =('01_Historical_IS'!B3/('02_Historical_BS'!B17-'02_Historical_BS'!B25)) -> 0.43907343 | O13: =('01_Historical_IS'!C3/('02_Historical_BS'!C17-'02_Historical_BS'!C25)) -> 0.41842317 | P13: =('01_Historical_IS'!D3/('02_Historical_BS'!D17-'02_Historical_BS'!D25)) -> 0.77743436 | Q13: =('01_Historical_IS'!E3/('02_Historical_BS'!E17-'02_Historical_BS'!E25)) -> 0.48957294 | R13: =('01_Historical_IS'!F3/('02_Historical_BS'!F17-'02_Historical_BS'!F25)) -> 0.6511961
A14: EBIT Margin | C14: ='01_Historical_IS'!B12/'01_Historical_IS'!B3 -> 0.26067045 | D14: ='01_Historical_IS'!C12/'01_Historical_IS'!C3 -> 0.27178411 | E14: ='01_Historical_IS'!D12/'01_Historical_IS'!D3 -> 0.37307721 | F14: ='01_Historical_IS'!E12/'01_Historical_IS'!E3 -> 0.15659524 | G14: ='01_Historical_IS'!F12/'01_Historical_IS'!F3 -> 0.54121664 | H14: ='01_Historical_IS'!G12/'01_Historical_IS'!G3 -> 0.62417527 | K14: Payable Days | N14: =365/N10 -> 66.791687 | O14: =365/O10 -> 68.947452 | P14: =365/P10 -> 37.480203 | Q14: =365/Q10 -> 59.270501 | R14: =365/R10 -> 70.564356
A15: EBT Margin | C15: ='01_Historical_IS'!B19/'01_Historical_IS'!B3 -> 0.27202784 | D15: ='01_Historical_IS'!C19/'01_Historical_IS'!C3 -> 0.2644078 | E15: ='01_Historical_IS'!D19/'01_Historical_IS'!D3 -> 0.36936167 | F15: ='01_Historical_IS'!E19/'01_Historical_IS'!E3 -> 0.15500111 | G15: ='01_Historical_IS'!F19/'01_Historical_IS'!F3 -> 0.55510325 | H15: ='01_Historical_IS'!G19/'01_Historical_IS'!G3 -> 0.6438922 | K15: Inventory Days | N15: =365/N11 -> 106.14588 | O15: =365/O11 -> 100.73366 | P15: =365/P11 -> 162.0791 | Q15: =365/Q11 -> 115.99362 | R15: =365/R11 -> 112.72404
A16: Net Profit Margin | C16: ='01_Historical_IS'!B21/'01_Historical_IS'!B3 -> 0.25609086 | D16: ='01_Historical_IS'!C21/'01_Historical_IS'!C3 -> 0.2597901 | E16: ='01_Historical_IS'!D21/'01_Historical_IS'!D3 -> 0.3623393 | F16: ='01_Historical_IS'!E21/'01_Historical_IS'!E3 -> 0.16193371 | G16: ='01_Historical_IS'!F21/'01_Historical_IS'!F3 -> 0.48849348 | H16: ='01_Historical_IS'!G21/'01_Historical_IS'!G3 -> 0.55848027 | K16: Receivables Days | N16: =365/N9 -> 53.168516 | O16: =365/O9 -> 63.061975 | P16: =365/P9 -> 51.785238 | Q16: =365/Q9 -> 59.906684 | R16: =365/R9 -> 64.512786
K17: Cash Conversion Cycle | N17: =(N16+N15)-N14 -> 92.522712 | O17: =(O16+O15)-O14 -> 94.848181 | P17: =(P16+P15)-P14 -> 176.38414 | Q17: =(Q16+Q15)-Q14 -> 116.62981 | R17: =(R16+R15)-R14 -> 106.67247
A18: Liquidity Ratios
A19: Current Ratio | C19: 0 | D19: ='02_Historical_BS'!B10/'02_Historical_BS'!B25 -> 4.0904459 | E19: ='02_Historical_BS'!C10/'02_Historical_BS'!C25 -> 6.6502884 | F19: ='02_Historical_BS'!D10/'02_Historical_BS'!D25 -> 3.5156179 | G19: ='02_Historical_BS'!E10/'02_Historical_BS'!E25 -> 4.1712915 | H19: ='02_Historical_BS'!F10/'02_Historical_BS'!F25 -> 4.4398515 | K19: Cash Flow Performance Ratios
A20: Quik Ratio | C20: 0 | D20: =('02_Historical_BS'!B6+'02_Historical_BS'!B7)/'02_Historical_BS'!B25 -> 3.5643312 | E20: =('02_Historical_BS'!C6+'02_Historical_BS'!C7)/'02_Historical_BS'!C25 -> 5.9649366 | F20: =('02_Historical_BS'!D6+'02_Historical_BS'!D7)/'02_Historical_BS'!D25 -> 2.6090203 | G20: =('02_Historical_BS'!E6+'02_Historical_BS'!E7)/'02_Historical_BS'!E25 -> 3.3847239 | H20: =('02_Historical_BS'!F6+'02_Historical_BS'!F7)/'02_Historical_BS'!F25 -> 3.6723555 | K20: CFO/Sales | P20: ='04c_Projection_CF'!B$19/'01_Historical_IS'!E3 -> 0.20912731 | Q20: ='04c_Projection_CF'!C$19/'01_Historical_IS'!F3 -> 0.46108138 | R20: ='04c_Projection_CF'!D$19/'01_Historical_IS'!G3 -> 0.49111474
A21: Cash Ratio | C21: 0 | D21: ='02_Historical_BS'!B6/'02_Historical_BS'!B25 -> 2.9454777 | E21: ='02_Historical_BS'!C6/'02_Historical_BS'!C25 -> 4.8922722 | F21: ='02_Historical_BS'!D6/'02_Historical_BS'!D25 -> 2.0259028 | G21: ='02_Historical_BS'!E6/'02_Historical_BS'!E25 -> 2.4441727 | H21: ='02_Historical_BS'!F6/'02_Historical_BS'!F25 -> 2.3943038 | K21: CFO/Total Assets | P21: ='04c_Projection_CF'!B$19/'02_Historical_BS'!D17 -> 0.13697732 | Q21: ='04c_Projection_CF'!C$19/'02_Historical_BS'!E17 -> 0.42736733 | R21: ='04c_Projection_CF'!D$19/'02_Historical_BS'!F17 -> 0.57426905
K22: CFO/Total Debt | P22: =('04c_Projection_CF'!B$19/('02_Historical_BS'!B26+'02_Historical_BS'!B20)) -> 0.81013931 | Q22: =('04c_Projection_CF'!C$19/('02_Historical_BS'!C26+'02_Historical_BS'!C20)) -> 2.5662342 | R22: =('04c_Projection_CF'!D$19/('02_Historical_BS'!D26+'02_Historical_BS'!D20)) -> 5.8512736
A23: Solvency Ratios
A24: Debt-to-Equity Ratio | D24: ='02_Historical_BS'!B31/'02_Historical_BS'!B37 -> 0.7043154 | E24: ='02_Historical_BS'!C31/'02_Historical_BS'!C37 -> 0.66041635 | F24: ='02_Historical_BS'!D31/'02_Historical_BS'!D37 -> 0.8633546 | G24: ='02_Historical_BS'!E31/'02_Historical_BS'!E37 -> 0.52934059 | H24: ='02_Historical_BS'!F31/'02_Historical_BS'!F37 -> 0.40684761
A25: Debt Ratio | D25: ='02_Historical_BS'!B31/'02_Historical_BS'!B17 -> 0.41325414 | E25: ='02_Historical_BS'!C31/'02_Historical_BS'!C17 -> 0.39774142 | F25: ='02_Historical_BS'!D31/'02_Historical_BS'!D17 -> 0.4633335 | G25: ='02_Historical_BS'!E31/'02_Historical_BS'!E17 -> 0.34612342 | H25: ='02_Historical_BS'!F31/'02_Historical_BS'!F17 -> 0.28919096
A26: Interest Coverage Ratio | C26: ='01_Historical_IS'!B12/-'01_Historical_IS'!B16 -> 54.730769 | D26: ='01_Historical_IS'!C12/-'01_Historical_IS'!C16 -> 24.630435 | E26: ='01_Historical_IS'!D12/-'01_Historical_IS'!D16 -> 42.54661 | F26: ='01_Historical_IS'!E12/-'01_Historical_IS'!E16 -> 16.122137 | G26: ='01_Historical_IS'!F12/-'01_Historical_IS'!F16 -> 128.29572 | H26: ='01_Historical_IS'!G12/-'01_Historical_IS'!G16 -> 329.76923
A27: Equity Multiplier (leverage ratio) | D27: ='02_Historical_BS'!B17/'02_Historical_BS'!B37 -> 1.7043154 | E27: ='02_Historical_BS'!C17/'02_Historical_BS'!C37 -> 1.6604164 | F27: ='02_Historical_BS'!D17/'02_Historical_BS'!D37 -> 1.8633546 | G27: ='02_Historical_BS'!E17/'02_Historical_BS'!E37 -> 1.5293406 | H27: ='02_Historical_BS'!F17/'02_Historical_BS'!F37 -> 1.4068476
A29: Operating Efficiency Ratios
A30: Sales expenses%Sales | C30: ='01_Historical_IS'!B4/'01_Historical_IS'!B3 -> 0.38010625 | D30: ='01_Historical_IS'!C4/'01_Historical_IS'!C3 -> 0.37655172 | E30: ='01_Historical_IS'!D4/'01_Historical_IS'!D3 -> 0.35070967 | F30: ='01_Historical_IS'!E4/'01_Historical_IS'!E3 -> 0.43071106 | G30: ='01_Historical_IS'!F4/'01_Historical_IS'!F3 -> 0.27282427 | H30: ='01_Historical_IS'!G4/'01_Historical_IS'!G3 -> 0.25011303
A31: Depreciation%Sales | C31: ='01_Historical_IS'!B13/'01_Historical_IS'!B3 -> 0.034896501 | D31: ='01_Historical_IS'!C13/'01_Historical_IS'!C3 -> 0.065847076 | E31: ='01_Historical_IS'!D13/'01_Historical_IS'!D3 -> 0.043620421 | F31: ='01_Historical_IS'!E13/'01_Historical_IS'!E3 -> 0.057240305 | G31: ='01_Historical_IS'!F13/'01_Historical_IS'!F3 -> 0.024752963 | H31: ='01_Historical_IS'!G13/'01_Historical_IS'!G3 -> 0.014283853
A32: OperatingIncome%Sales | C32: ='01_Historical_IS'!B12/'01_Historical_IS'!B3 -> 0.26067045 | D32: ='01_Historical_IS'!C12/'01_Historical_IS'!C3 -> 0.27178411 | E32: ='01_Historical_IS'!D12/'01_Historical_IS'!D3 -> 0.37307721 | F32: ='01_Historical_IS'!E12/'01_Historical_IS'!E3 -> 0.15659524 | G32: ='01_Historical_IS'!F12/'01_Historical_IS'!F3 -> 0.54121664 | H32: ='01_Historical_IS'!G12/'01_Historical_IS'!G3 -> 0.62417527

Sheet 09_WorkingCapital
A1: Working capital schedule
A3: Working capital schedule
A4: ($ in million) | B4: 2021 | C4: 2022 | D4: 2023 | E4: 2024 | F4: 2025 | G4: 2026F | H4: 2027F | I4: 2028F | J4: 2029F | K4: 2030F
A5: Sales | B5: ='01_Historical_IS'!C3 -> 16675 | C5: ='01_Historical_IS'!D3 -> 26914 | D5: ='01_Historical_IS'!E3 -> 26974 | E5: ='01_Historical_IS'!F3 -> 60922 | F5: ='01_Historical_IS'!G3 -> 130497 | G5: ='04a_Projection_IS'!H81 -> 211566.26 | H5: ='04a_Projection_IS'!I81 -> 295121.29 | I5: ='04a_Projection_IS'!J81 -> 371459.26 | J5: ='04a_Projection_IS'!K81 -> 429310.52 | K5: ='04a_Projection_IS'!L81 -> 521670.89
A6: COGS | B6: ='01_Historical_IS'!C4 -> 6279 | C6: ='01_Historical_IS'!D4 -> 9439 | D6: ='01_Historical_IS'!E4 -> 11618 | E6: ='01_Historical_IS'!F4 -> 16621 | F6: ='01_Historical_IS'!G4 -> 32639 | G6: ='04a_Projection_IS'!H82 -> 48684.153 | H6: ='04a_Projection_IS'!I82 -> 62008.827 | I6: ='04a_Projection_IS'!J82 -> 70619.244 | J6: ='04a_Projection_IS'!K82 -> 73031.313 | K6: ='04a_Projection_IS'!L82 -> 78309.598
A7: Total operating expenses | B7: 5864 | C7: 7434 | D7: 11132 | E7: 11329 | F7: 16405 | G7: ='04a_Projection_IS'!H89 -> 25387.951 | H7: ='04a_Projection_IS'!I89 -> 34529.19 | I7: ='04a_Projection_IS'!J89 -> 41974.896 | J7: ='04a_Projection_IS'!K89 -> 47224.157 | K7: ='04a_Projection_IS'!L89 -> 55818.786
A9: Receivables | B9: 2429 | C9: 4650 | D9: 3827 | E9: 9999 | F9: 23065 | G9: =(G22/365)*G5 -> 36814.144 | H9: =(H22/365)*H5 -> 50544.805 | I9: =(I22/365)*I5 -> 62601.352 | J9: =(J22/365)*J5 -> 71174.728 | K9: =(K22/365)*K5 -> 85057.776
A10: Inventory | B10: 1826 | C10: 2605 | D10: 5159 | E10: 5282 | F10: 10080 | G10: =(G26/365)*G6 -> 14671.937 | H10: =(H26/365)*H6 -> 17838.156 | I10: =(I26/365)*I6 -> 19347.738 | J10: =(J26/365)*J6 -> 19008.15 | K10: =(K26/365)*K6 -> 19309.216
A11: Prepaid Expenses | B11: 239 | C11: 366 | D11: 791 | E11: 3080 | F11: 3771 | G11: =G7*G36 -> 5074.263 | H11: =H7*H36 -> 5865.4371 | I11: =I7*I36 -> 5870.9843 | J11: =J7*J36 -> 5666.8989 | K11: =K7*K36 -> 5581.8786
A12: Total short-term operating assets | B12: =SUM(B9:B11) -> 4494 | C12: =SUM(C9:C11) -> 7621 | D12: =SUM(D9:D11) -> 9777 | E12: =SUM(E9:E11) -> 18361 | F12: =SUM(F9:F11) -> 36916 | G12: =SUM(G9:G11) -> 56560.343 | H12: =SUM(H9:H11) -> 74248.398 | I12: =SUM(I9:I11) -> 87820.075 | ... K12: =SUM(K9:K11) -> 109948.87
A14: Accounts Payable | B14: 1149 | C14: 1783 | D14: 1193 | E14: 2699 | F14: 6310 | G14: =(G30/365)*G6 -> 9278.5801 | H14: =(H30/365)*H6 -> 11648.206 | I14: =(I30/365)*I6 -> 13072.175 | J14: =(J30/365)*J6 -> 13318.582 | K14: =(K30/365)*K6 -> 14066.626
A15: Accrued and other current liabilities | B15: =SUM('02_Historical_BS'!B19:B24) -> 2776 | C15: =SUM('02_Historical_BS'!C19:C24) -> 2552 | D15: =SUM('02_Historical_BS'!D19:D24) -> 5370 | E15: =SUM('02_Historical_BS'!E19:E24) -> 7932 | F15: =SUM('02_Historical_BS'!F19:F24) -> 11737 | G15: =(G6+G7)*G37 -> 17726.619 | H15: =(H6+H7)*H37 -> 23103.065 | I15: =(I6+I7)*I37 -> 26945.547 | J15: =(J6+J7)*J37 -> 28779.024 | K15: =(K6+K7)*K37 -> 32099.03
A16: Total short-term operating liabilities | B16: =SUM(B14:B15) -> 3925 | C16: =SUM(C14:C15) -> 4335 | D16: =SUM(D14:D15) -> 6563 | E16: =SUM(E14:E15) -> 10631 | F16: =SUM(F14:F15) -> 18047 | G16: =SUM(G14:G15) -> 27005.199 | H16: =SUM(H14:H15) -> 34751.271 | I16: =SUM(I14:I15) -> 40017.722 | ... K16: =SUM(K14:K15) -> 46165.656
A18: Net Working capital | B18: =B12-B16 -> 569 | C18: =C12-C16 -> 3286 | D18: =D12-D16 -> 3214 | E18: =E12-E16 -> 7730 | F18: =F12-F16 -> 18869 | G18: =G12-G16 -> 29555.145 | H18: =H12-H16 -> 39497.126 | I18: =I12-I16 -> 47802.353 | ... K18: =K12-K16 -> 63783.214
A19: Changes in working capital | C19: =C18-B18 -> 2717 | D19: =D18-C18 -> -72 | E19: =E18-D18 -> 4516 | F19: =F18-E18 -> 11139 | G19: =G18-F18 -> 10686.145 | H19: =H18-G18 -> 9941.9818 | I19: =I18-H18 -> 8305.2265 | J19: =J18-I18 -> 5949.8178 | K19: =K18-J18 -> 10031.044
A21: DSO | B21: =(B9/B5)*365 -> 53.168516 | C21: =(C9/C5)*365 -> 63.061975 | D21: =(D9/D5)*365 -> 51.785238 | E21: =(E9/E5)*365 -> 59.906684 | F21: =(F9/F5)*365 -> 64.512786 | G21: =G22 -> 63.512786 | H21: =H22 -> 62.512786 | I21: =I22 -> 61.512786 | J21: =J22 -> 60.512786 | K21: =K22 -> 59.512786
A22: Base case | G22: =F21-1 -> 63.512786 | H22: =G22-1 -> 62.512786 | I22: =H22-1 -> 61.512786 | J22: =I22-1 -> 60.512786 | K22: =J22-1 -> 59.512786
A23: Upside case | G23: 62 | H23: 60 | I23: 58 | J23: 56 | K23: 54
A24: Downside case | G24: 72 | H24: 74 | I24: 76 | J24: 78 | K24: 80
A25: DIO | B25: =(B10/B6)*365 -> 106.14588 | C25: =(C10/C6)*365 -> 100.73366 | D25: =(D10/D6)*365 -> 162.0791 | E25: =(E10/E6)*365 -> 115.99362 | F25: =(F10/F6)*365 -> 112.72404 | G25: 110 | H25: 105 | I25: 100 | J25: 95 | K25: 90
A26: Base case | G26: 110 | H26: 105 | I26: 100 | J26: 95 | K26: 90
A27: Upside case | G27: 95 | H27: 85 | I27: 75 | J27: 71 | K27: 65
A28: Downside case | G28: 160 | H28: 150 | I28: 140 | J28: 120 | K28: 110
A29: DPO | B29: =(B14/B6)*365 -> 66.791687 | C29: =(C14/C6)*365 -> 68.947452 | D29: =(D14/D6)*365 -> 37.480203 | E29: =(E14/E6)*365 -> 59.270501 | F29: =(F14/F6)*365 -> 70.564356 | G29: =G30 -> 69.564356 | H29: =H30 -> 68.564356 | I29: =I30 -> 67.564356 | J29: =J30 -> 66.564356 | K29: =K30 -> 65.564356
A30: Base case | G30: =F29-1 -> 69.564356 | H30: =G30-1 -> 68.564356 | I30: =H30-1 -> 67.564356 | J30: =I30-1 -> 66.564356 | K30: =J30-1 -> 65.564356
A31: Upside case | G31: 72 | H31: 74 | I31: 76 | J31: 78 | K31: 80
A32: Downside case | G32: 60 | H32: 55 | I32: 50 | J32: 48 | K32: 46
A34: CCC | B34: =(B21+B25)-B29 -> 92.522712 | C34: =(C21+C25)-C29 -> 94.848181 | D34: =(D21+D25)-D29 -> 176.38414 | E34: =(E21+E25)-E29 -> 116.62981 | F34: =(F21+F25)-F29 -> 106.67247 | G34: =(G21+G25)-G29 -> 103.94843 | H34: =(H21+H25)-H29 -> 98.94843 | I34: =(I21+I25)-I29 -> 93.94843 | ... K34: =(K21+K25)-K29 -> 83.94843
A36: Prepaid % of Operating Expenses | B36: =B11/B7 -> 0.040757162 | C36: =C11/C7 -> 0.049233253 | D36: =D11/D7 -> 0.071056414 | E36: =E11/E7 -> 0.27186866 | F36: =F11/F7 -> 0.22986894 | G36: =F36-3% -> 0.19986894 | H36: =G36-3% -> 0.16986894 | I36: =H36-3% -> 0.13986894 | J36: 0.12 | K36: 0.1
A37: Accrued % of COGS + OpEx | B37: =B15/(B6+B7) -> 0.22860908 | C37: =C15/(C6+C7) -> 0.15124756 | D37: =D15/(D6+D7) -> 0.23604396 | E37: =E15/(E6+E7) -> 0.28379249 | F37: =F15/(F6+F7) -> 0.23931572 | G37: =F37 -> 0.23931572 | H37: =G37 -> 0.23931572 | I37: =H37 -> 0.23931572 | J37: =I37 -> 0.23931572 | K37: =J37 -> 0.23931572

Sheet 10_GrowthRates
C1: 2014 | D1: 2015 | E1: 2016 | F1: 2017 | G1: 2018 | H1: 2019 | I1: 2020 | J1: 2021 | K1: 2022 | L1: 2023 | M1: 2024 | N1: 2025
B2: Revenue | C2: 4130 | D2: 4682 | E2: 5010 | F2: 6910 | G2: 9714 | H2: 11716 | I2: 10918 | J2: 16675 | K2: 26914 | L2: 26974 | M2: 60922 | N2: 130497
B3: Growth rate | C3: 0 | D3: =(D2/C2)-1 -> 0.13365617 | E3: =(E2/D2)-1 -> 0.070055532 | F3: =(F2/E2)-1 -> 0.37924152 | G3: =(G2/F2)-1 -> 0.40578871 | H3: =(H2/G2)-1 -> 0.2060943 | I3: =(I2/H2)-1 -> -0.068111984 | J3: =(J2/I2)-1 -> 0.52729438 | K3: =(K2/J2)-1 -> 0.61403298 | ... N3: =(N2/M2)-1 -> 1.1420341
B4: Gross profit | C4: 2268 | D4: 2599 | E4: 2811 | F4: 4063 | G4: 5822 | H4: 7171 | I4: 6768 | J4: 10396 | K4: 17475 | L4: 15356 | M4: 44301 | N4: 97858
B5: Growth rate | C5: 0 | D5: =(D4/C4)-1 -> 0.14594356 | E5: =(E4/D4)-1 -> 0.081569835 | F5: =(F4/E4)-1 -> 0.4453931 | G5: =(G4/F4)-1 -> 0.43293133 | H5: =(H4/G4)-1 -> 0.23170732 | I5: =(I4/H4)-1 -> -0.056198578 | J5: =(J4/I4)-1 -> 0.53605201 | K5: =(K4/J4)-1 -> 0.68093497 | ... N5: =(N4/M4)-1 -> 1.2089343
B6: R&D | C6: 1336 | D6: 1360 | E6: 1331 | F6: 1463 | G6: 1797 | H6: 23.76 | I6: 2829 | J6: 3924 | K6: 5268 | L6: 7339 | M6: 8675 | N6: 12914
B7: Growth rate | C7: 0 | D7: =(D6/C6)-1 -> 0.017964072 | E7: =(E6/D6)-1 -> -0.021323529 | F7: =(F6/E6)-1 -> 0.099173554 | G7: =(G6/F6)-1 -> 0.22829802 | H7: =(H6/G6)-1 -> -0.98677796 | I7: =(I6/H6)-1 -> 118.06566 | J7: =(J6/I6)-1 -> 0.38706257 | K7: =(K6/J6)-1 -> 0.34250765 | ... N7: =(N6/M6)-1 -> 0.48864553
B8: CAPEX | C8: -255 | D8: -122 | E8: -86 | F8: -176 | G8: -593 | H8: -600 | I8: -489 | J8: -1128 | K8: -976 | L8: -1833 | M8: -1069 | N8: -3236
B9: Growth rate | C9: 0 | D9: =(D8/C8)-1 -> -0.52156863 | E9: =(E8/D8)-1 -> -0.29508197 | F9: =(F8/E8)-1 -> 1.0465116 | G9: =(G8/F8)-1 -> 2.3693182 | H9: =(H8/G8)-1 -> 0.011804384 | I9: =(I8/H8)-1 -> -0.185 | J9: =(J8/I8)-1 -> 1.3067485 | K9: =(K8/J8)-1 -> -0.13475177 | ... N9: =(N8/M8)-1 -> 2.0271282
C12: 2025 | D12: 2024 | E12: 2023
B13: Data Center | C13: 115186 | D13: 47525 | E13: 15005
B14: Compute | C14: 102196 | D14: 38950 | E14: 11317
B15: Networking | C15: 12990 | D15: 8575 | E15: 3688
B16: Gaming | C16: 11350 | D16: 10447 | E16: 9067
B17: Professional Visualization | C17: 1878 | D17: 1553 | E17: 1544
B18: Automotive | C18: 1694 | D18: 1091 | E18: 903
B19: OEM and Other | C19: 389 | D19: 306 | E19: 455
B20: Total revenue | C20: 130497 | D20: 60922 | E20: 26974
C23: 2025 | D23: 2024 | E23: 2023
B24: United States | C24: 61257 | D24: 26966 | E24: 8292
B25: Singapore | C25: 23684 | D25: 6831 | E25: 2288
B26: Taiwan | C26: 20573 | D26: 13405 | E26: 6986
B27: China (including Hong Kong) | C27: 17108 | D27: 10306 | E27: 5785
B28: Other | C28: 7875 | D28: 3414 | E28: 3623
B29: Total revenue | C29: 130497 | D29: 60922 | E29: 26974

Sheet 11_DA
A1: D&A
A3: Average Useful life (years): | B3: 5 | M3: 10-K notes estimated useful lives
M4: Years | N4: 2 | O4: 3 | P4: 4 | Q4: 5 | R4: 6 | S4: 7
A5: D&A Forecasting | B5: Projected
B6: 2026F | C6: 2027F | D6: 2028F | E6: 2029F | F6: 2030F
A7: For CaPex in
A8: 2022 | B8: =D26/$B$3 -> 195.2 | C8: =B8 -> 195.2
A9: 2023 | B9: =E26/$B$3 -> 366.6 | C9: =B9 -> 366.6 | D9: =C9 -> 366.6
A10: 2024 | B10: =F26/B3 -> 213.8 | C10: =B10 -> 213.8 | D10: =C10 -> 213.8 | E10: =D10 -> 213.8
A11: 2025 | B11: =G26/B3 -> 647.2 | C11: =B11 -> 647.2 | D11: =C11 -> 647.2 | E11: =D11 -> 647.2
A12: 2026 | B12: =H26/B3 -> 1269.3976 | C12: =B12 -> 1269.3976 | D12: =C12 -> 1269.3976 | E12: =D12 -> 1269.3976 | F12: =E12 -> 1269.3976
A13: 2027 | C13: =I26/B3 -> 1888.7762 | D13: =C13 -> 1888.7762 | E13: =D13 -> 1888.7762 | F13: =E13 -> 1888.7762
A14: 2028 | D14: =J26/B3 -> 2451.6311 | E14: =D14 -> 2451.6311 | F14: =E14 -> 2451.6311
A15: 2029 | E15: =K26/B3 -> 2575.8631 | F15: =E15 -> 2575.8631
A16: 2030 | F16: =L26/B3 -> 2921.357
A17: Total Depreciation | B17: =SUM(B8:B16) -> 2692.1976 | C17: =SUM(C8:C16) -> 4580.9738 | D17: =SUM(D8:D16) -> 6837.4049 | E17: =SUM(E8:E16) -> 9046.668 | F17: =SUM(F8:F16) -> 11107.025
A18: Amortization | B18: 354 | C18: 236 | D18: 84 | E18: 31 | F18: 10
A19: Totat D&A | B19: =SUM(B17:B18) -> 3046.1976 | C19: =SUM(C17:C18) -> 4816.9738 | D19: =SUM(D17:D18) -> 6921.4049 | E19: =SUM(E17:E18) -> 9077.668 | F19: =SUM(F17:F18) -> 11117.025
B24: Historical | H24: Projected
B25: 2020A | C25: 2021A | D25: 2022A | E25: 2023A | F25: 2024A | G25: 2025A | H25: 2026 F | I25: 2027 F | J25: 2028 F | K25: 2029 F | L25: 2030 F
A26: ='12_FixedAssets'!A6 -> CaPex | B26: ='12_FixedAssets'!C6 -> 489 | C26: ='12_FixedAssets'!D6 -> 1128 | D26: ='12_FixedAssets'!E6 -> 976 | E26: ='12_FixedAssets'!F6 -> 1833 | F26: ='12_FixedAssets'!G6 -> 1069 | G26: ='12_FixedAssets'!H6 -> 3236 | H26: ='12_FixedAssets'!I6 -> 6346.9878 | I26: ='12_FixedAssets'!J6 -> 9443.8812 | ... L26: ='12_FixedAssets'!M6 -> 14606.785
A27: ='12_FixedAssets'!A7 -> CaPex, % Revenue | B27: ='12_FixedAssets'!C7 -> 0.044788423 | C27: ='12_FixedAssets'!D7 -> 0.067646177 | D27: ='12_FixedAssets'!E7 -> 0.036263655 | E27: ='12_FixedAssets'!F7 -> 0.067954326 | F27: ='12_FixedAssets'!G7 -> 0.017547027 | G27: ='12_FixedAssets'!H7 -> 0.024797505 | H27: ='12_FixedAssets'!I7 -> 0.03 | I27: ='12_FixedAssets'!J7 -> 0.032 | ... L27: ='12_FixedAssets'!M7 -> 0.028
A29: ='12_FixedAssets'!J43 -> Future Amortization expenses 10-k
A30: ='12_FixedAssets'!J44 -> Fiscal Year | B30: ='12_FixedAssets'!K44 -> (in millions $)
A31: ='12_FixedAssets'!J45 -> 2026 | B31: ='12_FixedAssets'!K45 -> 354
A32: ='12_FixedAssets'!J46 -> 2027 | B32: ='12_FixedAssets'!K46 -> 236
A33: ='12_FixedAssets'!J47 -> 2028 | B33: ='12_FixedAssets'!K47 -> 84
A34: ='12_FixedAssets'!J48 -> 2029 | B34: ='12_FixedAssets'!K48 -> 31
A35: ='12_FixedAssets'!J49 -> 2030 | B35: ='12_FixedAssets'!K49 -> 10
A36: ='12_FixedAssets'!J50 -> 2031 and thereafter | B36: ='12_FixedAssets'!K50 -> 92
A37: ='12_FixedAssets'!J51 -> Total | B37: ='12_FixedAssets'!K51 -> 807

Sheet 12_FixedAssets
A1: Fixed assets model
A3: Long-term Asset Schedule | C3: Historical | I3: Projected
A4: $ in millions | C4: 2020 | D4: 2021 | E4: 2022 | F4: 2023 | G4: 2024 | H4: 2025 | I4: 2026F | J4: 2027F | K4: 2028F | L4: 2029F | M4: 2030F
A5: Revenue | C5: ='04a_Projection_IS'!B81 -> 10918 | D5: ='04a_Projection_IS'!C81 -> 16675 | E5: ='04a_Projection_IS'!D81 -> 26914 | F5: ='04a_Projection_IS'!E81 -> 26974 | G5: ='04a_Projection_IS'!F81 -> 60922 | H5: ='04a_Projection_IS'!G81 -> 130497 | I5: ='04a_Projection_IS'!H81 -> 211566.26 | J5: ='04a_Projection_IS'!I81 -> 295121.29 | ... M5: ='04a_Projection_IS'!L81 -> 521670.89
A6: CaPex | C6: =489 -> 489 | D6: 1128 | E6: 976 | F6: =-'03_Historical_CF'!B25 -> 1833 | G6: =-'03_Historical_CF'!C25 -> 1069 | H6: =-'03_Historical_CF'!D25 -> 3236 | I6: =I5*I7 -> 6346.9878 | J6: =J5*J7 -> 9443.8812 | K6: =K5*K7 -> 12258.155 | L6: =L5*L7 -> 12879.316 | M6: =M5*M7 -> 14606.785
A7: CaPex, % Revenue | C7: =C6/C5 -> 0.044788423 | D7: =D6/D5 -> 0.067646177 | E7: =E6/E5 -> 0.036263655 | F7: =F6/F5 -> 0.067954326 | G7: =G6/G5 -> 0.017547027 | H7: =H6/H5 -> 0.024797505 | I7: =B37 -> 0.03 | J7: =C37 -> 0.032 | K7: =D37 -> 0.033 | L7: =E37 -> 0.03 | M7: =F37 -> 0.028
A9: Property and Equipment Schedule
A10: Opening balance | C10: 0 | D10: 0 | E10: ='02_Historical_BS'!B11 -> 2149 | F10: ='02_Historical_BS'!C11 -> 2778 | G10: ='02_Historical_BS'!D11 -> 3807 | H10: ='02_Historical_BS'!E11 -> 3914 | I10: ='02_Historical_BS'!F11 -> 6283 | J10: =I12 -> 12629.988 | K10: =J12 -> 22073.869 | L10: =K12 -> 34332.024 | M10: =L12 -> 47211.34
A11: Add: CaPex | C11: 0 | D11: =D6 -> 1128 | E11: =E6 -> 976 | F11: =F6 -> 1833 | G11: =G6 -> 1069 | H11: =H6 -> 3236 | I11: =I6 -> 6346.9878 | J11: =J6 -> 9443.8812 | K11: =K6 -> 12258.155 | ... M11: =M6 -> 14606.785
A12: Total Fixed Assets | C12: 0 | D12: =SUM(D10:D11) -> 1128 | E12: =SUM(E10:E11) -> 3125 | F12: =SUM(F10:F11) -> 4611 | G12: =SUM(G10:G11) -> 4876 | H12: =SUM(H10:H11) -> 7150 | I12: =SUM(I10:I11) -> 12629.988 | J12: =SUM(J10:J11) -> 22073.869 | K12: =SUM(K10:K11) -> 34332.024 | ... M12: =SUM(M10:M11) -> 61818.125
A13: Less: Depreciation | C13: 0 | D13: =D15-D12 -> 1021 | E13: =E15-E12 -> -347 | F13: =F15-F12 -> -804 | G13: =G15-G12 -> -962 | H13: =H15-H12 -> -867 | I13: =-'11_DA'!B17 -> -2692.1976 | J13: =-'11_DA'!C17 -> -4580.9738 | K13: =-'11_DA'!D17 -> -6837.4049 | L13: =-'11_DA'!E17 -> -9046.668 | M13: =-'11_DA'!F17 -> -11107.025
A14: Depreciation % of Gross PP&E | C14: 0 | D14: 0 | E14: =-E13/E10 -> 0.16147045 | F14: =-F13/F10 -> 0.28941685 | G14: =-G13/G10 -> 0.25269241 | H14: =-H13/H10 -> 0.22151252 | I14: =B42 -> 0.22 | J14: =C42 -> 0.22 | K14: =D42 -> 0.22 | L14: =E42 -> 0.22 | M14: =F42 -> 0.22
A15: Closing Balance | C15: =D10 -> 0 | D15: 2149 | E15: 2778 | F15: 3807 | G15: 3914 | H15: 6283 | I15: =I12+I13 -> 9937.7902 | J15: =J12+J13 -> 17492.895 | K15: =K12+K13 -> 27494.62 | L15: =L12+L13 -> 38164.672 | M15: =M12+M13 -> 50711.1
A17: Fixed asset turnover ratio | D17: =D12/D5 -> 0.067646177 | E17: =E12/E5 -> 0.11611057 | F17: =F12/F5 -> 0.17094239 | G17: =G12/G5 -> 0.080036768 | H17: =H12/H5 -> 0.054790532 | I17: =I12/I5 -> 0.059697552 | J17: =J12/J5 -> 0.074795923 | K17: =K12/K5 -> 0.092424738 | ... M17: =M12/M5 -> 0.11850024
A19: ='03_Historical_CF'!A50 -> Accumulated Amortization | C19: ='03_Historical_CF'!B50 -> 25 | D19: ='03_Historical_CF'!C50 -> 612 | E19: ='03_Historical_CF'!D50 -> 563 | F19: ='03_Historical_CF'!E50 -> 699 | G19: ='03_Historical_CF'!F50 -> 614 | H19: ='03_Historical_CF'!G50 -> 593 | I19: =K45 -> 354 | J19: =K46 -> 236 | K19: =K47 -> 84 | L19: =K48 -> 31 | M19: =10 -> 10
A21: Other intangible asset schedule
A22: Opening balance | C22: 0 | D22: =C27 -> 49 | E22: =D27 -> 2737 | F22: =E27 -> 2339 | G22: =F27 -> 1676 | H22: =G27 -> 1112 | I22: =H27 -> 807 | J22: =I27 -> 1214.6385 | K22: =J27 -> 2111.9043 | ... M22: =L27 -> 5013.4008
A23: Add: intangible Purchases | C23: 0 | D23: =D27-D22+D26 -> 3300 | E23: =E27-E22+E26 -> 165 | F23: =F27-F22+F26 -> 36 | G23: =G27-G22+G26 -> 50 | H23: =H27-H22+H26 -> 288 | I23: =I24*I6 -> 761.63854 | J23: =J24*J6 -> 1133.2657 | K23: =K24*K6 -> 1470.9787 | L23: =L24*L6 -> 1545.5179 | M23: =M24*M6 -> 1752.8142
A24: intangible Purchases % CaPex | D24: =D23/D6 -> 2.9255319 | E24: =E23/E6 -> 0.16905738 | F24: =F23/F6 -> 0.019639935 | G24: =G23/G6 -> 0.046772685 | H24: =H23/H6 -> 0.088998764 | I24: =B47 -> 0.12 | J24: =C47 -> 0.12 | K24: =D47 -> 0.12 | L24: =E47 -> 0.12 | M24: =F47 -> 0.12
A25: Total Fixed assets | C25: 0 | D25: =D27+D26 -> 3349 | E25: =E27+E26 -> 2902 | F25: =F27+F26 -> 2375 | G25: =G27+G26 -> 1726 | H25: =H27+H26 -> 1400 | I25: =I22+I23 -> 1568.6385 | J25: =J22+J23 -> 2347.9043 | K25: =K22+K23 -> 3582.8829 | L25: =L22+L23 -> 5044.4008 | M25: =M22+M23 -> 6766.215
A26: Less: Amortization | C26: 0 | D26: =D19 -> 612 | E26: =E19 -> 563 | F26: =F19 -> 699 | G26: =G19 -> 614 | H26: =H19 -> 593 | I26: =I19 -> 354 | J26: =J19 -> 236 | K26: =K19 -> 84 | L26: =L19 -> 31 | M26: =+K49 -> 10
A27: Closing balance | C27: 49 | D27: ='02_Historical_BS'!B14 -> 2737 | E27: ='02_Historical_BS'!C14 -> 2339 | F27: ='02_Historical_BS'!D14 -> 1676 | G27: ='02_Historical_BS'!E14 -> 1112 | H27: ='02_Historical_BS'!F14 -> 807 | I27: =I25-I26 -> 1214.6385 | J27: =J25-J26 -> 2111.9043 | K27: =K25-K26 -> 3498.8829 | L27: =L25-L26 -> 5013.4008 | M27: =M25-M26 -> 6756.215
A34: Assumptions :
B35: 2026 F | C35: 2027 F | D35: 2028 F | E35: 2029 F | F35: 2030 F
A36: CapEx % Rev
A37: Base case | B37: 0.03 | C37: 0.032 | D37: 0.033 | E37: 0.03 | F37: 0.028
A38: Upside case | B38: 0.035 | C38: 0.04 | D38: 0.045 | E38: 0.035 | F38: 0.045
A39: Downside case | B39: 0.02 | C39: 0.022 | D39: 0.023 | E39: 0.02 | F39: 0.025
A41: Depreciation % PP&E
A42: Base case | B42: 0.22 | C42: 0.22 | D42: 0.22 | E42: 0.22 | F42: 0.22
A43: Upside case | B43: =B42+3% -> 0.25 | C43: =C42+3% -> 0.25 | D43: =D42+3% -> 0.25 | E43: =E42+3% -> 0.25 | F43: =F42+3% -> 0.25 | J43: Future Amortization expenses 10-k
A44: Downside case | B44: =B42-3% -> 0.19 | C44: =C42-3% -> 0.19 | D44: =D42-3% -> 0.19 | E44: =E42-3% -> 0.19 | F44: =F42-3% -> 0.19 | J44: Fiscal Year | K44: (in millions $)
J45: 2026 | K45: 354
A46: intangible Purchases % CaPex | J46: 2027 | K46: 236
A47: Base case | B47: 0.12 | C47: 0.12 | D47: 0.12 | E47: 0.12 | F47: 0.12 | J47: 2028 | K47: 84
A48: Upside case | B48: 0.15 | C48: 0.15 | D48: 0.15 | E48: 0.15 | F48: 0.15 | J48: 2029 | K48: 31
A49: Downside case | B49: 0.08 | C49: 0.08 | D49: 0.08 | E49: 0.08 | F49: 0.08 | J49: 2030 | K49: 10
J50: 2031 and thereafter | K50: 92
J51: Total | K51: =SUM(K45:K50) -> 807

Sheet 13_DebtSchedule
A1: Debt Schedule
A3: Debt Schedule | D3: Historical | I3: Projected
A4: $ in millions | D4: 2021 | E4: 2022 | F4: 2023 | G4: 2024 | H4: 2025 | I4: 2026F | J4: 2027F | K4: 2028F | L4: 2029F | M4: 2030F
A6: Opening balance | D6: =C8 -> 10946 | E6: =D8 -> 6963 | F6: =E8 -> 10946 | G6: =F8 -> 10953 | H6: =G8 -> 9709 | I6: =H8 -> 8463 | J6: =I8 -> 7463 | K6: =J8 -> 7463 | ... M6: =L8 -> 6213
A7: Add/Less: Debt incurred (repaid) | D7: =D8-D6 -> -3983 | E7: =E8-E6 -> 3983 | F7: =F8-F6 -> 7 | G7: =G8-G6 -> -1244 | H7: =H8-H6 -> -1246 | I7: =-B18 -> -1000 | J7: =-C18 -> 0 | K7: =-D18 -> -1250 | L7: =-E18 -> 0 | M7: =-F18 -> -1500
A8: Closing Balance | C8: 10946 | D8: ='02_Historical_BS'!B20+'02_Historical_BS'!B26 -> 6963 | E8: ='02_Historical_BS'!C20+'02_Historical_BS'!C26 -> 10946 | F8: ='02_Historical_BS'!D20+'02_Historical_BS'!D26 -> 10953 | G8: ='02_Historical_BS'!E20+'02_Historical_BS'!E26 -> 9709 | H8: ='02_Historical_BS'!F20+'02_Historical_BS'!F26 -> 8463 | I8: =I6+I7 -> 7463 | J8: =J6+J7 -> 7463 | K8: =K6+K7 -> 6213 | L8: =L6+L7 -> 6213 | M8: =M6+M7 -> 4713
A9: Average Debt Balance | D9: =AVERAGE(D6,D8) -> 8954.5 | E9: =AVERAGE(E6,E8) -> 8954.5 | F9: =AVERAGE(F6,F8) -> 10949.5 | G9: =AVERAGE(G6,G8) -> 10331 | H9: =AVERAGE(H6,H8) -> 9086 | I9: =AVERAGE(I6,I8) -> 7963 | J9: =AVERAGE(J6,J8) -> 7463 | K9: =AVERAGE(K6,K8) -> 6838 | ... M9: =AVERAGE(M6,M8) -> 5463
A11: Interest Expenses | D11: ='01_Historical_IS'!B16 -> -52 | E11: ='01_Historical_IS'!C16 -> -184 | F11: ='01_Historical_IS'!D16 -> -236 | G11: ='01_Historical_IS'!E16 -> -262 | H11: ='01_Historical_IS'!F16 -> -257 | I11: =-I9*I13 -> -263.5753 | J11: =-J9*J13 -> -247.0253 | K11: =-K9*K13 -> -112.1432 | L11: =-L9*L13 -> -101.8932 | M11: =-M9*M13 -> -160.0659
A12: Net Interest Expenses
A13: Interest rate (pre tax) | D13: =-D11/D9 -> 0.0058071361 | E13: =-E11/E9 -> 0.020548328 | F13: =-F11/F9 -> 0.021553496 | G13: =-G11/G9 -> 0.025360565 | H13: =-H11/H9 -> 0.028285274 | I13: =B25 -> 0.0331 | J13: =C25 -> 0.0331 | K13: =D25 -> 0.0164 | L13: =E25 -> 0.0164 | M13: =F25 -> 0.0293
A16: Assumptions Net debt flow ( through note 11-debt 10-k 2025 )
A17: $ in millions | B17: 2026 F | C17: 2027 F | D17: 2028 F | E17: 2029 F | F17: 2030 F
A18: Base case | B18: 1000 | C18: 0 | D18: 1250 | E18: 0 | F18: 1500
A23: Assumptions Interest rate (pre tax) ( through note 11-debt 10-k 2025)
A24: $ in millions | B24: 2026 F | C24: 2027 F | D24: 2028 F | E24: 2029 F | F24: 2030 F
A25: Base case | B25: 0.0331 | C25: 0.0331 | D25: 0.0164 | E25: 0.0164 | F25: 0.0293
A26: Upside case | B26: 0.0331 | C26: 0.028 | D26: 0.0164 | E26: 0.012 | F26: 0.0293
A27: Downside case | B27: 0.0331 | C27: 0.035 | D27: 0.0164 | E27: 0.026 | F27: 0.0293

Sheet 14_Beta
A3: S&P 500 2 years Daily return | F3: NVIDIA 2 years Daily return
A4: Date | B4: Price | C4: Return | F4: Date | G4: Price | H4: Return | K4: Beta | L4: =_xlfn.COVARIANCE.S(H6:H507,C6:C507)/_xlfn.VAR.S(C6:C507) -> 2.1534719
A5: 45947 | B5: 6664.01 | F5: 45947 | G5: 183.22
A6: 45946 | B6: 6629.07 | C6: =B6/B5-1 -> -0.0052430894 | F6: 45946 | G6: 181.81 | H6: =G6/G5-1 -> -0.0076956664 | K6: Beta Drifting ( Blume Method)
A7: 45945 | B7: 6671.06 | C7: =B7/B6-1 -> 0.0063342218 | F7: 45945 | G7: 179.83 | H7: =G7/G6-1 -> -0.01089049 | K7: Levered raw beta | L7: =L4 -> 2.1534719
A8: 45944 | B8: 6644.31 | C8: =B8/B7-1 -> -0.0040098575 | F8: 45944 | G8: 180.03 | H8: =G8/G7-1 -> 0.0011121615 | K8: Raw beta weight | L8: 0.67
A9: 45943 | B9: 6654.72 | C9: =B9/B8-1 -> 0.0015667541 | F9: 45943 | G9: 188.32 | H9: =G9/G8-1 -> 0.046047881
A10: 45940 | B10: 6552.51 | C10: =B10/B9-1 -> -0.015359023 | F10: 45940 | G10: 183.16 | H10: =G10/G9-1 -> -0.02740017 | K10: Market beta | L10: 1
A11: 45939 | B11: 6735.11 | C11: =B11/B10-1 -> 0.027867184 | F11: 45939 | G11: 192.57 | H11: =G11/G10-1 -> 0.051375846 | K11: Market beta weight | L11: 0.33
A12: 45938 | B12: 6753.72 | C12: =B12/B11-1 -> 0.0027631323 | F12: 45938 | G12: 189.11 | H12: =G12/G11-1 -> -0.017967492
A13: 45937 | B13: 6714.59 | C13: =B13/B12-1 -> -0.005793844 | F13: 45937 | G13: 185.04 | H13: =G13/G12-1 -> -0.021521866 | K13: Adjusted Beta | L13: =(L7*L8)+(L10*L11) -> 1.7728261
A14: 45936 | B14: 6740.28 | C14: =B14/B13-1 -> 0.0038259968 | F14: 45936 | G14: 185.54 | H14: =G14/G13-1 -> 0.0027021185
A15: 45933 | B15: 6715.79 | C15: =B15/B14-1 -> -0.0036333802 | F15: 45933 | G15: 187.62 | H15: =G15/G14-1 -> 0.011210521
A16: 45932 | B16: 6715.35 | C16: =B16/B15-1 -> -6.5517236e-05 | F16: 45932 | G16: 188.89 | H16: =G16/G15-1 -> 0.0067690012
A17: 45931 | B17: 6711.2 | C17: =B17/B16-1 -> -0.00061798715 | F17: 45931 | G17: 187.24 | H17: =G17/G16-1 -> -0.0087352427 | K17: SUMMARY OUTPUT
A18: 45930 | B18: 6688.46 | C18: =B18/B17-1 -> -0.0033883657 | F18: 45930 | G18: 186.58 | H18: =G18/G17-1 -> -0.0035248878
A19: 45929 | B19: 6661.21 | C19: =B19/B18-1 -> -0.0040741815 | F19: 45929 | G19: 181.85 | H19: =G19/G18-1 -> -0.025351056 | K19: Regression Statistics
A20: 45926 | B20: 6643.7 | C20: =B20/B19-1 -> -0.0026286516 | F20: 45926 | G20: 178.19 | H20: =G20/G19-1 -> -0.020126478 | K20: Multiple R | L20: 0.67490423
A21: 45925 | B21: 6604.72 | C21: =B21/B20-1 -> -0.0058672125 | F21: 45925 | G21: 177.69 | H21: =G21/G20-1 -> -0.0028059936 | K21: R Square | L21: 0.45549572
A22: 45924 | B22: 6637.97 | C22: =B22/B21-1 -> 0.0050342785 | F22: 45924 | G22: 176.97 | H22: =G22/G21-1 -> -0.0040520007 | K22: Adjusted R Square | L22: 0.45440671
A23: 45923 | B23: 6656.92 | C23: =B23/B22-1 -> 0.0028547884 | F23: 45923 | G23: 178.43 | H23: =G23/G22-1 -> 0.0082499859 | K23: Standard Error | L23: 0.0074014299
A24: 45922 | B24: 6693.75 | C24: =B24/B23-1 -> 0.0055325886 | F24: 45922 | G24: 183.61 | H24: =G24/G23-1 -> 0.029030993 | K24: Observations | L24: 502
A25: 45919 | B25: 6664.36 | C25: =B25/B24-1 -> -0.0043906629 | F25: 45919 | G25: 176.67 | H25: =G25/G24-1 -> -0.037797506
A26: 45918 | B26: 6631.96 | C26: =B26/B25-1 -> -0.0048616821 | F26: 45918 | G26: 176.24 | H26: =G26/G25-1 -> -0.0024339163 | K26: ANOVA
A27: 45917 | B27: 6600.35 | C27: =B27/B26-1 -> -0.0047663134 | F27: 45917 | G27: 170.29 | H27: =G27/G26-1 -> -0.033760781 | L27: df | M27: SS | N27: MS | O27: F | P27: Significance F
A28: 45916 | B28: 6606.76 | C28: =B28/B27-1 -> 0.00097116062 | F28: 45916 | G28: 174.88 | H28: =G28/G27-1 -> 0.02695402 | K28: Regression | L28: 1 | M28: 0.022913121 | N28: 0.022913121 | O28: 418.26642 | P28: 5.2758575e-68
A29: 45915 | B29: 6615.28 | C29: =B29/B28-1 -> 0.0012895882 | F29: 45915 | G29: 177.75 | H29: =G29/G28-1 -> 0.016411253 | K29: Residual | L29: 500 | M29: 0.027390582 | N29: 5.4781164e-05
A30: 45912 | B30: 6584.29 | C30: =B30/B29-1 -> -0.004684609 | F30: 45912 | G30: 177.82 | H30: =G30/G29-1 -> 0.00039381153 | K30: Total | L30: 501 | M30: 0.050303703
A31: 45911 | B31: 6587.47 | C31: =B31/B30-1 -> 0.00048296779 | F31: 45911 | G31: 177.17 | H31: =G31/G30-1 -> -0.0036553818
A32: 45910 | B32: 6532.04 | C32: =B32/B31-1 -> -0.0084144596 | F32: 45910 | G32: 177.33 | H32: =G32/G31-1 -> 0.00090308743 | L32: Coefficients | M32: Standard Error | N32: t Stat | O32: P-value | P32: Lower 95% | Q32: Upper 95% | R32: Lower 95.0% | S32: Upper 95.0%
A33: 45909 | B33: 6512.61 | C33: =B33/B32-1 -> -0.0029745684 | F33: 45909 | G33: 170.76 | H33: =G33/G32-1 -> -0.037049569 | K33: Intercept | L33: -0.00029513189 | M33: 0.00033122167 | N33: -0.89104042 | O33: 0.37333605 | P33: -0.00094588967 | Q33: 0.00035562589 | R33: -0.00094588967 | S33: 0.00035562589
A34: 45908 | B34: 6495.15 | C34: =B34/B33-1 -> -0.0026809528 | F34: 45908 | G34: 168.31 | H34: =G34/G33-1 -> -0.014347622 | K34: X Variable 1 | L34: 0.21151691 | M34: 0.010342335 | N34: 20.451563 | O34: 5.2758575e-68 | P34: 0.19119712 | Q34: 0.2318367 | R34: 0.19119712 | S34: 0.2318367
A35: 45905 | B35: 6481.5 | C35: =B35/B34-1 -> -0.0021015681 | F35: 45905 | G35: 167.02 | H35: =G35/G34-1 -> -0.0076644287
A36: 45904 | B36: 6502.08 | C36: =B36/B35-1 -> 0.0031751909 | F36: 45904 | G36: 171.66 | H36: =G36/G35-1 -> 0.027781104
A37: 45903 | B37: 6448.26 | C37: =B37/B36-1 -> -0.0082773512 | F37: 45903 | G37: 170.62 | H37: =G37/G36-1 -> -0.0060584877
A38: 45902 | B38: 6415.54 | C38: =B38/B37-1 -> -0.0050742371 | F38: 45902 | G38: 170.78 | H38: =G38/G37-1 -> 0.00093775642
A39: 45898 | B39: 6460.26 | C39: =B39/B38-1 -> 0.0069705746 | F39: 45898 | G39: 174.18 | H39: =G39/G38-1 -> 0.019908654
A40: 45897 | B40: 6501.86 | C40: =B40/B39-1 -> 0.0064393693 | F40: 45897 | G40: 180.17 | H40: =G40/G39-1 -> 0.034389712
A41: 45896 | B41: 6481.4 | C41: =B41/B40-1 -> -0.0031467918 | F41: 45896 | G41: 181.6 | H41: =G41/G40-1 -> 0.0079369484
A42: 45895 | B42: 6465.94 | C42: =B42/B41-1 -> -0.0023852871 | F42: 45895 | G42: 181.77 | H42: =G42/G41-1 -> 0.00093612335
A43: 45894 | B43: 6439.32 | C43: =B43/B42-1 -> -0.0041169575 | F43: 45894 | G43: 179.81 | H43: =G43/G42-1 -> -0.010782857
A44: 45891 | B44: 6466.91 | C44: =B44/B43-1 -> 0.0042846139 | F44: 45891 | G44: 177.99 | H44: =G44/G43-1 -> -0.010121795
A45: 45890 | B45: 6370.17 | C45: =B45/B44-1 -> -0.014959231 | F45: 45890 | G45: 174.98 | H45: =G45/G44-1 -> -0.016911062
A46: 45889 | B46: 6395.78 | C46: =B46/B45-1 -> 0.0040203009 | F46: 45889 | G46: 175.4 | H46: =G46/G45-1 -> 0.0024002743
... A507: 45216 | B507: 4373.2 | C507: =B507/B506-1 -> 0.013581792 | F507: 45216 | G507: 43.94 | H507: =G507/G506-1 -> 0.041232227

Sheet 15_WACC
A1: WACC
B3: WACC = % of equity * Cost of equity + % of debt * Cost of debt * (1 - Corporate tax rate)
B4: Cost of equity = Risk-free return+ company Beta * (Market Risk Premium - Risk-free return)
B6: WACC (October 17, 2025) | M6: Cost of Debt | P6: 2025
B7: Market cap | F7: 4452000
B8: % OF Equity | F8: =F7/(F14+F7) -> 0.99810266 | M8: Pre-Tax Cost of Debt | P8: ='13_DebtSchedule'!H13 -> 0.028285274
B9: Cost of equity | F9: =F10+F11*F12 -> 0.12934131 | M9: Effective Tax Rate | P9: =F17 -> 0.13264942
B10: Risk Free rate | F10: 0.0407 | M10: Post Tax Cost of Debt | P10: =P8*(1-P9) -> 0.024533249
B11: Adjusted Beta | F11: ='14_Beta'!L13 -> 1.7728261
B12: Market Risk Premium | F12: 0.05
B14: Debt | F14: ='02_Historical_BS'!F20+'02_Historical_BS'!F26 -> 8463
B15: % of Debt | F15: =F14/(F7+F14) -> 0.0018973367
B16: =M8 -> Pre-Tax Cost of Debt | F16: =P8 -> 0.028285274
B17: Tax Rate | F17: ='04a_Projection_IS'!F71 -> 0.13264942
B19: WACC | F19: =F8*F9+F15*F16*(1-F17) -> 0.12914245

Sheet 16_MarketData
A2: 52 Week High/ Low
A3: 52 Week High | B3: =MAX(B9:B268) -> 192.57
A4: 52 Week Low | B4: =MIN(B9:B268) -> 94.31
A8: Date | B8: Close/Last | C8: Open | D8: High | E8: Low | F8: Volume
A9: 45947 | B9: 183.22 | C9: 180.18 | D9: 184.1 | E9: 179.75 | F9: 173135200
A10: 45946 | B10: 181.81 | C10: 182.23 | D10: 183.28 | E10: 179.77 | F10: 179723300
A11: 45945 | B11: 179.83 | C11: 184.8 | D11: 184.87 | E11: 177.29 | F11: 214450500
A12: 45944 | B12: 180.03 | C12: 184.77 | D12: 184.8 | E12: 179.7 | F12: 205641400
A13: 45943 | B13: 188.32 | C13: 187.965 | D13: 190.1099 | E13: 185.96 | F13: 153482800
A14: 45940 | B14: 183.16 | C14: 193.505 | D14: 195.62 | E14: 182.05 | F14: 268774400
A15: 45939 | B15: 192.57 | C15: 192.225 | D15: 195.3 | E15: 191.06 | F15: 182997200
A16: 45938 | B16: 189.11 | C16: 186.57 | D16: 189.6 | E16: 186.54 | F16: 130168900
A17: 45937 | B17: 185.04 | C17: 186.23 | D17: 189.06 | E17: 184 | F17: 140088000
A18: 45936 | B18: 185.54 | C18: 185.5 | D18: 187.23 | E18: 183.33 | F18: 157678100
A19: 45933 | B19: 187.62 | C19: 189.19 | D19: 190.36 | E19: 185.38 | F19: 137596900
A20: 45932 | B20: 188.89 | C20: 189.6 | D20: 191.05 | E20: 188.06 | F20: 136805800
... A257: 45586 | B257: 143.71 | C257: 138.13 | D257: 143.71 | E257: 138 | F257: 264554500
A258: 18/10/2024 | B258: 138 | C258: 138.66 | D258: 138.9 | E258: 137.28 | F258: 176,09M
A259: 17/10/2024 | B259: 136.39 | C259: 139.34 | D259: 140.89 | E259: 136.87 | F259: 306,44M
A260: 16/10/2024 | B260: 135.72 | C260: 133.98 | D260: 136.62 | E260: 131.58 | F260: 264,88M
A261: 15/10/2024 | B261: 131.6 | C261: 137.87 | D261: 138.57 | E261: 128.74 | F261: 377,83M
A262: 14/10/2024 | B262: 138.07 | C262: 136.47 | D262: 139.6 | E262: 136.3 | F262: 232,35M
A263: 45606 | B263: 134.8 | C263: 134.01 | D263: 135.78 | E263: 133.66 | F263: 170,21M
A264: 45575 | B264: 134.81 | C264: 131.91 | D264: 135 | E264: 131 | F264: 242,31M
A265: 45545 | B265: 132.65 | C265: 134.11 | D265: 134.52 | E265: 131.38 | F265: 246,19M
A266: 45514 | B266: 132.89 | C266: 130.26 | D266: 133.48 | E266: 129.42 | F266: 285,72M
A267: 45483 | B267: 127.72 | C267: 124.99 | D267: 130.64 | E267: 124.95 | F267: 346,25M
A268: 45392 | B268: 124.92 | C268: 124.94 | D268: 125.04 | E268: 121.83 | F268: 244,47M

Sheet 17_ComparableAnalysis
A1: Comparable Companies Analysis for NVIDIA
B3: Market Data | I3: Financials | M3: Valuation
A4: Company | B4: Share Price | C4: EPS | D4: Shares Outstanding | E4: Market Capit-alization | F4: Net Debt | G4: Enterprise Value | I4: Revenue | J4: EBITDA | K4: Net Income | M4: EV/Revenue | N4: EV/EBITDA | O4: P/E
A6: NVIDIA | B6: 183.22 | C6: 3.51 | D6: 24.3 | E6: =B6*D6 -> 4452.246 | F6: -32.94 | G6: 4406.05 | I6: 165.22 | J6: 98.28 | K6: 86.6 | M6: =G6/I6 -> 26.667776 | N6: =G6/J6 -> 44.831604 | O6: =E6/K6 -> 51.411617
A7: AMD | B7: 233.08 | C7: 1.73 | E7: 378.25 | G7: 376.27 | I7: 29.6 | J7: 5.51 | K7: 2.83 | M7: =G7/I7 -> 12.711824 | N7: =G7/J7 -> 68.288566 | O7: =E7/K7 -> 133.65724
A8: Intel | B8: 37.01 | C8: -4.73 | E8: 176.06 | G8: 205.15 | I8: 53.07 | J8: 9.2 | K8: -20.5 | M8: =G8/I8 -> 3.8656491 | N8: =G8/J8 -> 22.298913 | O8: =E8/K8 -> -8.5882927
A9: Qualcomm (QCOM) | B9: 163.45 | C9: 10.36 | E9: 175.44 | G9: 180.22 | I9: 43.26 | J9: 13.87 | K9: 11.58 | M9: =G9/I9 -> 4.1659732 | N9: =G9/J9 -> 12.993511 | O9: =E9/K9 -> 15.150259
A10: Broadcom (AVGO) | B10: 349.33 | C10: 3.92 | E10: 1649.66 | G10: 1703.17 | I10: 59.93 | J10: 32.75 | K10: 18.93 | M10: =G10/I10 -> 28.419323 | N10: =G10/J10 -> 52.005191 | O10: =E10/K10 -> 87.145272
A11: TSMC | B11: 295.08 | C11: 9.94 | E11: 1225.79 | G11: 1168.51 | I11: 119.13 | J11: 81.75 | K11: 51.57 | M11: =G11/I11 -> 9.8086964 | N11: =G11/J11 -> 14.2937 | O11: =E11/K11 -> 23.76944
A13: High | M13: =MAX(M6:M11) -> 28.419323 | N13: =MAX(N6:N11) -> 68.288566 | O13: =MAX(O6:O11) -> 133.65724
A14: 75th Percentile | M14: =_xlfn.QUARTILE.EXC(M6:M11,3) -> 27.105663 | N14: =_xlfn.QUARTILE.EXC(N6:N11,3) -> 56.076035 | O14: =_xlfn.QUARTILE.EXC(O6:O11,3) -> 98.773265
A15: Average | M15: =AVERAGE(M6:M11) -> 14.273207 | N15: =AVERAGE(N6:N11) -> 35.785248 | O15: =AVERAGE(O6:O11) -> 50.424256
A16: Median | M16: =MEDIAN(M6:M11) -> 11.26026 | N16: =MEDIAN(N6:N11) -> 33.565258 | O16: =MEDIAN(O6:O11) -> 37.590528
A17: 25th Percentile | M17: =_xlfn.QUARTILE.EXC(M6:M11,1) -> 4.0908922 | N17: =_xlfn.QUARTILE.EXC(N6:N11,1) -> 13.968653 | O17: =_xlfn.QUARTILE.EXC(O6:O11,1) -> 9.2156211
A18: Low | M18: =MIN(M6:M11) -> 3.8656491 | N18: =MIN(N6:N11) -> 12.993511 | O18: =MIN(O6:O11) -> -8.5882927
A20: NVIDIA Valuation | M20: EV/Revenue | N20: EV/EBITDA | O20: P/E
A21: Implied Enterprise Value | M21: =I6*M16 -> 1860.4202 | N21: =J6*N16 -> 3298.7936 | O21: =O23+O22 -> 3222.3997
A22: Net Debt | M22: =F6 -> -32.94 | N22: =M22 -> -32.94 | O22: =N22 -> -32.94
A23: Implied Market Value | M23: =M21-M22 -> 1893.3602 | N23: =N21-N22 -> 3331.7336 | O23: =K6*O16 -> 3255.3397
A24: Shares Outstanding | M24: =D6 -> 24.3 | N24: =M24 -> 24.3 | O24: =N24 -> 24.3
A25: Implied Value Per Share | M25: =M23/M24 -> 77.916058 | N25: =N23/N24 -> 137.10838 | O25: =O23/O24 -> 133.9646
M26: =IF(M25>$B$6,"Undervalued","Overvalued") -> Overvalued | N26: =IF(N25>$B$6,"Undervalued","Overvalued") -> Overvalued | O26: =IF(O25>$B$6,"Undervalued","Overvalued") -> Overvalued

Sheet 98_Notes
A1: NVIDIA Corporation — Financial Model Notes
A2: Model metadata, version history, and data source documentation
A4: Field | B4: Value | C4: Notes | D4: Last Updated
A5: Version | B5: 1.0 | C5: Initial release | D5: Oct 2025
A6: Author | B6: Aditya Gupta | C6: Primary model builder | D6: Oct 2025
A7: Valuation Date | B7: October 17, 2025 | C7: FY2025 close; market data Oct 2025 | D7: Oct 2025
A8: Data Sources | B8: NVIDIA 10-K FY2025 (SEC EDGAR), Yahoo Finance | C8: All historical data from 10-K filings | D8: Oct 2025
A9: Model Purpose | B9: L3 DCF Valuation — NVIDIA Corporation (NVDA) | C9: FCFF / Gordon Growth + Exit Multiple cross-check | D9: Oct 2025
A10: Currency | B10: USD millions (unless stated) | C10: All $ figures in $M | D10: Oct 2025
A11: Fiscal Year End | B11: January 31 | C11: NVIDIA FY ends late Jan/early Feb | D11: Oct 2025
A12: Forecast Period | B12: FY2026F – FY2030F (5 years) | C12: Base case only | D12: Oct 2025
A13: WACC | B13: 12.91% | C13: Blume-adjusted beta; CAPM | D13: Oct 2025
A14: Terminal Growth | B14: 4.00% | C14: Long-run GDP growth proxy | D14: Oct 2025
A17: Version History
A18: Version | B18: Date | C18: Change | D18: Author
A19: 1.0 | B19: Oct 2025 | C19: Initial model build — historical IS/BS/CF, WACC, Comps, DCF | D19: Aditya Gupta
A20: 1.0 | B20: Oct 2025 | C20: Step 2: added named ranges, FCFF validation, data_loader.py | D20: Aditya Gupta
A21: 1.0 | B21: Oct 2025 | C21: Step 3: fixed Other net assumption, filled notes, adjustments tab | D21: Aditya Gupta

Sheet 99_Validation
A1: NVIDIA Financial Model — Validation & Reconciliation Checks
A2: All checks should equal ZERO. Red = fail (tolerance > 0.01). Green = pass. Run Ctrl+Alt+F9 before reviewing.
A4: Check 1 — Balance Sheet Tie : Total Assets = Total Liabilities + Equity
A5: Metric | B5: 2021 | C5: 2022 | D5: 2023 | E5: 2024 | F5: 2025 | H5: Expected
A6: Total Assets ($M) | B6: ='02_Historical_BS'!B17 -> 28791 | C6: ='02_Historical_BS'!C17 -> 44187 | D6: ='02_Historical_BS'!D17 -> 41182 | E6: ='02_Historical_BS'!E17 -> 65728 | F6: ='02_Historical_BS'!F17 -> 111601
A7: Total Liab. + Equity ($M) | B7: ='02_Historical_BS'!B31+'02_Historical_BS'!B37 -> 28791 | C7: ='02_Historical_BS'!C31+'02_Historical_BS'!C37 -> 44187 | D7: ='02_Historical_BS'!D31+'02_Historical_BS'!D37 -> 41182 | E7: ='02_Historical_BS'!E31+'02_Historical_BS'!E37 -> 65728 | F7: ='02_Historical_BS'!F31+'02_Historical_BS'!F37 -> 111601
A8: Difference (should = 0) | B8: =B6-B7 -> 0 | C8: =C6-C7 -> 0 | D8: =D6-D7 -> 0 | E8: =E6-E7 -> 0 | F8: =F6-F7 -> 0 | H8: 0
A10: Check 2 — Cash Flow Reconciliation : CFO + CFI + CFF = Net Change in Cash
A11: Metric | B11: 2023 | C11: 2024 | D11: 2025 | F11: Expected
A12: CFO ($M) | B12: ='03_Historical_CF'!B19 -> 5641 | C12: ='03_Historical_CF'!C19 -> 28090 | D12: ='03_Historical_CF'!D19 -> 64089
A13: CFI ($M) | B13: ='03_Historical_CF'!B29 -> 7375 | C13: ='03_Historical_CF'!C29 -> -10566 | D13: ='03_Historical_CF'!D29 -> -20421
A14: CFF ($M) | B14: ='03_Historical_CF'!B38 -> -11617 | C14: ='03_Historical_CF'!C38 -> -13633 | D14: ='03_Historical_CF'!D38 -> -42359
A15: CFO+CFI+CFF (sum) | B15: =B12+B13+B14 -> 1399 | C15: =C12+C13+C14 -> 3891 | D15: =D12+D13+D14 -> 1309
A16: Net Change in Cash (per CF stmt) | B16: ='03_Historical_CF'!B39 -> 1399 | C16: ='03_Historical_CF'!C39 -> 3891 | D16: ='03_Historical_CF'!D39 -> 1309
A17: Difference (should = 0) | B17: =B15-B16 -> 0 | C17: =C15-C16 -> 0 | D17: =D15-D16 -> 0 | F17: 0
A19: Check 3 — Revenue Cross-Check : 01_Historical_IS vs 05a_FCFF
A20: Metric | B20: FY2023 | C20: FY2024 | D20: FY2025 | E20: Expected
A21: Revenue from IS ($M) | B21: ='01_Historical_IS'!E3 -> 26974 | C21: ='01_Historical_IS'!F3 -> 60922 | D21: ='01_Historical_IS'!G3 -> 130497
A22: Revenue from FCFF ($M) | B22: ='05a_FCFF'!C4 -> 26974 | C22: ='05a_FCFF'!D4 -> 60922 | D22: ='05a_FCFF'!E4 -> 130497
A23: Difference (should = 0) | B23: =B21-B22 -> 0 | C23: =C21-C22 -> 0 | D23: =D21-D22 -> 0 | E23: 0
A25: Check 4 — DCF Output Snapshot (model outputs at a glance)
A26: WACC | B26: ='05b_DCF'!C14 -> 0.12914245
A27: Terminal Growth Rate (g) | B27: ='05b_DCF'!C13 -> 0.04
A28: Sum of PV FCFs ($M) | B28: ='05b_DCF'!C11 -> 664084.81
A29: Terminal Value ($M) | B29: ='05b_DCF'!C15 -> 3593999.4
A30: PV of Terminal Value ($M) | B30: ='05b_DCF'!C16 -> 1958097.6
A31: Enterprise Value ($M) | B31: ='05b_DCF'!C17 -> 2622182.4
A32: Net Debt / (Cash) ($M) | B32: ='05b_DCF'!C18 -> -32940
A33: Equity Value ($M) | B33: ='05b_DCF'!C19 -> 2655122.4
A34: Diluted Shares (M) | B34: ='05b_DCF'!C20 -> 24300
A35: Implied Price — Gordon Growth | B35: ='05b_DCF'!C21 -> 109.26429
A36: Implied Price — Exit Multiple | B36: ='05b_DCF'!C51 -> 222.44867
A37: Market Price (Oct 17 2025) | B37: 183.22
A38: Upside / Downside (GG) | B38: ='05b_DCF'!C21/183.22-1 -> -0.40364428
A42: Check 5 — FCFF → Operating CF Reconciliation : Part A = arithmetic self-check | Part B = CFO boundary (informational)
A43: Part A: FCFF = NOPAT + D&A − CapEx − ΔNWC (all from 05a_FCFF). Part B: FCFF vs CFO+CapEx; residual = SBC + deferred tax + other non-cash — expected, not an error.
A45: Part A — Schedule Arithmetic Self-Check ($M)
A46: Metric | B46: FY2023 | C46: FY2024 | D46: FY2025 | E46: Target | F46: Status
A47: FCFF — from schedule | B47: 2650 | C47: 23329 | D47: 55932
A48: FCFF — recalculated (NOPAT+DA−CapEx−ΔNWC) | B48: 2650 | C48: 23329 | D48: 55932
A49: Difference (target = 0) | B49: 0 | C49: 0 | D49: 0 | E49: =0 -> 0 | F49: ✓ PASS
A51: Part B — CFO Boundary Check ($M) [Informational]
A52: Metric | B52: FY2023 | C52: FY2024 | D52: FY2025 | E52: Notes
A53: FCFF — 05a_FCFF schedule ($M) | B53: 2650 | C53: 23329 | D53: 55932
A54: CFO + CapEx (reported FCF from CF stmt, $M) | B54: 3808 | C54: 27021 | D54: 60853
A55: Residual (FCFF minus CFO+CapEx) | B55: -1158 | C55: -3692 | D55: -4921 | E55: = SBC + deferred tax + gains/other (see below)
A56: Explained: SBC + deferred tax + gains/losses + other ($M) | B56: -1936 | C56: -544 | D56: 1272 | E56: Remaining unexplained diff = NWC scope difference (operating vs total CF). Expected, not a model error.
A58: Check 5 Status: Part A — ✓ PASS | Part B — Informational | Overall — ✓ PASS
